Workbook

Sheet Data and Count
A1: Program Count by Year
A13: COUNTA of Duplicate Record
A14: COUNTA of Duplicate Record | B14: Year
A15: Duplicate Record | C15: 20 - 21 | D15: 21 - 22 | E15: 21 - 22, 20 - 21 | F15: 22 - 23 | G15: 23 - 24 | H15: Grand Total
A16: Duplicate | B16: 19 | C16: 11 | D16: 40 | E16: 1 | F16: 72 | G16: 8 | H16: 151
A17: Grand Total | B17: 19 | C17: 11 | D17: 40 | E17: 1 | F17: 72 | G17: 8 | H17: 151
A19: School Count

Sheet #Cheers4Careers Info Update For
A1: Timestamp | B1: Email Address | C1: Full Name | D1: Full Address with Zip Code (this will help us identify opportunities for you) | E1: Phone Number | F1: What is your current career interest? | G1: What school do you attend? (If you're not in school, put N/A) | H1: Do you have a job? If so, what company are you with and what do you do? (If you are not currently employed, put N/A) | I1: Are you looking for an internship or job? Tell us more. | J1: What #Cheers4Careers event are you attending? (Provide the date and location) | K1: Would you like to participate in the following (please select all that you're interested in) | L1: Please let us know if you have any food allergies or food restrictions
A2: 46105.769 | B2: ousmane@speakhire.org | C2: Ousmane Diallo | D2: 1011 East 53rd street Brooklyn NY 11234 | E2: 6467038461 | F2: Tech ( Mainframe) | G2: CUNY City Tech | H2: N/A | I2: Yes. | J2: March 24 Midtown | K2: SpeakHire Summit - June 7 - Connect with other alumni for a day of professional development and networking
A3: 46105.896 | B3: jhanmottap@gmail.com | C3: Jhan pier Motta Londoño | D3: 3540 83rd Jackson heights 11372 | E3: 6467256084 | F3: Theater ( acting ) and art ( photography) | G3: Brooklyn College | H3: Freelance model | I3: If there is an job opportunity that is relate with art. | J3: 03/24/26 (246 W 38th St) | K3: Other #Cheers4Careers events -- Alumni #Cheers4Careers is March 28th from 1 - 3 pm at Queens Museum featuring 3 Champions speaking about leadership
A4: 46106.369 | B4: naim.bakere@ellisprep.com | C4: Naim Bakere | D4: 2015 Southern Blvd 9c Bronx NY 10460 | E4: 9294221124 | F4: Business administration | G4: Monroe University expre | H4: I work with kid from KidFit soccer. We usually have different locations, so we work depending on the schedule. There is part time and full time.Since I’m a college student athlete,I work part time there. The kid are wonderful, good learners we enjoy every moment. I also do other shift as security certain day | I4: Not right now, but it would be for my colleague who is in college right now also. | J4: March 24 Midtown | K4: SpeakHire Summit - June 7 - Connect with other alumni for a day of professional development and networking
A5: 46106.897 | B5: mi577957@gmail.com | C5: Mingyu(Carl) Huo | D5: 14620 58th Ave, Flushing NY 11355 | E5: 929-319-9980 | F5: Math Education | G5: Queens College | H5: N/A | I5: Looking for jobs in education field | J5: March 28th Queens Museum | K5: Other #Cheers4Careers events -- Alumni #Cheers4Careers is March 28th from 1 - 3 pm at Queens Museum featuring 3 Champions speaking about leadership
A6: 46108.496 | B6: ousmane@speakhire.org | C6: Ousmane Diallo | D6: 1011 East 53rd street Brooklyn NY 11234 | E6: 6467038461 | F6: Systems programming | G6: City Tech | H6: N/A | I6: Both | J6: Cheers4Careers Alumni | K6: SpeakHire Summit - June 7 - Connect with other alumni for a day of professional development and networking, Other #Cheers4Careers events -- Alumni #Cheers4Careers is March 28th from 1 - 3 pm at Queens Museum featuring 3 Champions speaking about leadership
A7: 46108.945 | B7: jackelinemoran278@gmail.com | C7: Jackeline Susano Moran | D7: 104-41 41st Ave Corona NY 11368 | E7: 9179436216 | F7: Medical/Research | G7: Talent Unlimited High School | H7: N/A | I7: Yes, part time maybe | J7: Alumni- 03/28/26 @Queens Museum | K7: #SpeakingMyName - June 16th - Share your name story video and join the campaign!, SpeakHire Summit - June 7 - Connect with other alumni for a day of professional development and networking, Other #Cheers4Careers events -- Alumni #Cheers4Careers is March 28th from 1 - 3 pm at Queens Museum featuring 3 Champions speaking about leadership
A8: 46109.388 | B8: elisaoch3@gmail.com | C8: Elisa och | D8: 142-19 horace harding express way 11367 | E8: 9496878921 | F8: Airforce | G8: john bowne high school | H8: No i do not have a job | I8: Yes i am looking for a job | J8: Queens museum 3/28/2026 | K8: Other #Cheers4Careers events -- Alumni #Cheers4Careers is March 28th from 1 - 3 pm at Queens Museum featuring 3 Champions speaking about leadership
A9: 46109.411 | B9: mahaic2023@gmail.com | C9: Mahia | D9: 10453 | E9: 92296705851 | F9: Yes | G9: ! | H9: N | I9: Yes | J9: Yes | K9: #SpeakingMyName - June 16th - Share your name story video and join the campaign!, SpeakHire Summit - June 7 - Connect with other alumni for a day of professional development and networking, Other #Cheers4Careers events -- Alumni #Cheers4Careers is March 28th from 1 - 3 pm at Queens Museum featuring 3 Champions speaking about leadership
A10: 46109.441 | B10: mennatallah@speakhire.org | C10: Mennatallah Mahmoud | D10: 490 Grandview Ave, Ridgewood, NY 11385 | E10: 9293314859 | F10: Law | G10: MESA Charter High School | H10: N/A | I10: Yes, I would like to find a virtual internship, so it doesn’t effect school. | J10: 3/28/2026 Queens Museum | K10: #SpeakingMyName - June 16th - Share your name story video and join the campaign!, SpeakHire Summit - June 7 - Connect with other alumni for a day of professional development and networking, Other #Cheers4Careers events -- Alumni #Cheers4Careers is March 28th from 1 - 3 pm at Queens Museum featuring 3 Champions speaking about leadership
A11: 46109.447 | B11: leyli@speakhire.org | C11: Leyli Hernandez | D11: 99-22 42nd Ave Bsmt Corona NY 11368 | E11: (347)453-8142 | F11: STEM, Agriculture, Environmental | G11: Academy of American Studies | H11: N/A | I11: Yes, I am looking for a job for during the summer because at the moment I am busy with school and after school practices. | J11: 03/28/2026 at the Queens Museum | K11: SpeakHire Summit - June 7 - Connect with other alumni for a day of professional development and networking, Other #Cheers4Careers events -- Alumni #Cheers4Careers is March 28th from 1 - 3 pm at Queens Museum featuring 3 Champions speaking about leadership
A12: 46111.538 | B12: samueltavarez74@gmail.com | C12: Samuel Tavarez | D12: 559 W 158 St 10032 New York, NY | E12: 6463387513 | F12: Finance, International Business | G12: Baruch College | H12: N/A | I12: Intership | J12: April 18 Queens Museum | K12: SpeakHire Summit - June 7 - Connect with other alumni for a day of professional development and networking
A13: 46116.072 | B13: Cristinape31@gmail.com | C13: Jayda Caimares | D13: 65-21 79th st Middle Village NY 11379 | E13: 646-421-9589 | F13: Student | G13: PS 49 Middle Village NY 11379 | H13: Student | I13: Student | J13: Saturday, April 18 Queens Museum | K13: #SpeakingMyName - June 16th - Share your name story video and join the campaign!, SpeakHire Summit - June 7 - Connect with other alumni for a day of professional development and networking | L13: N/A
A14: 46116.074 | B14: Cristinape31@gmail.com | C14: Cristina Peña Caimares | D14: 65-21 79th st Middle Village NY 11379 | E14: 646-421-9589 | F14: Student | G14: Student | H14: Department of Education | I14: Speech Pathology | J14: Saturday, April 18 Queens Museum | K14: #SpeakingMyName - June 16th - Share your name story video and join the campaign!, SpeakHire Summit - June 7 - Connect with other alumni for a day of professional development and networking | L14: N/A
A15: 46122.654 | B15: elisaoch3@gmail.com | C15: Elisa och | D15: 142-19 horace harding expressway 11367 | E15: 9496878921 | F15: Health and nutrition science | G15: John Bowne highschool | H15: no i do not have a job | I15: no i am not intrested in any jobs yet maybe after highschool yeah | J15: Saturday april 18th 2026 | K15: #SpeakingMyName - June 16th - Share your name story video and join the campaign!, SpeakHire Summit - June 7 - Connect with other alumni for a day of professional development and networking, Other #Cheers4Careers events -- Alumni #Cheers4Careers is March 28th from 1 - 3 pm at Queens Museum featuring 3 Champions speaking about leadership | L15: No i do not have any allergies
A16: 46122.763 | B16: richie334455@gmail.com | C16: Richie Hung | D16: 108-19 71 AVENUE FOREST HILLS, NY 11375 | E16: 6466175246 | F16: Economic and data science | G16: Baruch college | H16: Retail | I16: I am looking for internships related to my major | J16: April 18th, forest hill public library | K16: SpeakHire Summit - June 7 - Connect with other alumni for a day of professional development and networking | L16: N/A
A17: 46123.872 | B17: raselali833@gmail.com | C17: Rasel Ali | D17: 10472 | E17: 9293305644 | F17: Education, non profit org, operations management | G17: CUNY Lehman | H17: Substitute NYC DOE | I17: . | J17: April 18, both ice cream and leadership talk | K17: #SpeakingMyName - June 16th - Share your name story video and join the campaign! | L17: N/A
A18: 46124.463 | B18: ousmane@speakhire.org | C18: Ousmane Diallo | D18: 11234 | E18: 6467038461 | F18: Research Scientists | G18: City Tech | H18: N/A | I18: Yes | J18: April 18 | K18: SpeakHire Summit - June 7 - Connect with other alumni for a day of professional development and networking | L18: Shrimp
A19: 46125.969 | B19: leyli@speakhire.org | C19: Leyli Hernandez | D19: 99-22 42nd Ave Bsmt Corona NY 11368 | E19: (347)453-8142 | F19: STEM, Agricultural Engineering, | G19: Academy of American Studies | H19: N/A | I19: I am currently working in my resume and have some companies in mind to apply at, but a internship would also help me with my career development so I may look into that as well. | J19: April 18 at Cookies n’ Cream 70-17 Austin St Forest Hills NY 11375 | K19: SpeakHire Summit - June 7 - Connect with other alumni for a day of professional development and networking, Other #Cheers4Careers events -- Alumni #Cheers4Careers is March 28th from 1 - 3 pm at Queens Museum featuring 3 Champions speaking about leadership | L19: No allergies or food restrictions
A20: 46128.709 | B20: yiengchukdorji123@gmail.com | C20: Yeingchuk Dorji | D20: 11373 | E20: 6462095546 | F20: Law, psychology | G20: Arizona state university | H20: Babysitting job | I20: Yes, currently looking for internships | J20: April 18 | K20: Other #Cheers4Careers events -- Alumni #Cheers4Careers is March 28th from 1 - 3 pm at Queens Museum featuring 3 Champions speaking about leadership | L20: I can help out with the set up.
A21: 46130.436 | B21: akiramartinez002@gmail.com | C21: Akira Z. Quezada | D21: 124 Farnham avenue, Garfield, NJ 07026. | E21: 7188442579 | F21: Biomedical engineering. | G21: The City College of New York. | H21: I work at International Community High School, I am a math tuttor. | I21: Yes, I'm looking for an internship in the STEM field, or a part time job related to my career interest. | J21: Ice cream and networking, leadership talks. | K21: SpeakHire Summit - June 7 - Connect with other alumni for a day of professional development and networking | L21: No allergies.
A22: 46140.769 | B22: ousmane@speakhire.org | C22: Ousmane Diallo | D22: 11234 | E22: 6467038461 | F22: Research Scientist in AI/ML | G22: CUNY City Tech | H22: N/A | I22: Yes | J22: May 24 | K22: #SpeakingMyName - June 16th - Share your name story video and join the campaign!, SpeakHire Summit - June 7 - Connect with other alumni for a day of professional development and networking, Other #Cheers4Careers events -- Alumni #Cheers4Careers is March 28th from 1 - 3 pm at Queens Museum featuring 3 Champions speaking about leadership | L22: No seafood
A23: 46154.545 | B23: ousmane@speakhire.org | C23: Ousmane Diallo | D23: 11234 | E23: 6467038461 | F23: Research in AI | G23: CUNY City Tech | H23: No | I23: Yes | J23: May 24 Lehman College | K23: #SpeakingMyName - June 16th - Share your name story video and join the campaign!, SpeakHire Summit - June 7 - Connect with other alumni for a day of professional development and networking, Other #Cheers4Careers events -- Alumni #Cheers4Careers is March 28th from 1 - 3 pm at Queens Museum featuring 3 Champions speaking about leadership | L23: No seafood
A24: 46159.686 | B24: libanezadelacruz4@gmail.com | C24: Jhanna De La Cruz | D24: 156E 171st St 3L Bronx, NY 10452 | E24: 9294044915 | F24: Social worker, Assistant Research, Human Resources and career related to psychology . | G24: N/A | H24: N/A | I24: Job but can be both. | J24: Lehman college Bronx, May 24 | K24: SpeakHire Summit - June 7 - Connect with other alumni for a day of professional development and networking | L24: No
A25: 46161.476 | B25: naimbakere@ellisprep.com | C25: Naim | D25: 2015 southern blvd 9c Bronx NY 10460 | E25: 9 | F25: Data analysis | G25: Monroe graduated | H25: PPI security duty | I25: Yes flexible job and good location | J25: Lehman college Bronx | K25: SpeakHire Summit - June 11 - Connect with other alumni for a day of professional development and networking, Other #Cheers4Careers events -- Alumni #Cheers4Careers is May 24th from 1 - 3 pm at Lehman College | L25: N/A

Sheet Champions
A1: First Name | B1: Last Name | C1: Full Name | D1: Phone Number | E1: Email Address | F1: Contact Status | G1: Kintone Record Number | H1: Hub Champion ID | I1: Hub User ID | J1: Main Career Field | K1: Notes | L1: Date Applied | M1: NY Congressional Districts | N1: NY Senate District | O1: NY Assembly District | P1: NYC City Council District | Q1: Address | R1: Current Location | S1: City | T1: State | U1: Current Company | V1: Programs Participated in | W1: Connected Interns | X1: Partner Orgs Supported | Y1: Testimonials | Z1: #Cheers4Careers Outreach | AA1: Soiree Outreach | AB1: Hub Active | AC1: Unsubscribed from Mailing List | AD1: Magazine Issue Mailed | AE1: Magazine Issue Mailed Date | AF1: Purpose of mailing | AG1: Donation Amount
A2: Tahsina | B2: Ahmed | C2: =CONCATENATE(A2," ",B2) -> Tahsina Ahmed | F2: Inactive CPC | G2: 671 | H2: {=IFERROR(INDEX('Hub CPC 226'!A:A, MATCH(C2, 'Hub CPC 226'!B:B, 0)), "")} -> 5 | I2: {=IFERROR(INDEX('Hub Users 226'!A:A, MATCH(C2, 'Hub Users 226'!B:B, 0)), "")} -> 25 | J2: STEM (Science, Technology, Engineering, Math) | L2: 44851.765 | T2: NJ | V2: FY 17 - 18 | W2: Ecstacy Holland and Mimi Agbobli | X2: American History | AB2: =IFERROR(__xludf.DUMMYFUNCTION("IF( ISNUMBER(MATCH( C2, IMPORTRANGE(""https://docs.google.com/spreadsheets/d/1yTh1ELC33JHYOeEdgIiEclxPRyh0zOKtlawDltfUay8"",""'Champions'!A:A""), 0 )), ""Outreach Conducted"", """")"),"")
A3: John ?Nico? | B3: Johnson | C3: =CONCATENATE(A3," ",B3) -> John ?Nico? Johnson | D3: 8582600744 | E3: 1nicojohnson@gmail.com | F3: Active CPC | G3: 399 | H3: {=IFERROR(INDEX('Hub CPC 226'!A:A, MATCH(C3, 'Hub CPC 226'!B:B, 0)), "")} -> 6 | I3: {=IFERROR(INDEX('Hub Users 226'!A:A, MATCH(C3, 'Hub Users 226'!B:B, 0)), "")} -> 26 | K3: 1/11/23 SB sent email about IR2 12/19/22 Nico confirmed Wheels schedule for IR2. CT 12/08/22 CT asked about Wheels schedule for IR2 12/16/21 Nico has only shown to 1 out of 4 sessions for FY21-22 IR1 so far SB Nico is active US Navy for the past 13 years Can be matched on Engineering and law enforcement / army Nico has basic Spanish (can understand at a minimum really) and told Hetal to take it off as a language. Can match on Spanish if the student puts 'Somewhat Comfortable' put shows higher proficiency and needs someone without the Spanish cruth. He can do Japanese (conversational) and ASL. (HJ, 10/20/21) Nico informed us on May 3rd, 2021 that he changed companies from Insight Global to Bravura (HJ) Nico attended a training on 2/26/21 with JPS JPS followed up on 2/20/21 &#43; invited Nico to schedule a training Nico was screened on 2/19/21 by Malak Baker at 1 pm est Double checked 1/26 (KW) | L3: 44200.699 | Q3: 630 8th Avenue, San Diego | R3: San Diego | S3: San Diego | T3: CA | U3: Bravura | V3: Seminars 22, Seminars 21, FY 22 - 23, FY 21 - 22, FY 20 - 21 | W3: Richard Murillo, Aristid Reynoso, Emanuel Ortiz, Jason Hernandez, Rubaya Nasrin, Michael Suarez Suarez, Vimadel Estrella, Alessandro Pineda, Elver Veras, Maria Ventura, Francis Calderon, Jose Rivera and Trisha Landolt | X3: ClaremontIHS, WheelsNYC, HSEI, IHS Health, FlushingIHS | AB3: =IFERROR(__xludf.DUMMYFUNCTION("IF( ISNUMBER(MATCH( C3, IMPORTRANGE(""https://docs.google.com/spreadsheets/d/1yTh1ELC33JHYOeEdgIiEclxPRyh0zOKtlawDltfUay8"",""'Champions'!A:A""), 0 )), ""Outreach Conducted"", """")"),"")
A4: Abdelrahman | B4: Bannora | C4: =CONCATENATE(A4," ",B4) -> Abdelrahman Bannora | D4: 201200000000 | E4: a_bannora@yahoo.co.uk | F4: Inactive CPC | G4: 491 | H4: {=IFERROR(INDEX('Hub CPC 226'!A:A, MATCH(C4, 'Hub CPC 226'!B:B, 0)), "")} -> 7 | I4: {=IFERROR(INDEX('Hub Users 226'!A:A, MATCH(C4, 'Hub Users 226'!B:B, 0)), "")} -> 27 | J4: Health Sciences/Medicine | K4: Has no US experience so asked to be a seminar speaker or Speaker Series speaker (SB, 9/21/21) Screening call completed 9/2/21 SB Sent screening scheduling email 8/23/21 SB | L4: 44427.463 | Q4: Building 12A,Street 42, 11th district, Zayed, Giza, Egypt | R4: Cairo, Egypt | U4: N/A, I'm a freelancer | AB4: =IFERROR(__xludf.DUMMYFUNCTION("IF( ISNUMBER(MATCH( C4, IMPORTRANGE(""https://docs.google.com/spreadsheets/d/1yTh1ELC33JHYOeEdgIiEclxPRyh0zOKtlawDltfUay8"",""'Champions'!A:A""), 0 )), ""Outreach Conducted"", """")"),"")
A5: Andres | B5: Rubiano | C5: =CONCATENATE(A5," ",B5) -> Andres Rubiano | D5: (941) 296-5946 | E5: Aar2213@tc.Columbia.edu | F5: Active CPC | G5: 647 | H5: {=IFERROR(INDEX('Hub CPC 226'!A:A, MATCH(C5, 'Hub CPC 226'!B:B, 0)), "")} | I5: {=IFERROR(INDEX('Hub Users 226'!A:A, MATCH(C5, 'Hub Users 226'!B:B, 0)), "")} -> 28 | J5: Entertainment/Lifestyle | K5: 3/31/23 CT updated bio &amp; job title 3/23/23 CT updated email to Aar2213@tc.Columbia.edu 3/15/23 CT asked to be in-person Seminar Speaker at BUSHWICKCHS | L5: 44678.582 | R5: New York | T5: NY | U5: SuitUp | V5: Seminars 23, Seminars 22 | X5: BUSHWICKCHS, P2GBronx | AB5: =IFERROR(__xludf.DUMMYFUNCTION("IF( ISNUMBER(MATCH( C5, IMPORTRANGE(""https://docs.google.com/spreadsheets/d/1yTh1ELC33JHYOeEdgIiEclxPRyh0zOKtlawDltfUay8"",""'Champions'!A:A""), 0 )), ""Outreach Conducted"", """")"),"")
A6: Abhishek | B6: Mehta | C6: =CONCATENATE(A6," ",B6) -> Abhishek Mehta | D6: 16692884132 | E6: abhisshekmehta@gmail.com | F6: Active CPC | G6: 489 | H6: {=IFERROR(INDEX('Hub CPC 226'!A:A, MATCH(C6, 'Hub CPC 226'!B:B, 0)), "")} -> 9 | I6: {=IFERROR(INDEX('Hub Users 226'!A:A, MATCH(C6, 'Hub Users 226'!B:B, 0)), "")} -> 29 | J6: Health Sciences/Medicine | K6: 7/17/23 - SB sent email for IRS, BC called &amp; left VM, SB sent follow up text 1/12/23 emailed SB, &#34;My schedule will not allow me to undertake this project over the next several months. As much as I loved doing this, I'll have to skip for the next few months at least.&#34; - not available for IR2 and IR3 - try for FY 23-24 IRS or IR1 1/11/23 SB sent email for IR2 for Mondays 3/6/22 Emailed in response to IR3 availability request saying he is not available for this round but is interested in future rounds Completed Training and Onboarding on 9/1/21 SB Training scheduling email sent 8/10/21 Passed screening 8/9/21 SB Sent follow up scheduling email 8/4/21 SB Sent screening scheduling email 8/2/21 SB Social Media Handle: @abhisshekmehta | L6: 44410.79 | Q6: 1836 Lee Way, Milpitas, CA 95035 | R6: Milpitas, CA | S6: Milpitas | T6: CA | U6: Tesla, Inc. | V6: FY 21 - 22 | W6: Ousmane Diallo, Abdelrahman Mohamed, Ricaldyne Saturne, Ligia Espinoza, Eliana Alfonso Hernandez and Paola Munoz | X6: NYC Mission - Emma Lazarus, IHS Lafayette, IHS Health, FlushingIHS | AB6: =IFERROR(__xludf.DUMMYFUNCTION("IF( ISNUMBER(MATCH( C6, IMPORTRANGE(""https://docs.google.com/spreadsheets/d/1yTh1ELC33JHYOeEdgIiEclxPRyh0zOKtlawDltfUay8"",""'Champions'!A:A""), 0 )), ""Outreach Conducted"", """")"),"")
A7: Adela | B7: Cimic | C7: =CONCATENATE(A7," ",B7) -> Adela Cimic | D7: 6365412393 | E7: adelacimic@gmail.com | F7: Active CPC | G7: 416 | H7: {=IFERROR(INDEX('Hub CPC 226'!A:A, MATCH(C7, 'Hub CPC 226'!B:B, 0)), "")} -> 10 | I7: {=IFERROR(INDEX('Hub Users 226'!A:A, MATCH(C7, 'Hub Users 226'!B:B, 0)), "")} -> 30 | J7: Business | K7: Not available for IR1 &amp; probably not much time in the future due to personal reasons. CT 9/7/22 7/5/22 LG reached out for IRS availability 3/24/22 Not available for Seminars in May &amp; June due to visiting family overseas. CT 3/21/22 Not available for IR3 CT 12/22/21 SB sent IR2 FY21-22 schedule list for matching Adela attended a training webinar on 3/8/21 with JPS HJ marked Adela as Active Green based off of Malak's notes from screening (2/26/2021) Adela had a screening call with Malak Baker on 2/15/21 JPS emailed on 2/7/2021 to schedule a Screening Call Double checked 1/26 (KW) | L7: 44200.819 | M7: 7 | N7: 59 | O7: 50 | P7: 33 | Q7: 208 Java St apt 1A, Brooklyn NY | R7: NYC | S7: Brooklyn | T7: NY | U7: Columbia university medical center | V7: Seminars 22, FY 20 - 21 | W7: Dariel Harrison and Blair Vales | X7: IHSUnionSquare, QueensPrepAcad | AB7: =IFERROR(__xludf.DUMMYFUNCTION("IF( ISNUMBER(MATCH( C7, IMPORTRANGE(""https://docs.google.com/spreadsheets/d/1yTh1ELC33JHYOeEdgIiEclxPRyh0zOKtlawDltfUay8"",""'Champions'!A:A""), 0 )), ""Outreach Conducted"", """")"),"")
A8: Addy Michelle | B8: Jimenez Haga | C8: =CONCATENATE(A8," ",B8) -> Addy Michelle Jimenez Haga | D8: 17142903471 | E8: adrianna.haga@gmail.com | F8: Active CPC | G8: 55 | H8: {=IFERROR(INDEX('Hub CPC 226'!A:A, MATCH(C8, 'Hub CPC 226'!B:B, 0)), "")} -> 11 | I8: {=IFERROR(INDEX('Hub Users 226'!A:A, MATCH(C8, 'Hub Users 226'!B:B, 0)), "")} -> 31 | J8: Armed Services/Law Enforcement | K8: 12/4/23 Addy confirmed availability for IR2, SB emailed About Interns to confirm group 11/29/23 Add replied to newsletter saying she was interested in IR2 - SB sent dates to check availability Addy made the #ChampionItForward video 7/18/23 WW emailed for IRS availability, FG followed up with call and text, not available for IRS - &#34;If something comes up between 11:30 - 1:00 PM PDT please let me know.&#34; 12/16/22 Addy confirmed availability for IR2 - Mondays at 3 pm est 12/13/22 SB sent follow up email about matching - Addy responded that she is talking with boss and will get back to us later this week 12/6/22 SB emailed schedules and request for IR2 12/1/22 emailed SB current availability: 6-7 am or between 11:00 - 1:00 pm PST (9-10 am est or 2-4 pm est) Travelling most of November and might not be able to join IR1. She wants to receive schedule though and might be able to participate. Best times for her are 11 am to 1:30 pm PST. CT 08/31/2022 7/12/22 Addy emailed letting us know availability/flexibility at work is limited. Doing internship rounds early in the morning (pst) would work better for her. SB 3/14/22 Not available for IR3 due to new position at work. Reach out for next round. CT Best form of contact is phone 2/18/22 SB asked Addy for a seminar, she would love to but unable to Monday thru Thursday when also doing sessions. Asked to be considered for Friday Seminars! She waited over a year for a mentee and wasn't match due to lack of school partners at the time. She said she is no longer available but if you have a good match, it might be worth reaching out to see. | L8: 43338.743 | Q8: 1723 Capitol Ave Apt 6, Sacramento, CA 95811 | S8: Sacramento | T8: CA | U8: California Governor's Office of Emergency Services (Cal OES) | V8: Seminars 21, FY 20 - 21, FY 21 - 22, FY 22 - 23, FY 23 - 24 | W8: Licsy Reyes, Tariana Garcia Encarnacion, Tasnim Jahan, Bianka Pena, Rafialy Carrasco, Ofelia (Sara) Lopez, Emili Ordonez, Jazling Garcia Garcia, Wilberto Verlasquez, Norvia Tavarez, Robeliza Nunez, Daniela Gonzalez, Claudia Herazo, Karilyne Suazo, Tariana Garcia Encarnacion, Ronald Pujols, Lesly Chucino, Lia Luciano, Yoleinny Sosa Marte and Lleilin Guerra | X8: SOF, ELLIS, CrotonaIHS | AB8: =IFERROR(__xludf.DUMMYFUNCTION("IF( ISNUMBER(MATCH( C8, IMPORTRANGE(""https://docs.google.com/spreadsheets/d/1yTh1ELC33JHYOeEdgIiEclxPRyh0zOKtlawDltfUay8"",""'Champions'!A:A""), 0 )), ""Outreach Conducted"", """")"),"")
A9: Ashley Elizabeth | B9: Hudson-Hines | C9: =CONCATENATE(A9," ",B9) -> Ashley Elizabeth Hudson-Hines | D9: 619-243-4904 | E9: aehhines@gmail.com | F9: Active CPC | G9: 110 | H9: {=IFERROR(INDEX('Hub CPC 226'!A:A, MATCH(C9, 'Hub CPC 226'!B:B, 0)), "")} -> 12 | I9: {=IFERROR(INDEX('Hub Users 226'!A:A, MATCH(C9, 'Hub Users 226'!B:B, 0)), "")} -> 32 | K9: 5/16/22 SB emailed for re-engagement 12/30/21 SB sent IR2 FY21-22 schedule list for matching 12/10/21 and 12/13/21 SB reached-out via text to match for FY21-22 IR1, Ashley unable due to health concerns. Reach out for IR2 to see if she can | L9: 43484.717 | Q9: 4526 Kensington Dr. San Diego, CA 92116 | R9: San Diego, CA | S9: San Diego | T9: CA | U9: ELM Learning | AB9: =IFERROR(__xludf.DUMMYFUNCTION("IF( ISNUMBER(MATCH( C9, IMPORTRANGE(""https://docs.google.com/spreadsheets/d/1yTh1ELC33JHYOeEdgIiEclxPRyh0zOKtlawDltfUay8"",""'Champions'!A:A""), 0 )), ""Outreach Conducted"", """")"),"")
A10: Anne | B10: Tam | C10: =CONCATENATE(A10," ",B10) -> Anne Tam | D10: 347-528-1314 | E10: agwtam@gmail.com | F10: Active CPC | G10: 112 | H10: {=IFERROR(INDEX('Hub CPC 226'!A:A, MATCH(C10, 'Hub CPC 226'!B:B, 0)), "")} -> 13 | I10: {=IFERROR(INDEX('Hub Users 226'!A:A, MATCH(C10, 'Hub Users 226'!B:B, 0)), "")} -> 33 | K10: 3/17/23 Confirmed group for IR3 3/14/23 agreed to Wheels schedule, emailing About Interns 3/8/23 SB emailed about IR3 2/8/23 unavailable for IR2 - starting new job. SB emailed asking for updated job information 2/6/23 CT asked for IR2 with Wheels schedule 10/14/22 Anne confirmed wheels availability 10/13/22 SB sent match request for Wheels 7/11/22 Anne unavailable for IRS SB 7/7/22 LG called, emailed for IRS availability 3/21/22 Not available for IR3 CT 1/7/22 Update job info and added new resume SB 01/05/22 CT sent follow up email for matching 12/30/21 SB sent IR2 FY21-22 schedule list for matching JPS sent re-engagement email to Anne on 1/6/2021 | L10: 43484.724 | M10: 7 | N10: 12 | O10: 37 | P10: 26 | Q10: 4705 47th Ave #1F Woodside, NY 11377 | S10: Woodside | T10: NY | U10: CUREBASE | V10: FY 22 - 23, FY 21 - 22 | W10: Skirlie De La Cruz, Ayele Dounou, Ismatu Barry, Fatoumata Barry, Zhihao Huang, Yechi Ma, JiaJing Li, Lhianna Capell, Rashel Cabreja, Ashley Diaz, Karina Tejada, Schayna Ceballos, Kimberly Paulino, Anais Martinez and Aaliyah Escalante | X10: ICHSBronx, WheelsNYC, FlushingIHS | AB10: =IFERROR(__xludf.DUMMYFUNCTION("IF( ISNUMBER(MATCH( C10, IMPORTRANGE(""https://docs.google.com/spreadsheets/d/1yTh1ELC33JHYOeEdgIiEclxPRyh0zOKtlawDltfUay8"",""'Champions'!A:A""), 0 )), ""Outreach Conducted"", """")"),"")
A11: Afia | B11: Howladar | C11: =CONCATENATE(A11," ",B11) -> Afia Howladar | D11: 13475250223 | E11: ahowladar98@gmail.com | F11: Inactive CPC | G11: 663 | H11: {=IFERROR(INDEX('Hub CPC 226'!A:A, MATCH(C11, 'Hub CPC 226'!B:B, 0)), "")} -> 14 | I11: {=IFERROR(INDEX('Hub Users 226'!A:A, MATCH(C11, 'Hub Users 226'!B:B, 0)), "")} -> 34 | J11: Health Sciences/Medicine | K11: 10/26/22 Afia emailed, &#34;Hope you have been well! I am reaching out to be pulled from the SpeakHire program as I am currently interviewing at other companies and likely will not be with my current company very long. I apologize for pulling out last second and I wish you luck!&#34; SB followed up to see if we could reach out once she has settled at her new job - marking as inactive for now 9/26/22 Afia signed up for 10/27 training and said about match, &#34;need to conduct these sessions during my lunch, I would need them to take place anytime between 11am-3pm.&#34; need to see if any group can meet at that time. SB 9/24/22 SB followed up for training and asked for IR1 for Ellis 9/21/22 She is interested in IR1 but January is busy so may need to reschedule those sessions early. SB Passed screening- sending training email. 9/21/22 SB 9/14/22 SB sent screening scheduling follow up 9/9/22 SB sent screening scheduling email | L11: 44812.976 | M11: 12 | N11: 28 | O11: 76 | P11: 5 | Q11: 526 east 85th st #4D | R11: New York, NY | S11: New York | T11: NY | U11: Russell Tobin | AB11: =IFERROR(__xludf.DUMMYFUNCTION("IF( ISNUMBER(MATCH( C11, IMPORTRANGE(""https://docs.google.com/spreadsheets/d/1yTh1ELC33JHYOeEdgIiEclxPRyh0zOKtlawDltfUay8"",""'Champions'!A:A""), 0 )), ""Outreach Conducted"", """")"),"")
A12: Amy | B12: Meredith Jones | C12: =CONCATENATE(A12," ",B12) -> Amy Meredith Jones | D12: 310-666-0661 | E12: aj@recollectbetter.com | F12: Inactive CPC | G12: 63 | H12: {=IFERROR(INDEX('Hub CPC 226'!A:A, MATCH(C12, 'Hub CPC 226'!B:B, 0)), "")} -> 15 | I12: {=IFERROR(INDEX('Hub Users 226'!A:A, MATCH(C12, 'Hub Users 226'!B:B, 0)), "")} -> 35 | J12: Health Sciences/Medicine | K12: Amy responded 5/17/22 &#34; Unfortunately im still grappling with chronic illness and not able to support in this way. Thank you. &#34; 5/16/22 SB sent re-engagement email 12/30/21 SB sent IR2 FY21-22 schedule list for matching email 8/10/21 responded they currently can't be in the program due to health reasons but will still like to stay in contact. HH JPS followed up via email once again on 7/22/21 and let Amy know that it appears she did go through screening - gaging her interested to move forward in this process. HH voicemail/text 7/20/21 JPS sent an outreach email on 6/2/21 Amy was screened by Scotney on 9/7/2018. She was unable to complete the training process due to an illness in September 2018. | L12: 43338.743 | Q12: 28295 Via Rueda San Juan Capistrano, CA 92675 | S12: San Juan Capistrano | T12: CA | U12: Love Saves Lives, Inc. | AB12: =IFERROR(__xludf.DUMMYFUNCTION("IF( ISNUMBER(MATCH( C12, IMPORTRANGE(""https://docs.google.com/spreadsheets/d/1yTh1ELC33JHYOeEdgIiEclxPRyh0zOKtlawDltfUay8"",""'Champions'!A:A""), 0 )), ""Outreach Conducted"", """")"),"")
A13: Alyssa Jean | B13: Marion Daum | C13: =CONCATENATE(A13," ",B13) -> Alyssa Jean Marion Daum | D13: 949-266-7357 | E13: ajmdaum@gmail.com | F13: Inactive CPC | G13: 208 | H13: {=IFERROR(INDEX('Hub CPC 226'!A:A, MATCH(C13, 'Hub CPC 226'!B:B, 0)), "")} -> 16 | I13: {=IFERROR(INDEX('Hub Users 226'!A:A, MATCH(C13, 'Hub Users 226'!B:B, 0)), "")} -> 36 | K13: 12/27/21 Unable do IR2, &#34;For the foreseeable future, I will not be able to do any mentoring&#34; SB 12/22/21 SB sent IR2 FY21-22 schedule list for matching Alyssa responded to outreach on 2/10/21 and said, &#34;Thank you for reaching out. Unfortunately, I will be unable to take on matches this school year, but I would love to reconnect next school year. Also, will you please update my email to ajmdaum@gmail.com ? This is my work email, I would prefer to be reached via my personal email.&#34; JPS emailed on 2/10/21 to see if Alyssa can accommodate an IR2 20-21 match | L13: 43727.731 | Q13: 46 Camino del Oro RSM, CA 92688 | R13: Foothill Ranch, CA | S13: Foothill Ranch | T13: CA | U13: ExoAnalytic Solutions | AB13: =IFERROR(__xludf.DUMMYFUNCTION("IF( ISNUMBER(MATCH( C13, IMPORTRANGE(""https://docs.google.com/spreadsheets/d/1yTh1ELC33JHYOeEdgIiEclxPRyh0zOKtlawDltfUay8"",""'Champions'!A:A""), 0 )), ""Outreach Conducted"", """")"),"")
A14: Akanksha | B14: Raina | C14: =CONCATENATE(A14," ",B14) -> Akanksha Raina | D14: 857-389-9018 | E14: akanksharaina@gmail.com | F14: Active CPC | G14: 387 | H14: {=IFERROR(INDEX('Hub CPC 226'!A:A, MATCH(C14, 'Hub CPC 226'!B:B, 0)), "")} -> 17 | I14: {=IFERROR(INDEX('Hub Users 226'!A:A, MATCH(C14, 'Hub Users 226'!B:B, 0)), "")} -> 37 | J14: Business | K14: 2/28/23 CT left voicemail &amp; sent text to about taking over Wheels group for IR2 2/27/23 CT sent email asking to take over Wheels group for IR2 12/14/21 SB called and she is unable due to traveling these months, asked to be reached out to for IR2 FY21-22 12/13/21 SB and CT reached out for IR1 FY21-22 match Akanksha atteneded a CPC Training on 4/10/21 with JPS Doubled Checked 1/19 (KW) | L14: 44200.643 | M14: 12 | N14: 47 | O14: 67 | P14: 3 | Q14: 888 8th Avenue, 12 O, NY | R14: New York | S14: New York | T14: NY | U14: Common Living | V14: FY 20 - 21 | W14: Trisha Landolt and Nicole Molano | X14: ClaremontIHS | AB14: =IFERROR(__xludf.DUMMYFUNCTION("IF( ISNUMBER(MATCH( C14, IMPORTRANGE(""https://docs.google.com/spreadsheets/d/1yTh1ELC33JHYOeEdgIiEclxPRyh0zOKtlawDltfUay8"",""'Champions'!A:A""), 0 )), ""Outreach Conducted"", """")"),"")
A15: Joseph | B15: Temowo | C15: =CONCATENATE(A15," ",B15) -> Joseph Temowo | D15: 9173016742 | E15: akintemowo@yahoo.com | F15: Inactive CPC | G15: 405 | H15: {=IFERROR(INDEX('Hub CPC 226'!A:A, MATCH(C15, 'Hub CPC 226'!B:B, 0)), "")} -> 18 | I15: {=IFERROR(INDEX('Hub Users 226'!A:A, MATCH(C15, 'Hub Users 226'!B:B, 0)), "")} -> 38 | J15: Armed Services/Law Enforcement | K15: 7/24/23 WW called - too busy for any round for the rest of the year, SB marking inactive re-engage summer of 24 12/13/22 SB sent follow up email about IR2 12/8/22 SB emailed for Ellis match 6/15/22 FY 21-22 IR3 he had low engagement from Interns and felt discouraged. Give him a break for IRS and give him stronger students next round. 4/14/22 Not available for IR3, lot of travelling internationally. CT Joseph is an active duty military member Joseph attended a training session on 3/8/21 with JPS Joseph was screened on 2/15/21 by Malak Baker. JPS sent follow up email &#43; invited Joseph to schedule a training JPS emailed on 2/7/2021 to schedule a Screening Call Double checked 1/26 (KW) | L15: 44200.769 | Q15: 14 Glacier Dr., Morris Plains | R15: New Jersey, United States | S15: Morris Plains | T15: NJ | U15: Bloom Energy Corporation | V15: FY 22 - 23, FY 21 - 22, FY 20 - 21 | W15: Rasheed Abdulla, Yasmin Abdulla, Awa Ndiaye, Naim Bakere, Marwin Silverio Rodriguez, Fatou Diedhiou, Carlos Ramirez, Cesar Misael Orellana Riera, Nasif Zaman, Yemili Goodridge, Munir Ahmad Bakhtyar, bessirou doukoure and dalissa cabrera | X15: ELLIS, FlushingIHS | AB15: =IFERROR(__xludf.DUMMYFUNCTION("IF( ISNUMBER(MATCH( C15, IMPORTRANGE(""https://docs.google.com/spreadsheets/d/1yTh1ELC33JHYOeEdgIiEclxPRyh0zOKtlawDltfUay8"",""'Champions'!A:A""), 0 )), ""Outreach Conducted"", """")"),"")
A16: Alina | B16: Ispas Montbriand | C16: =CONCATENATE(A16," ",B16) -> Alina Ispas Montbriand | D16: 267-235-7033 | E16: alina.ispas.09@gmail.com | F16: Active CPC | G16: 131 | H16: {=IFERROR(INDEX('Hub CPC 226'!A:A, MATCH(C16, 'Hub CPC 226'!B:B, 0)), "")} -> 19 | I16: {=IFERROR(INDEX('Hub Users 226'!A:A, MATCH(C16, 'Hub Users 226'!B:B, 0)), "")} -> 39 | K16: 7/15/23 SB emailed for IRS 2/21/23 CT sent email about being Seminar Speaker for IHS US 1/24/23 CT Alina was impacted by recent Google layoffs. Don't reach out to her until the end of Feb at the earliest. 10/4/22 SB emailed Alina for Ellis match, she confirmed availability 8/12/22 Interested in IR1 SB 4/8/22 passed training with SB 3/1/22 SB call Alina - leave VM and send text about training and Claremont Match 01/21/22 CT Screening Call passed, sent Orientation &amp; Onboarding email with session schedules IR2 12/28/21 SB sent IR2 FY21-22 schedule list for matching JPS sent an email via Champions@speakhire.org to schedule a training webinar on 7/21/21. Had a Screening Call with Scotney Jan 2019 - passed | L16: 43590.632 | Q16: 1824 Spruce Street, Apt 4F, Philadelphia, PA 19103 | S16: Philadelphia | T16: PA | U16: Google Workspace | V16: Seminars 23, FY 21 - 22, FY 22 - 23 | W16: Wladimir Veloz Balbuena, Mohamed Danso, Mariama Diallo, Jariel Fernandez and Johalyn Perez | X16: IHSUnionSquare, ELLIS, WheelsNYC | AB16: =IFERROR(__xludf.DUMMYFUNCTION("IF( ISNUMBER(MATCH( C16, IMPORTRANGE(""https://docs.google.com/spreadsheets/d/1yTh1ELC33JHYOeEdgIiEclxPRyh0zOKtlawDltfUay8"",""'Champions'!A:A""), 0 )), ""Outreach Conducted"", """")"),"")
A17: Alpa | B17: Lachhman Rajai | C17: =CONCATENATE(A17," ",B17) -> Alpa Lachhman Rajai | D17: 9175421226 | E17: alpa.rajai@gmail.com | F17: Active CPC | G17: 61 | H17: {=IFERROR(INDEX('Hub CPC 226'!A:A, MATCH(C17, 'Hub CPC 226'!B:B, 0)), "")} -> 20 | I17: {=IFERROR(INDEX('Hub Users 226'!A:A, MATCH(C17, 'Hub Users 226'!B:B, 0)), "")} -> 40 | J17: Entertainment/Lifestyle | K17: 7/18/23 WW emailed for IRS availability, FG called and left VM and texted 3/15/23 CT left voicemail &amp; sent text for IR3 3/14/23 CT left voicemail &amp; sent text about taking over group of Interns for IR2 01/05/22 CT sent follow up email for matching 12/30/21 SB sent IR2 FY21-22 schedule list for matching 12/20 SB called Alpa and left a Voicemail 12/17 SB sent Alpa a text about match for FY21-22 IR1 | L17: 43338.743 | Q17: 700 Grove St, Apt 5R, Jersey City, NJ 07310 | S17: Jersey City | T17: NJ | U17: Barclays | V17: FY 19 - 20 | W17: Nicole Quiga and Sabrin Haque | X17: FlushingHigh | AB17: =IFERROR(__xludf.DUMMYFUNCTION("IF( ISNUMBER(MATCH( C17, IMPORTRANGE(""https://docs.google.com/spreadsheets/d/1yTh1ELC33JHYOeEdgIiEclxPRyh0zOKtlawDltfUay8"",""'Champions'!A:A""), 0 )), ""Outreach Conducted"", """")"),"")
A18: Alvaro | B18: Pavas-Hincapie | C18: =CONCATENATE(A18," ",B18) -> Alvaro Pavas-Hincapie | D18: 19294367119 | E18: alpavash@gmail.com | F18: Prospective | G18: 539 | H18: {=IFERROR(INDEX('Hub CPC 226'!A:A, MATCH(C18, 'Hub CPC 226'!B:B, 0)), "")} -> 21 | I18: {=IFERROR(INDEX('Hub Users 226'!A:A, MATCH(C18, 'Hub Users 226'!B:B, 0)), "")} -> 41 | J18: Health Sciences/Medicine | K18: 4/3/23 CT sent follow up to schedule Screening Call 2/22/23 CT sent follow up email to re-engage 2/9/23 CT sent re-engagement email 5/24/22 SB sent re-engagement email Screening invite sent 11/7/21 | L18: 44505.633 | Q18: Calle 53C Sur #40B 78 Ap 904 | R18: Montreal, Quebec - Canadá | U18: Orbis International | AB18: =IFERROR(__xludf.DUMMYFUNCTION("IF( ISNUMBER(MATCH( C18, IMPORTRANGE(""https://docs.google.com/spreadsheets/d/1yTh1ELC33JHYOeEdgIiEclxPRyh0zOKtlawDltfUay8"",""'Champions'!A:A""), 0 )), ""Outreach Conducted"", """")"),"")
A19: Albert | B19: Rocco | C19: =CONCATENATE(A19," ",B19) -> Albert Rocco | D19: 2014017738 | E19: alrocco5@gmail.com | F19: Active CPC | G19: 359 | H19: {=IFERROR(INDEX('Hub CPC 226'!A:A, MATCH(C19, 'Hub CPC 226'!B:B, 0)), "")} -> 22 | I19: {=IFERROR(INDEX('Hub Users 226'!A:A, MATCH(C19, 'Hub Users 226'!B:B, 0)), "")} -> 42 | J19: Arts/Creative | K19: He texted WW 3/8/24: Please refrain from contacting me until 2025 7/11/23 emailed SB not available for IRS 7/10/23 SB emailed for IRS 12/26/22 responded saying he has many travel commitments and cannot participate in IR2. SB 12/22/22 SB emailed for Ellis match Albert attended a CPC Training Webinar on 1/16/2021 with JPS at 11 am est Hetal Jani had second screening call on November 17, 2020 -- he was able to understand our approach; seemed he looked more into what we did. Older, has a lot of experience, can guide a student with a lot of self-advocacy so they can ask targeted questions Jennifer Peterson-Sharma emailed Albert on 10/27/2020 to schedule a second screening call next week with Hetal Jani. Had a Mentor Screening Call on 10/13/2020 at 4:30 pm EST with Jennifer Peterson-Sharma. Albert is scheduled for a Screening Call on 10/13/2020. Albert was emailed on 10/12/2020 to schedule a mentor screening call | L19: 44116.51 | Q19: 131 Magnolia Ave, Tenafly, NJ | R19: NJ | S19: Tenafly | T19: NJ | U19: Koslow Scientific Company | V19: FY 21 - 22 | W19: Diego Dinardi, Lisvany Guzman, Kadidiatou Traore, Wendy Ouedraogo and Tariana Garcia Encarnacion | X19: ClaremontIHS, CrotonaIHS | AB19: =IFERROR(__xludf.DUMMYFUNCTION("IF( ISNUMBER(MATCH( C19, IMPORTRANGE(""https://docs.google.com/spreadsheets/d/1yTh1ELC33JHYOeEdgIiEclxPRyh0zOKtlawDltfUay8"",""'Champions'!A:A""), 0 )), ""Outreach Conducted"", """")"),"")
A20: Amanda | B20: Morgan Mackler | C20: =CONCATENATE(A20," ",B20) -> Amanda Morgan Mackler | D20: 2015464923 | E20: amackler40@gmail.com | F20: Active CPC | G20: 361 | H20: {=IFERROR(INDEX('Hub CPC 226'!A:A, MATCH(C20, 'Hub CPC 226'!B:B, 0)), "")} -> 23 | I20: {=IFERROR(INDEX('Hub Users 226'!A:A, MATCH(C20, 'Hub Users 226'!B:B, 0)), "")} -> 43 | J20: Service/Hospitality Industry | K20: 12/20 SB called Amanda and left a Voicemail 12/17 SB sent Amanda a text about match for FY21-22 IR1 Amanda attended a training on 2/26/21 with JPS JPS followed up on 2/17/21 to schedule Amanda for a training JPS sent Amanda congratulations email &#43; tried to get Amanda to schedule a training in January, but Amanda was unable to attend. JPS followed up on 2/4/21 to see if Amanda wanted to attend a training in February. Amanda was screened on 10/22/2020 at 4:20 pm EST by Jennifer Peterson-Sharma. Jennifer Peterson-Sharma emailed to schedule a screening call on 10/22/2020. | L20: 44119.568 | Q20: New York | T20: NY | U20: KPMG | V20: FY 20 - 21 | W20: Bradley Edwards and Bindadevi Sukhandan | X20: QueensPrepAcad | AB20: =IFERROR(__xludf.DUMMYFUNCTION("IF( ISNUMBER(MATCH( C20, IMPORTRANGE(""https://docs.google.com/spreadsheets/d/1yTh1ELC33JHYOeEdgIiEclxPRyh0zOKtlawDltfUay8"",""'Champions'!A:A""), 0 )), ""Outreach Conducted"", """")"),"")
A21: Andrea | B21: Goodfriend | C21: =CONCATENATE(A21," ",B21) -> Andrea Goodfriend | D21: 18184513081 | E21: amandel@pinterest.com | F21: Active CPC | G21: 506 | H21: {=IFERROR(INDEX('Hub CPC 226'!A:A, MATCH(C21, 'Hub CPC 226'!B:B, 0)), "")} -> 24 | I21: {=IFERROR(INDEX('Hub Users 226'!A:A, MATCH(C21, 'Hub Users 226'!B:B, 0)), "")} -> 44 | J21: Education | K21: 5/10/23 email auto responded - on maternity leave 2/7/23 CT left voicemail &amp; sent text to check in 1/11/23 CT sent follow up email 01/03/23 CT sent follow up email 12/22/22 CT sent check in email 12/22/21 SB sent IR2 FY21-22 schedule list for matching Had to back out after match and a few sessions due to family emergency 12/7/21 SB Completed training 11/12/21 SB 10/26/21 SB Screening note: She prefers to be matched with Interns who identify as being from Central or South America. 10/27/21 SB sent congrats and training scheduling email. Andrea responded asking for more dates, SB asked her availability second week of November Passed screening on 10/26/21 SB Sent screening scheduling email on10/8/21 SB | L21: 44476.76 | Q21: 5130 INADALE AVE, Los Angeles, CA 90043 | R21: Los Angeles, CA | S21: Los Angelos | T21: CA | U21: Pinterest | AB21: =IFERROR(__xludf.DUMMYFUNCTION("IF( ISNUMBER(MATCH( C21, IMPORTRANGE(""https://docs.google.com/spreadsheets/d/1yTh1ELC33JHYOeEdgIiEclxPRyh0zOKtlawDltfUay8"",""'Champions'!A:A""), 0 )), ""Outreach Conducted"", """")"),"")
A22: Alissa | B22: Meddlesaint | C22: =CONCATENATE(A22," ",B22) -> Alissa Meddlesaint | D22: 484-903-2662 | E22: ameddlesaint@gmail.com | F22: Prospective | G22: 132 | H22: {=IFERROR(INDEX('Hub CPC 226'!A:A, MATCH(C22, 'Hub CPC 226'!B:B, 0)), "")} -> 25 | I22: {=IFERROR(INDEX('Hub Users 226'!A:A, MATCH(C22, 'Hub Users 226'!B:B, 0)), "")} -> 45 | J22: STEM (Science, Technology, Engineering, Math) | K22: 8/18/23 - AT sent re-engagement message on LinkedIn. Awaiting response. 8/8/23 - AT emailed and sent re-engagement txt. Awaiting response. 4/3/23 CT sent follow up to schedule Screening Call 2/22/23 CT sent follow email to re-engage 2/9/23 CT sent re-engagement email 12/13/22 CT sent re-engagement email 5/24/22 SB sent re-engagement email 11/15/21 SB sent re-engagement email Alissa scheduled a screening call on 7/29/21 but did not show up. JPS gave her a call &amp; she said she did not realize it was on Google Meet and will schedule for another time. HH called is really interested in getting into the program would like a follow up email 7/20/21 JPS sent outreach email from Champions@speakhire.org on 7/20/21 uploaded to Kintone but marked as inactive/yellow until screening complete | L22: 43590.632 | Q22: 318 W Wilkes Barre St | R22: Easton | S22: Easton | T22: PA | U22: MAC Cosmetics | AB22: =IFERROR(__xludf.DUMMYFUNCTION("IF( ISNUMBER(MATCH( C22, IMPORTRANGE(""https://docs.google.com/spreadsheets/d/1yTh1ELC33JHYOeEdgIiEclxPRyh0zOKtlawDltfUay8"",""'Champions'!A:A""), 0 )), ""Outreach Conducted"", """")"),"")
A23: Amelia | B23: Geary | C23: =CONCATENATE(A23," ",B23) -> Amelia Geary | D23: 3472478763 | E23: ameliachamberlain@yahoo.com | F23: Inactive CPC | G23: 327 | H23: {=IFERROR(INDEX('Hub CPC 226'!A:A, MATCH(C23, 'Hub CPC 226'!B:B, 0)), "")} -> 26 | I23: {=IFERROR(INDEX('Hub Users 226'!A:A, MATCH(C23, 'Hub Users 226'!B:B, 0)), "")} -> 46 | K23: 9/30/22 Amelia emailed saying &#34;For the foreseeable future, I have very limited availability. Unfortunately, I think it best to remove me as a potential mentor for now. I?m happy to reach out in the future when things become more manageable.&#34; SB responded offering to reach out for future rounds 9/28/22 SB emailed for ellis match 7/5/22 LG called, texted for IRS availability; Amelia is never available for Summer, wants to be contacted for IR1 1/8/22 SB updated location from Lima, Peru to Barbados 12/22/21 SB sent IR2 FY21-22 schedule list for matching Unavailable for IR1 21 due to health, check for IR2 SB Amelia was trained on 10/20/2020 at 5:15 pm EST with Jennifer Peterson-Sharma Jennifer Peterson-Sharma called Amelia on 10/6/2020. She affirmed that she is available to mentor for the Round One mentoring session. She signed up for October 20 Training Webinar. Amelia was screened on 9/17/2020 by Kiesha Charles Emailed her to schedule a screening call on september 17th 2020 at 7pm Emailed on 8/31/2020 about setting up screening call | L23: 43989.603 | Q23: 85 Columbia Street, Apartment 2E | R23: Barbados | U23: Orbis International | V23: Seminars 22, Seminars 21, FY 20 - 21, FY 21 - 22 | W23: Francheska Caraballo, Aaliyah Aybar, Avril Mejia, Genesis Lochart, Ivania Posada, Licsy Reyes, Asmaa Alkhadashi, Arwa Alhaj, Yann Noumbi and Shabiha Rahman | X23: P2GManhattan, CypressHills, IHSUnionSquare, CrotonaIHS, ELLIS | AB23: =IFERROR(__xludf.DUMMYFUNCTION("IF( ISNUMBER(MATCH( C23, IMPORTRANGE(""https://docs.google.com/spreadsheets/d/1yTh1ELC33JHYOeEdgIiEclxPRyh0zOKtlawDltfUay8"",""'Champions'!A:A""), 0 )), ""Outreach Conducted"", """")"),"") | AD23: Issue 11 | AE23: 44593 | AF23: Thank you for your support letter | AG23: 50
A24: Ahmed | B24: Imam | C24: =CONCATENATE(A24," ",B24) -> Ahmed Imam | D24: 16027368545 | E24: ami2136@columbia.edu | F24: Active CPC | G24: 592 | H24: {=IFERROR(INDEX('Hub CPC 226'!A:A, MATCH(C24, 'Hub CPC 226'!B:B, 0)), "")} -> 27 | I24: {=IFERROR(INDEX('Hub Users 226'!A:A, MATCH(C24, 'Hub Users 226'!B:B, 0)), "")} -> 47 | J24: Business | K24: 12/29/23 SB reached out just to check in and touch base - hoping to re-engage 3/22/23 SB sent text for IR3 3/17/23 SB sent follow up email about IR3 3/14/23 SB emailed for IR3 wheels 12/20/22 SB followed up via email for IR2 match 12/16/22 SB emailed for IR2 queens match 10/04/22 Not available for IR1. CT 7/9/22 SB contacted for IRS match 4/27/22 Not available for Seminars in May. CT Completed Onboarding and Orientation Webinar 1/28/22 SB 01/18/22 CT sent email with training dates, handbook, instructional guide 1/17/22 SB sent screening follow up Sent screening scheduling email 1/13/22 SB | L24: 44571.864 | M24: 12 | N24: 28 | O24: 75 | P24: 3 | Q24: 230 W. 55th St #7D, New York, NY 10019 | R24: New York City | S24: New York | T24: NY | U24: Kirkland & Ellis LLP | V24: FY 21 - 22 | W24: Kenia Cholom, Afrin Tripti, Yiengchuk Dorji and Yonathan Martinez | X24: IHS Health | AB24: =IFERROR(__xludf.DUMMYFUNCTION("IF( ISNUMBER(MATCH( C24, IMPORTRANGE(""https://docs.google.com/spreadsheets/d/1yTh1ELC33JHYOeEdgIiEclxPRyh0zOKtlawDltfUay8"",""'Champions'!A:A""), 0 )), ""Outreach Conducted"", """")"),"")
A25: Abigail | B25: Mawhirter | C25: =CONCATENATE(A25," ",B25) -> Abigail Mawhirter | D25: 12547233110 | E25: amm09b@acu.edu | F25: Active CPC | G25: 445 | H25: {=IFERROR(INDEX('Hub CPC 226'!A:A, MATCH(C25, 'Hub CPC 226'!B:B, 0)), "")} -> 28 | I25: {=IFERROR(INDEX('Hub Users 226'!A:A, MATCH(C25, 'Hub Users 226'!B:B, 0)), "")} -> 48 | K25: 1/9/24 agreed to IR2, but had to drop due to health issues SB 10/5/23 Abigail expressed interests, will keep in touch about health science groups 9/18/23 WW emailed for IR1 Abigail made the #ChampionItForward video 7/24/23 Abigail reached out expressing interest in IRS, SB said we would follow up for IR1 3/30/23 texted SB, not available for IR3 but interested in IRS 3/27/23 SB sent dates of sessions - Abigail said mondays should work, checking schedule 3/21/23 SB sent text about IR3 availability - messaged back saying she would check work schedule 9/22/22 Abigail will not know her schedule until late October. She said, &#34; I do typically try to be off on Thursdays, since I tend to have other meetings at least 3 of the 4 Thursdays out of a month. Is that helpful? If not, I can still try to accommodate for the proposed Monday group?&#34; - will possibly work for Wheels. Will follow up as round gets closer and we get Wheels applications in. SB 9/20/22 match request sent to Abigail SB PQT confirmed by text on 8/4/22 for IR1 Ask her before giving her more than 3 Interns. Given Abigail's hectic working schedule at the hospital, she watched the onboarding video in replacement of attending a webinar. Abigail was screened by SU on 3/23/21 Abigail responded 2/12/21 saying she was very interested in being matched but needs a heads up on the schedule because her working hours vary every week. JPS sent her the schedules to potentially match for IR3 20-21. JPS followed up on 2/10/21 email to see if abigail could be a champion for the IR2 20-21 session JPS emailed on 2/10/2021 to schedule a screening call | L25: 44236.933 | Q25: 425 Sharron Dr, Woodway, TX 76712 | R25: Waco, TX | S25: Waco | T25: TX | U25: BSWH Hillcrest Baptist Medical Center | V25: FY 22 - 23, FY 21 - 22, FY 20 - 21 | W25: Schayna Ceballos, Tryana Hernandez, Adalbelys Polanco, Daylan Peralta, Amizo Kante, Naimatou Sefou Moussa, Lady Villa, Ilse Cotiy Tambriz, Rafialy Carrasco, Oceanne Compaore, Liccy Dubon Zamora, Raimelis Garcia, Batma Ramazanova and Zuura Ramazanova | X25: WheelsNYC, ELLIS, IHSUnionSquare, ClaremontIHS, CrotonaIHS, GWHS | AB25: =IFERROR(__xludf.DUMMYFUNCTION("IF( ISNUMBER(MATCH( C25, IMPORTRANGE(""https://docs.google.com/spreadsheets/d/1yTh1ELC33JHYOeEdgIiEclxPRyh0zOKtlawDltfUay8"",""'Champions'!A:A""), 0 )), ""Outreach Conducted"", """")"),"")
A26: Amrita | B26: Pritam | C26: =CONCATENATE(A26," ",B26) -> Amrita Pritam | D26: 4159965440 | E26: amritap4@gmail.com | F26: Active CPC | G26: 54 | H26: {=IFERROR(INDEX('Hub CPC 226'!A:A, MATCH(C26, 'Hub CPC 226'!B:B, 0)), "")} -> 29 | I26: {=IFERROR(INDEX('Hub Users 226'!A:A, MATCH(C26, 'Hub Users 226'!B:B, 0)), "")} -> 49 | J26: Law | K26: 7/18/23 WW emailed for IRS - responded not available, on maternity leave 4/26/23 SB emailed for IR2 1/13/23 SB emailed for IR2 - agreed to Monday schedule 10/05/22 Not available for IR1. Will be in India in November &amp; December but interested in Seminars. Sent her some Seminar schedules. CT 2/3/22 HJ texted her -- she had a new baby (Aayansh) and won't be available until maybe 22-23 IR1 01/05/22 CT sent follow up email for matching 12/30/21 SB sent IR2 FY21-22 schedule list for matching Amrita emailed on 1/8/2021 informing Jennifer Peterson-Sharma that she will not be available for matching until June 2021, although she would still love to be a part of the program. Norrell spoke with 05/18/2020 We need updated resume for Amrita. Her new title is: Microsoft, Software Develop Engineer, Domain is Android. Hetal called and left a voice message on 3/26/2020 | L26: 43338.743 | Q26: amritap4@gmail.com | S26: San Francisco | T26: CA | U26: Microsoft | V26: FY 22 - 23 | W26: Yancen Rodriguez and Kenry Aldana | X26: CrotonaIHS | AB26: =IFERROR(__xludf.DUMMYFUNCTION("IF( ISNUMBER(MATCH( C26, IMPORTRANGE(""https://docs.google.com/spreadsheets/d/1yTh1ELC33JHYOeEdgIiEclxPRyh0zOKtlawDltfUay8"",""'Champions'!A:A""), 0 )), ""Outreach Conducted"", """")"),"")
A27: Amy | B27: Sit | C27: =CONCATENATE(A27," ",B27) -> Amy Sit | D27: 510-501-9776 | E27: amy_sit@alumni.brown.edu | F27: Active CPC | G27: 202 | H27: {=IFERROR(INDEX('Hub CPC 226'!A:A, MATCH(C27, 'Hub CPC 226'!B:B, 0)), "")} -> 30 | I27: {=IFERROR(INDEX('Hub Users 226'!A:A, MATCH(C27, 'Hub Users 226'!B:B, 0)), "")} -> 50 | K27: Amy made the #ChampionItForward video 7/18/23 WW emailed for IRS, PQ followed up with text and call - not available for IRS, asked for IR1 3/29/23 SB sent text for IR3 11/28/22 Unavailable for IR2 - traveling in Feb. SB 10/31/22 Amy emailed SB saying, &#34; I just received word about a new workshop schedule for the next 8 weeks, I won't be available on Thursdays after all.&#34; 10/14/22 SB emailed for Wheels availability - Amy confirmed availability 1/10/22 SB sent follow up email 1/5/22 SB sent IR2 FY21-22 schedule list for matching JPS emailed on 1/5/2021 to check her engagement status. Amy responded on 1/13/2021 saying: &#34;Happy New Year! Apologies for the delay in response. In response to your questions, 1) I am still interested in being a Champion for the upcoming round, 2) I don't have a need for a refresh training at this time.&#34; Amy called Hetal back on March 24th saying she'd love to mentor during this time of COVID-19 and would love to share within her company -- knows women who would be interested Hetal called on March 19, 2020 and left a voice message to reengage. | L27: 43683.442 | M27: 9 | N27: 20 | O27: 43 | P27: 41 | Q27: 1081 Eastern Parkway Brooklyn NY 11213" | R27: NYC | S27: Brooklyn | T27: NY | U27: Capgemini Invent | V27: EY 19 - 20, FY 21 - 22, FY 20 - 21 | W27: Dema Alhuraibi, Karidjatou Kone, Fatou Diedhiou, Naim Bakere, Mingyu (Carl) Huo and Yongqiang Tan | X27: Abraham Lincoln HS, ELLIS, FlushingIHS | AB27: =IFERROR(__xludf.DUMMYFUNCTION("IF( ISNUMBER(MATCH( C27, IMPORTRANGE(""https://docs.google.com/spreadsheets/d/1yTh1ELC33JHYOeEdgIiEclxPRyh0zOKtlawDltfUay8"",""'Champions'!A:A""), 0 )), ""Outreach Conducted"", """")"),"")
A28: Amy | B28: Patel | C28: =CONCATENATE(A28," ",B28) -> Amy Patel | D28: 312-848-6508 | E28: amyp55@gmail.com | F28: Inactive CPC | G28: 45 | H28: {=IFERROR(INDEX('Hub CPC 226'!A:A, MATCH(C28, 'Hub CPC 226'!B:B, 0)), "")} -> 31 | I28: {=IFERROR(INDEX('Hub Users 226'!A:A, MATCH(C28, 'Hub Users 226'!B:B, 0)), "")} -> 51 | J28: Health Sciences/Medicine | K28: 11/28/22 unsubscribed from newsletter SB 10/18/22 CT marked as abandoned (see notes below) 5/24/22 SB sent re-engagement email 1/5/22 Unsubscribed from newsletter SB Amy responded to outreach on 5/27/21 and said: &#34;I don't have the bandwidth for this right now and do not want to commit to something I can't follow through on. I will reach out once things settle down.&#34; JPS called on 5/26/21. Amy was running into a meeting and couldn't talk, so JPS sent email. | L28: 43338.743 | Q28: 73 East Lake St, Chicago, IL 60601 | S28: Chicago | T28: IL | U28: BASF | AB28: =IFERROR(__xludf.DUMMYFUNCTION("IF( ISNUMBER(MATCH( C28, IMPORTRANGE(""https://docs.google.com/spreadsheets/d/1yTh1ELC33JHYOeEdgIiEclxPRyh0zOKtlawDltfUay8"",""'Champions'!A:A""), 0 )), ""Outreach Conducted"", """")"),"")
A29: Anya | B29: Smith | C29: =CONCATENATE(A29," ",B29) -> Anya Smith | D29: 16507850781 | E29: anakrokhina@hotmail.com | F29: Active CPC | G29: 668 | H29: {=IFERROR(INDEX('Hub CPC 226'!A:A, MATCH(C29, 'Hub CPC 226'!B:B, 0)), "")} -> 32 | I29: {=IFERROR(INDEX('Hub Users 226'!A:A, MATCH(C29, 'Hub Users 226'!B:B, 0)), "")} -> 52 | J29: Health Sciences/Medicine | K29: 1/9/24 WW LinkedIn message for IR2 Ellis 4/24/23 SB messaged Anya for IR3 - responded, &#34;I have been having a bit of a hard time personally around managing stress related to the looming layoffs and also won't know my own job status until later next month. In light of that I would prefer to not take one more right now. I do hope to help out again soon&#34; 4/18/23 SB emailed for IR3 3/6/23 CT updated phone number from ?(425) 737-8230? to &#43;16507850781 2/23/23 CT left voicemail &amp; sent text asking for Seminar 2/22/23 CT sent email asking about being Seminar Speaker for IHS Union Square 1/10/23 CT not available for IR2 because of new role at work and finishing last semester of MS degree. Asked to check in for IR3. 3/31/22 Not available for internship rounds until 2023 due to maternity leave. CT Completed Onboarding and Training 8/14/21 SB Training scheduled for 8/14/21 on 7/26/21 by SB Screened and passed on 7/21/21 by SB Her email address is under &#34;Anna&#34; but she prefers to be called &#34;Anya&#34; SB sent a screening call email on 7/12/21 | L29: 44833.453 | Q29: 5641 402nd Ave Se | R29: Snoqualmie, WA | S29: Snoqualmie | T29: WA | U29: Meta (formerly Facebook) | V29: FY 21 - 22, Seminars 22 | W29: Rasel Ali and Akira Quezada | X29: ICHSBronx, ClaremontIHS | AB29: =IFERROR(__xludf.DUMMYFUNCTION("IF( ISNUMBER(MATCH( C29, IMPORTRANGE(""https://docs.google.com/spreadsheets/d/1yTh1ELC33JHYOeEdgIiEclxPRyh0zOKtlawDltfUay8"",""'Champions'!A:A""), 0 )), ""Outreach Conducted"", """")"),"")
A30: Anya | B30: Smith | C30: =CONCATENATE(A30," ",B30) -> Anya Smith | D30: 14257378230 | E30: anakrokhina@hotmail.com | F30: Active CPC | G30: 486 | H30: {=IFERROR(INDEX('Hub CPC 226'!A:A, MATCH(C30, 'Hub CPC 226'!B:B, 0)), "")} -> 32 | I30: {=IFERROR(INDEX('Hub Users 226'!A:A, MATCH(C30, 'Hub Users 226'!B:B, 0)), "")} -> 52 | J30: STEM (Science, Technology, Engineering, Math) | K30: 3/20/23 CT Anya has a lot going on with Meta layoffs and school. Reach out after August for FY or Seminars. 3/31/22 Not available for internship rounds until 2023 due to maternity leave. CT Completed Onboarding and Training 8/14/21 SB Training scheduled for 8/14/21 on 7/26/21 by SB Screened and passed on 7/21/21 by SB Her email address is under &#34;Anna&#34; but she prefers to be called &#34;Anya&#34; SB sent a screening call email on 7/12/21 | L30: 44387.781 | Q30: 5641 402nd Ave Se | R30: Snoqualmie, WA | S30: Snoqualmie | T30: WA | U30: Meta (formerly Facebook) | V30: Seminars 22, FY 21 - 22 | W30: Rasel Ali and Akira Quezada | X30: IHSUnionSquare, ICHSBronx | AB30: =IFERROR(__xludf.DUMMYFUNCTION("IF( ISNUMBER(MATCH( C30, IMPORTRANGE(""https://docs.google.com/spreadsheets/d/1yTh1ELC33JHYOeEdgIiEclxPRyh0zOKtlawDltfUay8"",""'Champions'!A:A""), 0 )), ""Outreach Conducted"", """")"),"")
A31: Anastasia | B31: Maria Savelyeva | C31: =CONCATENATE(A31," ",B31) -> Anastasia Maria Savelyeva | D31: 917-500-4224 | E31: anastasia.msavelyeva@gmail.com | F31: Inactive CPC | G31: 134 | H31: {=IFERROR(INDEX('Hub CPC 226'!A:A, MATCH(C31, 'Hub CPC 226'!B:B, 0)), "")} -> 33 | I31: {=IFERROR(INDEX('Hub Users 226'!A:A, MATCH(C31, 'Hub Users 226'!B:B, 0)), "")} -> 53 | J31: Service/Hospitality Industry | K31: 3/1/22 SB call, leave VM and send text to check status 1/24 SB call, VM, text 01/05/22 CT sent follow up email for matching 12/30/21 SB sent IR2 FY21-22 schedule list for matching Anastasia unreachable throughout IR1 FY 21-22 communications, marking as inactive 11/15/21 SB Hetal called and left a vm on 11/8/2021 asking if she's still interested. SB sent text with Intern round schedule 11/7/21 | L31: 43590.633 | P31: 29 | Q31: 6225 84th ST C60, Rego Park | R31: New York | S31: Middle Village | T31: NY | U31: The Smith | V31: FY 19 - 20 | W31: Mamdiara Ndiaye and Nassira Cisse | X31: ELLIS | AB31: =IFERROR(__xludf.DUMMYFUNCTION("IF( ISNUMBER(MATCH( C31, IMPORTRANGE(""https://docs.google.com/spreadsheets/d/1yTh1ELC33JHYOeEdgIiEclxPRyh0zOKtlawDltfUay8"",""'Champions'!A:A""), 0 )), ""Outreach Conducted"", """")"),"")
A32: Andrew | B32: Baum | C32: =CONCATENATE(A32," ",B32) -> Andrew Baum | E32: Andrewbaum570@gmail.com | F32: Prospective | G32: 630 | H32: {=IFERROR(INDEX('Hub CPC 226'!A:A, MATCH(C32, 'Hub CPC 226'!B:B, 0)), "")} -> 34 | I32: {=IFERROR(INDEX('Hub Users 226'!A:A, MATCH(C32, 'Hub Users 226'!B:B, 0)), "")} -> 54 | J32: Health Sciences/Medicine | K32: 10/18/22 Someone name Andrew Baum with a similar email ( Baumandrew424@gmail.com) expressed interest via volunteermatch. SB called to see if it is the same Andrew. Left voice mail, followed up with email and text. (phone: &#43;13152897631) 9/15/22 Someone name Andrew Baum with a similar email ( Andrewbaum270@gmail.com) expressed interest via volunteermatch. SB emailed to see if it was the same person. Andrew scheduled screening but it was for Memorial day - so we let him know we needed to reschedule. He sent a new time. SB agreed but Andrew did not show up to the call 5/24/22 SB sent re-engagement email 3/31/22 CT emailed for IR3, rew responded and CT sent info for screening. No response | L32: 44630.438 | R32: Syracuse, NY | S32: Syracuse | T32: NY | U32: Driveline | AB32: =IFERROR(__xludf.DUMMYFUNCTION("IF( ISNUMBER(MATCH( C32, IMPORTRANGE(""https://docs.google.com/spreadsheets/d/1yTh1ELC33JHYOeEdgIiEclxPRyh0zOKtlawDltfUay8"",""'Champions'!A:A""), 0 )), ""Outreach Conducted"", """")"),"")
A33: Angana | B33: Deb | C33: =CONCATENATE(A33," ",B33) -> Angana Deb | D33: 650-495-9536 | E33: angana1985@gmail.com | F33: Inactive CPC | G33: 135 | H33: {=IFERROR(INDEX('Hub CPC 226'!A:A, MATCH(C33, 'Hub CPC 226'!B:B, 0)), "")} -> 35 | I33: {=IFERROR(INDEX('Hub Users 226'!A:A, MATCH(C33, 'Hub Users 226'!B:B, 0)), "")} -> 55 | J33: STEM (Science, Technology, Engineering, Math) | K33: 1/30/24 saw via linkedin - new job at pintrest as Lead Client Partner. Confirm when next in contact SB Angana is on maternity leave and wants to reconnect mid-2022. Angana emailed Jennifer Peterson-Sharma on 1/7/2021 stating that she cannot participate in the program this year and would like to be reach out to next year (2021-2022 program). Donated $500 in November 2019 and November 2020 through Google's Donation platform, Benevity. uploaded to Kintone but marked as inactive/yellow until screening complete | L33: 43590.633 | Q33: Google LLC, Suite 500, 121 Spear Street, CA, SF 94103 | R33: San Francisco | S33: San Francisco | T33: CA | U33: Google | V33: FY 19 - 20 | W33: Sanzida Chowdhury and Tasnim Jahan | X33: ELLIS | AB33: =IFERROR(__xludf.DUMMYFUNCTION("IF( ISNUMBER(MATCH( C33, IMPORTRANGE(""https://docs.google.com/spreadsheets/d/1yTh1ELC33JHYOeEdgIiEclxPRyh0zOKtlawDltfUay8"",""'Champions'!A:A""), 0 )), ""Outreach Conducted"", """")"),"")
A34: Angelo | B34: Rodriguez | C34: =CONCATENATE(A34," ",B34) -> Angelo Rodriguez | D34: 19174154436 | E34: angelo@nycasagroup.com | F34: Active CPC | G34: 664 | H34: {=IFERROR(INDEX('Hub CPC 226'!A:A, MATCH(C34, 'Hub CPC 226'!B:B, 0)), "")} -> 36 | I34: {=IFERROR(INDEX('Hub Users 226'!A:A, MATCH(C34, 'Hub Users 226'!B:B, 0)), "")} -> 56 | J34: Real Estate/Development | K34: 2/13/24 SB emailed for IR3 11/16/24 SB sent follow up about availability - not available, asking for IR3 1/11/24 SB called, left vm, sent text for IR2 - Angelo called back, he is traveling to visit family somewhere warm in feb. but will look at the schedule and let us know as soon as possible 1/10/24 SB emailed for IR2 Crotona 3/23/23 Angelo agreed to group and time for IR3 SB 3/22/23 Angelo emailed saying this round works but asked if there could be a time change - SB responded explaining schedules 3/21/23 SB sent Angelo text about IR3 - texted back said he would let us know by end of day 3/16/23 SB emailed for IR3 12/01/22 CT Completed Orientation &amp; Onboarding Webinar 11/30/22 CT left voicemail &amp; sent text about training 11/28/22 SB followed up and corrected training dates 11/21/22 SB followed up for training 9/27/22 passed screening with SB, sending training email Scheduled screening for 9/27/22. SB 9/22/22 SB sent screening scheduling email | L34: 44825.915 | M34: 10 | N34: 26 | O34: 52 | P34: 33 | Q34: 10 Clinton St. #4Q, Brooklyn NY 11201 | R34: Brooklyn, NY 11201 | S34: Brooklyn | T34: NY | U34: NY CASA GROUP | V34: FY 22 - 23, FY 24 - 25, Seminars 24, Seminars 23 | W34: Taliana Valencia, Nerely Roa, Michell Benavidez, Jesus (Daniel) Leon, Michell Benavidez and Jesus (Daniel) Leon | X34: CrotonaIHS, IHSUnionSquare, DeSoto 130, WheelsNYC | AB34: =IFERROR(__xludf.DUMMYFUNCTION("IF( ISNUMBER(MATCH( C34, IMPORTRANGE(""https://docs.google.com/spreadsheets/d/1yTh1ELC33JHYOeEdgIiEclxPRyh0zOKtlawDltfUay8"",""'Champions'!A:A""), 0 )), ""Outreach Conducted"", """")"),"")
A35: Anisa | B35: Shukla | C35: =CONCATENATE(A35," ",B35) -> Anisa Shukla | D35: 469-536-2287 | E35: anisa.shukla@gmail.com | F35: Inactive CPC | G35: 136 | H35: {=IFERROR(INDEX('Hub CPC 226'!A:A, MATCH(C35, 'Hub CPC 226'!B:B, 0)), "")} -> 37 | I35: {=IFERROR(INDEX('Hub Users 226'!A:A, MATCH(C35, 'Hub Users 226'!B:B, 0)), "")} -> 57 | J35: Law | K35: 5/18/22 SB sent re-engagement email 1/24/22 SB call and text 01/05/22 CT sent follow up email for matching 12/30/21 SB sent IR2 FY21-22 schedule list for matching JPS emailed on 7/22/21 via Champions@speakhire.org since it appears that Anisa has screened and possibly trained - want to check in on her status. HH text (phone disconnected when called) 7/20/2021 Sent another screening email 2/25/21. SU. Sent a screening email 2/20/21. SU Anisa passed a screening call on 7/21/2019. There is no screening form completed. She also said in an email to Scotney on 8/13/21 that she would love to be matched and that she submitted her materials in August 2019. It appears that she may have gone through training and completed an Instructional Guide, but we do not have one on file. | L35: 43590.633 | Q35: 11040 Blackhawk Drive, Texas | R35: New York, NY | S35: New York | T35: NY | U35: India Youth Fund | AB35: =IFERROR(__xludf.DUMMYFUNCTION("IF( ISNUMBER(MATCH( C35, IMPORTRANGE(""https://docs.google.com/spreadsheets/d/1yTh1ELC33JHYOeEdgIiEclxPRyh0zOKtlawDltfUay8"",""'Champions'!A:A""), 0 )), ""Outreach Conducted"", """")"),"")
A36: Anjuli | B36: Bahuguna | C36: =CONCATENATE(A36," ",B36) -> Anjuli Bahuguna | D36: -551816754 | E36: anjulibahuguna@gmail.com | F36: Active CPC | G36: 315 | H36: {=IFERROR(INDEX('Hub CPC 226'!A:A, MATCH(C36, 'Hub CPC 226'!B:B, 0)), "")} -> 38 | I36: {=IFERROR(INDEX('Hub Users 226'!A:A, MATCH(C36, 'Hub Users 226'!B:B, 0)), "")} -> 58 | J36: Health Sciences/Medicine | K36: 5/18/22 SB sent re-engagement email Anjuli Bahuguna was screened on 3/27/2020 by Dona Rehm | L36: 43913.185 | Q36: anjulibahuguna@gmail.com | R36: Dubai, United Arab Emirates | U36: KPMG Lower Gulf | AB36: =IFERROR(__xludf.DUMMYFUNCTION("IF( ISNUMBER(MATCH( C36, IMPORTRANGE(""https://docs.google.com/spreadsheets/d/1yTh1ELC33JHYOeEdgIiEclxPRyh0zOKtlawDltfUay8"",""'Champions'!A:A""), 0 )), ""Outreach Conducted"", """")"),"")
A37: Ankur | B37: Jaluria | C37: =CONCATENATE(A37," ",B37) -> Ankur Jaluria | D37: 6467891472 | E37: ankurjaluria@gmail.com | F37: Active CPC | G37: 331 | H37: {=IFERROR(INDEX('Hub CPC 226'!A:A, MATCH(C37, 'Hub CPC 226'!B:B, 0)), "")} -> 39 | I37: {=IFERROR(INDEX('Hub Users 226'!A:A, MATCH(C37, 'Hub Users 226'!B:B, 0)), "")} -> 59 | J37: Business | K37: 1/17/24 WW emailed for sponsor session 7/17/23 - SB sent email for IRS, BC called &amp; left VM, SB sent follow up text - Not available for IRS, asked for IR1 3/27/23 CT called. She's not available for the rest of the school year for FY or Seminars due to teaching. We can reach out next academic year and check in again. 3/2/23 CT sent email asking to be Speaker for BUSHWICKCHS Seminar 10/03/22 Not available for IR1 because of teaching 2 classes. Reach out for IR2. CT 4/16/22 Not available for Seminars during summer. CT Ankur informed us via email that her last name is only Jaluria now. CT 2/28/22 Ankur emailed Jennifer Peterson-Sharma on 1/7/2021 stating she will not be able to participate in the program for a month of two, but would like to continue with the program after a few months break. Should be okay to consider for round three 2020-2021, not round two. Ankur accepted match for Round One 2020, but emailed last minute with family emergency and said she could not longer accommodate the match. Ankur was trained on 9/28/2020 at 7:30 pm EST with Jennifer Peterson-Sharma and Kiesha Charles. Emailed her for a training call on for september 17th at 7pm Ankur was screened on 9/15/2020 by Kiesha Charles The Screening Call was scheduled for 9/12/2020 but Ankur emailed on 9/10/2020 to say that a family emergency has occurred and she will be unable to conduct the Screening Call on the 12th. She will be in contact with Kiesha Charles to reschedule. Emailed on 8/31/2020 about setting up screening call | L37: 44024.477 | M37: 12 | N37: 47 | O37: 75 | P37: 3 | Q37: 305 W 50th Street Apt 26C, New York, NY 10019 | R37: New York | S37: New York | T37: NY | U37: Universal McCann | V37: Seminars 22, FY 20 - 21 | W37: Allan Gonzalez, Sadi Islam, Alpha Sylla and Abrahan Castro | X37: P2GManhattan, FlushingIHS, ELLIS | AB37: =IFERROR(__xludf.DUMMYFUNCTION("IF( ISNUMBER(MATCH( C37, IMPORTRANGE(""https://docs.google.com/spreadsheets/d/1yTh1ELC33JHYOeEdgIiEclxPRyh0zOKtlawDltfUay8"",""'Champions'!A:A""), 0 )), ""Outreach Conducted"", """")"),"")
A38: Anna | B38: Carina Radulovich (D) | C38: =CONCATENATE(A38," ",B38) -> Anna Carina Radulovich (D) | D38: 7274590211 | E38: annaradulovich@gmail.com | F38: Duplicate Record | G38: 467 | H38: {=IFERROR(INDEX('Hub CPC 226'!A:A, MATCH(C38, 'Hub CPC 226'!B:B, 0)), "")} -> 40 | I38: {=IFERROR(INDEX('Hub Users 226'!A:A, MATCH(C38, 'Hub Users 226'!B:B, 0)), "")} -> 60 | K38: Anna attended a training session on 2/27/21 with JPS JPS followed up with congratulations &#43; training scheduling on 2/22/21 Screened with Sonya Uddin on 2/20/21 while Hetal Jani observed Double checked 1/26 (KW) | L38: 44291.453 | Q38: 357 Tamarack Ave, Apt B, Carlsbad | R38: Carlsbad, CA | S38: Carlsbad | T38: CA | V38: Seminars 22, Seminars 21, FY 20 - 21 | W38: Hasly Cortes, Juliana Cáceres, Joanna Veletanga, Khondoker Rahman, Xiuyan Piao and Leila Titikpina | X38: ClaremontIHS, ICHSBronx, FlushingIHS, ELLIS | AB38: =IFERROR(__xludf.DUMMYFUNCTION("IF( ISNUMBER(MATCH( C38, IMPORTRANGE(""https://docs.google.com/spreadsheets/d/1yTh1ELC33JHYOeEdgIiEclxPRyh0zOKtlawDltfUay8"",""'Champions'!A:A""), 0 )), ""Outreach Conducted"", """")"),"")
A39: Anna | B39: Butuzova | C39: =CONCATENATE(A39," ",B39) -> Anna Butuzova | D39: 8579282687 | E39: annibutuzova@gmail.com | F39: Active CPC | G39: 306 | H39: {=IFERROR(INDEX('Hub CPC 226'!A:A, MATCH(C39, 'Hub CPC 226'!B:B, 0)), "")} -> 41 | I39: {=IFERROR(INDEX('Hub Users 226'!A:A, MATCH(C39, 'Hub Users 226'!B:B, 0)), "")} -> 61 | J39: Law | K39: 6/29/23 Anna B confirmed group for IRS SB 6/28/23 Anna B emailed that schedule should work, SB sending About Interns to confirm group 6/27/23 SB called Anna B and left a voicemail 6/26/23 SB sent Anna google voice message about IRS times 6/22/23 Anna had emailed in response to the newsletter saying she is potentially available for IRS, SB responded with session time info to confirm 4/17/23 not available for IR3 SB 1/23/23 CT not available for IR2, looking for a job currently 1/23/23 CT updated professional references &amp; asked for IR2 availability 11/3/22 SB asked for bronx/qpa 10/20/22 Wheels time too early for Anna SB 10/19/22 SB emailed for Wheels availability 9/14/22 Might be available for IR1 depending on school schedule. CT Reach out to about professional references in January 23. She's applying for green card / work authorization in US and absent at work right now. CT 8/29/22 Completed onboarding and orientation webinar on 11/5/21 SB Doubled Checked 1/19 (KW) emailed her on august 28th to set up training and never replied followed up with her September 3rd and still no response. Anna was screened on 3/5/2020 by Dona Rehm | L39: 43879.623 | Q39: "I have just moved to San Rafael, CA. | R39: San Rafael, CA | S39: San Rafael | T39: CA | U39: Jackrabbit LX | V39: FY 22 - 23, FY 23 - 24, FY 21 - 22 | W39: Jayde Smoak, Skirlie De La Cruz, Raghd Salah, Assetou (Assia) Sacko, Naomi Nolasco, Jatziry Guity, Phue Naing, Romina Sulaimonova, Genesis Lochart, Xuyuan Zhao, Julia Pontes and Osvaldo Rodriguez | X39: QueensPrepAcad, ICHSBronx, NYC Mission - Emma Lazarus, IHSUnionSquare | AB39: =IFERROR(__xludf.DUMMYFUNCTION("IF( ISNUMBER(MATCH( C39, IMPORTRANGE(""https://docs.google.com/spreadsheets/d/1yTh1ELC33JHYOeEdgIiEclxPRyh0zOKtlawDltfUay8"",""'Champions'!A:A""), 0 )), ""Outreach Conducted"", """")"),"")
A40: Annie | B40: Camey Kuo | C40: =CONCATENATE(A40," ",B40) -> Annie Camey Kuo | D40: 16267551726 | E40: anniecameykuo@gmail.com | F40: Active CPC | G40: 531 | H40: {=IFERROR(INDEX('Hub CPC 226'!A:A, MATCH(C40, 'Hub CPC 226'!B:B, 0)), "")} -> 42 | I40: {=IFERROR(INDEX('Hub Users 226'!A:A, MATCH(C40, 'Hub Users 226'!B:B, 0)), "")} -> 62 | J40: STEM (Science, Technology, Engineering, Math) | K40: Led CCC 1/26/23 12/28/21 SB sent IR2 FY21-22 schedule list for matching Hetal created Annie's record after she confirmed she could step on for a Mandarin match 10/29/21 | L40: 44498.755 | R40: San Francisco | S40: San Francisco | T40: CA | U40: Stanford University | V40: FY 21 - 22 | W40: Abdulghani Ali, Yasmine El Himdi, Mayerli Torres, Yeling Lin, Yafei Huang and Valentina Jaque | X40: IHS Lafayette, FlushingIHS | AB40: =IFERROR(__xludf.DUMMYFUNCTION("IF( ISNUMBER(MATCH( C40, IMPORTRANGE(""https://docs.google.com/spreadsheets/d/1yTh1ELC33JHYOeEdgIiEclxPRyh0zOKtlawDltfUay8"",""'Champions'!A:A""), 0 )), ""Outreach Conducted"", """")"),"") | AD40: Issue 5, Issue 6, Issue 7, Issue 8, Issue 9, Issue 10, Issue 11 | AE40: Issue 6,7 - 12/14/20 Issue 8,9,10,11 - 2/8/22 | AF40: Thank you for your support letter | AG40: Issue 8,9,10,11 - 2500 + $50 Summit ticket
A41: April | B41: Carter | C41: =CONCATENATE(A41," ",B41) -> April Carter | D41: 14695712068 | E41: april.l.carter@gmail.com | F41: Active CPC | G41: 557 | H41: {=IFERROR(INDEX('Hub CPC 226'!A:A, MATCH(C41, 'Hub CPC 226'!B:B, 0)), "")} -> 43 | I41: {=IFERROR(INDEX('Hub Users 226'!A:A, MATCH(C41, 'Hub Users 226'!B:B, 0)), "")} -> 63 | J41: Arts/Creative | K41: 3/8/24 WW emailed for IR3 1/10/24 SB emailed for IR2 Crotona 2/28/23 CT sent email asking to take over Wheels group for IR2 Tried reaching out for FY 21-22 IR2 but wasn't able to confirm; Hetal emailed her saying we'd be in touch for the next round 4/13/22 12/20/21 completed onboarding training with SB and CT, waiting for Instructional Guide and onboarding materials, sent email asking for it 12/21 12/13/21 SB sent follow up SB sent Congrats on 12/9/21 12/6/21 passed screening SB 11/29/21 SB sent April screening scheduling email | L41: 44529.482 | Q41: 421 S 321st Street, C2, Federal Way, WA 98003 | R41: London, United Kingdom | S41: Federal Way | T41: WA | U41: IBM | AB41: =IFERROR(__xludf.DUMMYFUNCTION("IF( ISNUMBER(MATCH( C41, IMPORTRANGE(""https://docs.google.com/spreadsheets/d/1yTh1ELC33JHYOeEdgIiEclxPRyh0zOKtlawDltfUay8"",""'Champions'!A:A""), 0 )), ""Outreach Conducted"", """")"),"")
A42: Astha | B42: Rajvanshi | C42: =CONCATENATE(A42," ",B42) -> Astha Rajvanshi | D42: 9174462015 | E42: ar3541@columbia.edu | F42: Active CPC | G42: 15 | H42: {=IFERROR(INDEX('Hub CPC 226'!A:A, MATCH(C42, 'Hub CPC 226'!B:B, 0)), "")} -> 44 | I42: {=IFERROR(INDEX('Hub Users 226'!A:A, MATCH(C42, 'Hub Users 226'!B:B, 0)), "")} -> 64 | J42: Social Sciences/Psychology | K42: Double checked 1/26 (KW) | L42: 43338.743 | Q42: ar3541@columbia.edu | U42: Institute of Current World Affairs | V42: FY 17 - 18 | W42: Cristal Davidson | X42: American History | AB42: =IFERROR(__xludf.DUMMYFUNCTION("IF( ISNUMBER(MATCH( C42, IMPORTRANGE(""https://docs.google.com/spreadsheets/d/1yTh1ELC33JHYOeEdgIiEclxPRyh0zOKtlawDltfUay8"",""'Champions'!A:A""), 0 )), ""Outreach Conducted"", """")"),"")
A43: Arturo | B43: Paniagua | C43: =CONCATENATE(A43," ",B43) -> Arturo Paniagua | D43: 12097126225 | E43: arturo.paniagua@premiernutrition.com | F43: Active CPC | G43: 563 | H43: {=IFERROR(INDEX('Hub CPC 226'!A:A, MATCH(C43, 'Hub CPC 226'!B:B, 0)), "")} -> 45 | I43: {=IFERROR(INDEX('Hub Users 226'!A:A, MATCH(C43, 'Hub Users 226'!B:B, 0)), "")} -> 65 | J43: Health Sciences/Medicine | K43: 1/12/24 Arturo emailed back saying he is still adjusting to new job but to reach out for future rounds SB 1/11/23 SB sent email about IR2 Crotona 11/3/23 Arturo messaged, &#34; I changed jobs about 3 weeks ago and working now at Premier Nutrition. My email is arturo.paniagua@premiernutrition. Right now I can't committ to anything for like another 2-3 months due to the changing of jobs and the learning curve. Please keep in touch and will let you know how things are progressing&#34; SB - changing email. Get all new job info when he agrees to next match 11/1/23 WW follow up; Arturo no longer works at CSAA 10/31/23 SB sent text for IR1 10/30/23 SB emailed for IR1 4/17/23 SB emailed for IR3 2/28/23 CT sent email asking to take over Wheels group for IR2 7/14/22 SB messaged for match 4/1/22 On vacation until April 19th without any electronic devices. CT 3/14/22 Not available for IR3 due to very busy work schedule in April. Reach out for next round. CT Completed Onboarding and Orientation Webinar 1/28/22 SB 12/21/21 SB sent IR2 FY21-22 schedule list for matching He will send an email with information about a quarterly meeting from CSAA and thinks it would be great if we pitch in for 5-10 min to talk about SPEAKHIRE and maybe get more Champions that way. 12/16/2021 CT Passed screening, sent congrats email &amp; possible IR1 12/16/2021 CT Sent screening email 12/07/21 CT | L43: 44537.619 | Q43: arturo.paniagua@premiernutrition | U43: Premier Nutrition | V43: FY 21 - 22 | W43: Mishelle Carol and Bairon Villanueva | X43: FlushingIHS | AB43: =IFERROR(__xludf.DUMMYFUNCTION("IF( ISNUMBER(MATCH( C43, IMPORTRANGE(""https://docs.google.com/spreadsheets/d/1yTh1ELC33JHYOeEdgIiEclxPRyh0zOKtlawDltfUay8"",""'Champions'!A:A""), 0 )), ""Outreach Conducted"", """")"),"")
A44: Asha | B44: Nair | C44: =CONCATENATE(A44," ",B44) -> Asha Nair | D44: 7324213309 | E44: ashagnair@gmail.com | F44: Inactive CPC | G44: 11 | H44: {=IFERROR(INDEX('Hub CPC 226'!A:A, MATCH(C44, 'Hub CPC 226'!B:B, 0)), "")} | I44: {=IFERROR(INDEX('Hub Users 226'!A:A, MATCH(C44, 'Hub Users 226'!B:B, 0)), "")} -> 66 | J44: Health Sciences/Medicine | K44: 01/05/22 CT sent follow up email for matching 12/30/21 SB sent IR2 FY21-22 schedule list for matching Double checked 1/26 (KW) Hetal asked about mentoring FY 20-21 MR1, but Asha said work and personal life hectic; list as inactive and she will reach out to us in the future if she can be a SPEAK Mentor again Hetal messaged on March 19th -- Doctor so difficult during COVID 19, but she will share the message One of the first mentors of SPEAK. Best to contact by phone. | L44: 43338.743 | Q44: 20 Child Street, Apartment 813, Cambridge MA 02141 | S44: Cambridge | T44: MA | U44: Stanford health | V44: FY 17 - 18 | W44: Daya Stanley and Hannah John | X44: GWHS | AB44: =IFERROR(__xludf.DUMMYFUNCTION("IF( ISNUMBER(MATCH( C44, IMPORTRANGE(""https://docs.google.com/spreadsheets/d/1yTh1ELC33JHYOeEdgIiEclxPRyh0zOKtlawDltfUay8"",""'Champions'!A:A""), 0 )), ""Outreach Conducted"", """")"),"")
A45: Anna | B45: Stolbova | C45: =CONCATENATE(A45," ",B45) -> Anna Stolbova | D45: 321-696-3065 | E45: ast@isdglobal.org | F45: Prospective | G45: 137 | H45: {=IFERROR(INDEX('Hub CPC 226'!A:A, MATCH(C45, 'Hub CPC 226'!B:B, 0)), "")} -> 47 | I45: {=IFERROR(INDEX('Hub Users 226'!A:A, MATCH(C45, 'Hub Users 226'!B:B, 0)), "")} -> 67 | J45: Law | K45: 3/9/23 CT sent follow up to schedule screening 2/27/23 CT sent follow up to schedule screening 2/21/23 CT sent follow up email regarding Screening Call 2/14/23 CT talked to Anna over phone. She wants to participate in Seminars and FY. She's busy right now but probably available for IR3. Sent screening call email &amp; asked for updated information to update her profile. 2/13/23 CT schedule info phone call for 2/14/23 2/13/23 CT left voicemail &amp; sent text 2/9/23 CT sent re-engagement email, email bounced back 5/24/22 SB sent re-engagement email 3/1/22 SB called, left VM, sent text Hetal updated her profile job title from Senior Manager of Client Services to what it is now and the company name from Graphika to what it is now and reached her on LinkedIn to see if she's interested still (11/18/21) HH email 8/5/21, HH email (voicemail box is full) 7/29/21, HH voicemail/text 7/20/21 uploaded to Kintone but marked as inactive/yellow until screening complete | L45: 43590.633 | Q45: Brooklyn, NY | R45: Brooklyn, NY | S45: Brookyl | T45: NY | U45: Ethyka | AB45: =IFERROR(__xludf.DUMMYFUNCTION("IF( ISNUMBER(MATCH( C45, IMPORTRANGE(""https://docs.google.com/spreadsheets/d/1yTh1ELC33JHYOeEdgIiEclxPRyh0zOKtlawDltfUay8"",""'Champions'!A:A""), 0 )), ""Outreach Conducted"", """")"),"")
A46: AUGUSTO | B46: SALCEDO | C46: =CONCATENATE(A46," ",B46) -> AUGUSTO SALCEDO | D46: 51933538927 | E46: augustosalcedo76@gmail.com | F46: Active CPC | G46: 500 | H46: {=IFERROR(INDEX('Hub CPC 226'!A:A, MATCH(C46, 'Hub CPC 226'!B:B, 0)), "")} -> 48 | I46: {=IFERROR(INDEX('Hub Users 226'!A:A, MATCH(C46, 'Hub Users 226'!B:B, 0)), "")} -> 68 | J46: Arts/Creative | K46: 10/5/23 SB emailed to confirm IR1 availability - confirmed availability, will send about Intern group when we get the applications 8/18/23 Augusto asked to stay with current school (ICHS Bronx) for IR1, SB responded saying may be possible and also offering Crotona 7/18/23 PQ called for IRS - agreed to match and group 7/17/23 SB send email for IRS 3/14/23 CT not able to continue with IR2 due to being very busy, text with PT 1/12/23 CT sent about Interns email 1/12/23 agreed to wheels schedule for IR2 SB 1/10/23 SB sent follow up email about Wheels schedule 1/6/23 emailed SB that Wednesdays did not work and asked for Thursdays - SB sent the Wheels schedule 1/4/23 SB emailed for IR2 Union Square 11/29/22 Augusto confirmed for R2 -- Wheels and possibly Mondays 3pm (Crotona-QPA- ICHSB- US maybe) SB 11/16/22 Unavailable for IR1 - traveling for work through December 8/12/22 Interested in IR1 SB 1/22 Augusto jumped in to help with Seminars, was ready and excited to help with anything SB 1/6/22 SB followed up 12/22/21 SB sent IR2 FY21-22 schedule list for matching Completed training 11/12/21 SB Completed screening 11/9/21 SB Can be contacted via whats app Missed screening call on 9/22/21 - I think it was confusion from time zones. Sent rescheduling email SB Screening scheduling email sent 9/20/21 SB | L46: 44456.669 | Q46: 1390 BOLIVAR AVE. APT. 301 A | R46: LIMA PERU | U46: ECOLAB | V46: Seminars 22, FY 23 - 24, FY 21 - 22 | W46: Josue Martinez, Julian Duarte, Andy Caba, Jeter Perez, Miguel Angel Duarte Guiterrez, Lia Luciano, Angel Guzman, Joustin Hiraldo, Rafat Galeana, Lisbeth Peña, Katherine Ruano, Sandy Mercedes, Omairi Cruz Tejada, Slinne Cruz, Diego Rojas, Vilma Coc Pop, Andres Munoz, Mathews Huacon, Tatiana Cardona, Wilberto Velasquez, Daniela Gonzalez, Mishelle Carol and Elian Acosta | X46: CrotonaIHS, FlushingIHS | AB46: =IFERROR(__xludf.DUMMYFUNCTION("IF( ISNUMBER(MATCH( C46, IMPORTRANGE(""https://docs.google.com/spreadsheets/d/1yTh1ELC33JHYOeEdgIiEclxPRyh0zOKtlawDltfUay8"",""'Champions'!A:A""), 0 )), ""Outreach Conducted"", """")"),"")
A47: Muhammad | B47: Awais | C47: =CONCATENATE(A47," ",B47) -> Muhammad Awais | E47: awaisyad99@gmail.com | F47: Active CPC | G47: 726 | H47: {=IFERROR(INDEX('Hub CPC 226'!A:A, MATCH(C47, 'Hub CPC 226'!B:B, 0)), "")} -> 49 | I47: {=IFERROR(INDEX('Hub Users 226'!A:A, MATCH(C47, 'Hub Users 226'!B:B, 0)), "")} -> 69 | J47: Business | K47: 10/12/23 WW emailed for checking/providing reference contacts since no response; WW follow-up again 11/13/23 5/12/23 completed training with SB and WW (note: left after video and did not say anything, we followed up with an email with information he missed) 5/10/23 SB followed up via email for training -signed up for training 5/12 5/8/23 passed screening with SB, congrats/training sent 5/4/23 SB sent follow up screening email May not have relevant US experience for FY, SB sending screening email 5/1/23 | L47: 45047.594 | R47: Lahore, Pakistan | U47: Techno Control Corporation | AB47: =IFERROR(__xludf.DUMMYFUNCTION("IF( ISNUMBER(MATCH( C47, IMPORTRANGE(""https://docs.google.com/spreadsheets/d/1yTh1ELC33JHYOeEdgIiEclxPRyh0zOKtlawDltfUay8"",""'Champions'!A:A""), 0 )), ""Outreach Conducted"", """")"),"")
A48: Aya | B48: Elawad | C48: =CONCATENATE(A48," ",B48) -> Aya Elawad | D48: 85262069177 | E48: ayamohamed22@lpcuwc.edu.hk | F48: Prospective | G48: 586 | H48: {=IFERROR(INDEX('Hub CPC 226'!A:A, MATCH(C48, 'Hub CPC 226'!B:B, 0)), "")} -> 50 | I48: {=IFERROR(INDEX('Hub Users 226'!A:A, MATCH(C48, 'Hub Users 226'!B:B, 0)), "")} -> 70 | J48: Health Sciences/Medicine | K48: SB screened - needs more experience Aya is an 18 year old student, not sure if she has any US experience. But she speaks Arabic. Going to schedule a screening and frame it more towards Seminars. 1/6/22 SB 1/6/22 SB sent screening invite email | L48: 44567.326 | Q48: 10? Sai Sha Rd, Ma On Shan | R48: Hong Kong | U48: N/A | AB48: =IFERROR(__xludf.DUMMYFUNCTION("IF( ISNUMBER(MATCH( C48, IMPORTRANGE(""https://docs.google.com/spreadsheets/d/1yTh1ELC33JHYOeEdgIiEclxPRyh0zOKtlawDltfUay8"",""'Champions'!A:A""), 0 )), ""Outreach Conducted"", """")"),"")
A49: Dima | B49: Al Ayderous | C49: =CONCATENATE(A49," ",B49) -> Dima Al Ayderous | D49: 310-806-3571 | E49: ayd.dima@yahoo.com | F49: Active CPC | G49: 143 | H49: {=IFERROR(INDEX('Hub CPC 226'!A:A, MATCH(C49, 'Hub CPC 226'!B:B, 0)), "")} -> 51 | I49: {=IFERROR(INDEX('Hub Users 226'!A:A, MATCH(C49, 'Hub Users 226'!B:B, 0)), "")} -> 71 | J49: Armed Services/Law Enforcement | K49: Not available for IR1. CT 8/25/22 3/21/22 Not available for IR3 CT 12/30/21 SB sent IR2 FY21-22 schedule list for matching Dima said to reach out to her again in November 2021 Dima replied to outreach on 2/22/21, saying that she just had a baby and would not be able to do SPEAKHIRE while caring for a newborn. JPS followed up asking when would be a good time to reach back out. JPS sent email on 2/22/21 to gauge Dima's availability for a possible IR2 2020-2021 match | L49: 43590.635 | Q49: 1 Shoal CT | R49: Sacramento | S49: Sacramento | T49: CA | U49: Sacramento Native American Health Center | V49: FY 19 - 20, FY 21 - 22 | W49: Nassira Cisse, Afrida Ahmed, Aura Caraballo, Gabriel Morris and Paula Astudillo | X49: ELLIS, IHSUnionSquare | AB49: =IFERROR(__xludf.DUMMYFUNCTION("IF( ISNUMBER(MATCH( C49, IMPORTRANGE(""https://docs.google.com/spreadsheets/d/1yTh1ELC33JHYOeEdgIiEclxPRyh0zOKtlawDltfUay8"",""'Champions'!A:A""), 0 )), ""Outreach Conducted"", """")"),"")
A50: Azikiwe | B50: Rich | C50: =CONCATENATE(A50," ",B50) -> Azikiwe Rich | D50: 9179741379 | E50: azikiwe.rich@gmail.com | F50: Active CPC | G50: 646 | H50: {=IFERROR(INDEX('Hub CPC 226'!A:A, MATCH(C50, 'Hub CPC 226'!B:B, 0)), "")} | I50: {=IFERROR(INDEX('Hub Users 226'!A:A, MATCH(C50, 'Hub Users 226'!B:B, 0)), "")} -> 72 | J50: Arts/Creative | K50: 1/19/24 WW emailed for 2024 ccc 1/9/24 WW emailed for IR2 Ellis 8/18/23 HJ saw via linked in Azikiwe was appointed to the DOT's Advisory Committee, SB emailed to congratulate and to confirm any new job title/info 3/22/23 stronger Interns for next match (current ones are not participating and he feels very discouraged) SB 3/2/23 CT sent email asking to be Speaker for BUSHWICKCHS Seminar 2/21/23 job updated for Executive Director of NYC dept of transportation - CT emailed to congratulate and to ask for updated job information Not available for Feb 8th and Mar 8th session because of important monthly meeting 1/12/23 CT Complete in CPC Orientation &amp; Onboarding Webinar 1/5/23 CT had phone call with Azikiwe. He's available for IR2 &amp; added to CPC Training prior to start of FY Round. Sent over Handbook &amp; Instructional Guide along with more information. 1/5/23 CT scheduled phone call to discuss FY details 12/26/22 CT sent follow up CT for IR2 12/20/22 CT sent follow up for IR2 12/12/22 CT asked for IR2 availability with wheels schedule 10/27/22 Did not show for CPC Orientation &amp; Onboarding Training due to personal conflict. Sent email with more training dates. CT 9/6/22 passed screening SB | L50: 44678.581 | Q50: 155 Washington Street, Jersey City, NJ 07302 | R50: New Jersey | S50: Jersey City | T50: NJ | U50: NYC Department of Transportation | V50: FY 22 - 23, Seminars 22 | W50: Diarra Fall and Christopher Auquilla | X50: IHSUnionSquare, P2GBronx | AB50: =IFERROR(__xludf.DUMMYFUNCTION("IF( ISNUMBER(MATCH( C50, IMPORTRANGE(""https://docs.google.com/spreadsheets/d/1yTh1ELC33JHYOeEdgIiEclxPRyh0zOKtlawDltfUay8"",""'Champions'!A:A""), 0 )), ""Outreach Conducted"", """")"),"")
A51: Sara | B51: Benavent | C51: =CONCATENATE(A51," ",B51) -> Sara Benavent | D51: 33673503357 | E51: benavent.sara@gmail.com | F51: Inactive CPC | G51: 432 | H51: {=IFERROR(INDEX('Hub CPC 226'!A:A, MATCH(C51, 'Hub CPC 226'!B:B, 0)), "")} -> 53 | I51: {=IFERROR(INDEX('Hub Users 226'!A:A, MATCH(C51, 'Hub Users 226'!B:B, 0)), "")} -> 73 | K51: 10/30/23 WW tried to call her - no vm set/ can?t text probably because it?s a French number? 10/20/23 SB emailed for IR1 01/28/22 About to give birth to second baby and won't be able to continue being a Champion in the coming year (s). (email to Hetal) CT 12/22/21 SB sent IR2 FY21-22 schedule list for matching Sara was screened on 1/21/21 by Jennifer Peterson-Sharma | L51: 44218.499 | Q51: 273 Rue du Lavoir, 73310 Motz, France | U51: Orbis International | V51: FY 20 - 21 | W51: Jaiahna Gadsden, Jeimery Sosa, Raderly Morel and Oskarina Cepeda | X51: CypressHills, CrotonaIHS | AB51: =IFERROR(__xludf.DUMMYFUNCTION("IF( ISNUMBER(MATCH( C51, IMPORTRANGE(""https://docs.google.com/spreadsheets/d/1yTh1ELC33JHYOeEdgIiEclxPRyh0zOKtlawDltfUay8"",""'Champions'!A:A""), 0 )), ""Outreach Conducted"", """")"),"")
A52: Benjamin | B52: Curtis | C52: =CONCATENATE(A52," ",B52) -> Benjamin Curtis | D52: 17206081229 | E52: benjaminwcurtis@yahoo.com | F52: Inactive CPC | G52: 492 | H52: {=IFERROR(INDEX('Hub CPC 226'!A:A, MATCH(C52, 'Hub CPC 226'!B:B, 0)), "")} -> 54 | I52: {=IFERROR(INDEX('Hub Users 226'!A:A, MATCH(C52, 'Hub Users 226'!B:B, 0)), "")} -> 74 | J52: Social Sciences/Psychology | K52: &#34;Thanks for the message. Please don't contact my references at this time, in fact, it would be best if you just take me off your list for now. I'll inquire again if I'm interested in participating in the future.&#34; CT 08/10/22 Hetal spoke with Ben 1/17/22 since he said he didn't feel like he was a good fit for this population; she explained he was matched on language support which he said wasn't made clear. No other objections, but he felt this wasn't the right fit for him at this time, but maybe he can consider it again. Try again in March for FY21.22 IR3 and see what he says. 11/9/21 Completed onboarding and orientation webinar SB Busy in September 2021, email to schedule training in October SB Passed screening on 8/24/21 SB WhatsApp: &#43;385 98 967 0519 Sent screening scheduling email 8/24/21 SB | L52: 44431.654 | Q52: 8029 12th Ave NE Seattle WA 98115 | R52: Seattle and Prague | S52: Seattle | T52: WA | U52: Development Insights Partners and Rick Steves' Europe | V52: FY 21 - 22 | W52: Ancly Tzul and Fredis Chavez Portillo | X52: FlushingIHS | AB52: =IFERROR(__xludf.DUMMYFUNCTION("IF( ISNUMBER(MATCH( C52, IMPORTRANGE(""https://docs.google.com/spreadsheets/d/1yTh1ELC33JHYOeEdgIiEclxPRyh0zOKtlawDltfUay8"",""'Champions'!A:A""), 0 )), ""Outreach Conducted"", """")"),"")
A53: Bhakti | B53: Pitre | C53: =CONCATENATE(A53," ",B53) -> Bhakti Pitre | D53: 7815021841 | E53: bhaktipitre1084@gmail.com | F53: Active CPC | G53: 718 | H53: {=IFERROR(INDEX('Hub CPC 226'!A:A, MATCH(C53, 'Hub CPC 226'!B:B, 0)), "")} -> 55 | I53: {=IFERROR(INDEX('Hub Users 226'!A:A, MATCH(C53, 'Hub Users 226'!B:B, 0)), "")} -> 75 | J53: Law | K53: 05/10/24 - AT emailed re social media contribution. 12/8/23 stepping down from SPEAKHIRE board 5/23/23 CT Completed CPC Orientation &amp; Onboarding Webinar 5/10/23 Bhakti confused about references, HJ said other board member will talk to her and to snooze until July 2023 4/28/23 SB texted about training 4/24/23 SB sent text for training 4/6/23 confirmed group for IR3 SB 4/5/23 completed screening form on her own - HJ okayed this. Board member | L53: 45019.601 | Q53: Hayward California 94544, United States | R53: California | S53: Hayward | T53: CA | U53: ServiceNow | V53: FY 22 - 23 | W53: Yannick Diaby, Ana Almeida and Diarra Fall | X53: IHSUnionSquare | AB53: =IFERROR(__xludf.DUMMYFUNCTION("IF( ISNUMBER(MATCH( C53, IMPORTRANGE(""https://docs.google.com/spreadsheets/d/1yTh1ELC33JHYOeEdgIiEclxPRyh0zOKtlawDltfUay8"",""'Champions'!A:A""), 0 )), ""Outreach Conducted"", """")"),"") | AD53: Issue 11 | AE53: Issue 11 - 2/19/22 | AF53: Thank you for your support letter | AG53: Issue 11 - 50
A54: Bhavna | B54: Mohan Agnihotri | C54: =CONCATENATE(A54," ",B54) -> Bhavna Mohan Agnihotri | D54: 1 212 318 3061 | E54: bhavna.agnihotri@nortonrosefulbright.com | F54: Active CPC | G54: 26 | H54: {=IFERROR(INDEX('Hub CPC 226'!A:A, MATCH(C54, 'Hub CPC 226'!B:B, 0)), "")} -> 56 | I54: {=IFERROR(INDEX('Hub Users 226'!A:A, MATCH(C54, 'Hub Users 226'!B:B, 0)), "")} -> 76 | J54: STEM (Science, Technology, Engineering, Math) | K54: 4/14/2026 KW updated phone number from 646-404-4739 to +1 212 318 3061, email from Bhavna.agnihotri@aig.com to bhavna.agnihotri@nortonrosefulbright.com 2/8/24 WW emailed for IR3 Spanish only conversational, not fluent 4/26/23 SB messaged Bhavna for IR3, she replied to email asking for session dates. SB responded with them. - agreed to time, SB sent about 4/25/23 SB emailed for IR3 12/08/22 CT Bhavna confirmed availability for Wheels IR2 12/08/22 CT sent Wheels schedule for IR 2 8/15/22 SB followed up for email update. Bhavna out of country till September. SB asked about IR1 availability. She said year end is hectic for her, but she is interested in IR2 8/15/22 SB updated email to Bhavna.agnihotri@aig.com from bhavna_agnihotri@swissre.com 8/11/22 SB messaged Bhavna because her email is bouncing back, asked for updated one. 7/7/22 SB sent text for IRS match 7/5/22 SB sent email for match 12/22/21 SB sent IR2 FY21-22 schedule list for matching secondary email: bhavna.agnihotri@gmail.com | L54: 43338.743 | M54: 6 | N54: 14 | O54: 28 | P54: 29 | Q54: 73-20 Austin St #2F, Forest Hills NY 11375 | R54: New York | S54: Forest Hills | T54: NY | U54: Norton Rose Fulbright US LLP | V54: FY 17 - 18, FY 22 - 23, FY 20 - 21, FY 21 - 22, FY 23 - 24 | W54: Saima Akter, Noashin Sarker, Tariana Garcia Encarnacion, Marina Diaz, Claudia Herazo, Jose Sanan, Asmaa Alkhadashi, Tasnim Jahan, Eliana Cabral, Chanely Astacio, Ilsy Hernandez, Angelo De La Cruz, Rana Musleh, Tryana Hernandez, Aaliyah Escalante, Jaylenn Ortega, Wendinso Kabore, Emiliano Hernandez, Fatuma Bulloh and Reinalis Ayala | X54: ELLIS, CrotonaIHS, IHS Health, WheelsNYC, American History | AB54: =IFERROR(__xludf.DUMMYFUNCTION("IF( ISNUMBER(MATCH( C54, IMPORTRANGE(""https://docs.google.com/spreadsheets/d/1yTh1ELC33JHYOeEdgIiEclxPRyh0zOKtlawDltfUay8"",""'Champions'!A:A""), 0 )), ""Outreach Conducted"", """")"),"")
A55: Bindu | B55: Krishna | C55: =CONCATENATE(A55," ",B55) -> Bindu Krishna | D55: 19177150901 | E55: bindu.krishna@gmail.com | F55: Active CPC | G55: 609 | H55: {=IFERROR(INDEX('Hub CPC 226'!A:A, MATCH(C55, 'Hub CPC 226'!B:B, 0)), "")} -> 57 | I55: {=IFERROR(INDEX('Hub Users 226'!A:A, MATCH(C55, 'Hub Users 226'!B:B, 0)), "")} -> 77 | J55: Law | K55: 3/30/23 texted SB back asking about dates - SB sent - tried to make it work but would have to reschedule too much 3/28/23 SB sent text about IR3 1/23/23 SB emailed Bindu thank you for IR2 for Ellis - &#34;I have some travel coming up so I'm not sure that I can commit to a round at this time. I'd hate to keep cancelling as that was a problem even with this past round.&#34; 10/17/22 Can confirm Wheels but not for &#34;11/3 and 11/10 as I?m out of the country those dates on vacation&#34; - Confirm Bindu for a reschedule of 1.5 hour double session for the first two -- but match her to a group that applies a bit later. SB 10/14/22 SB emailed for availability for Wheels She's travelling in November but might be available for IR1 depending on schedule. Provide her with school schedule as soon as we have it. CT 8/23/22 7/12/22 Bindu confirmed match for IRS SB 7/7/22 LG called, emailed for IRS availability Completed Onboarding and Orientation Webinar 1/28/22 SB 01/25/22 Passed Screening CT 01/24/22 Sent Screening Call &amp; CPC Training email CT | L55: 44585.737 | Q55: 1600 15th St. Apt 502 | R55: San Francisco, CA | S55: San Francisco | T55: CA | U55: Havas Gemini, Havas Health & You | V55: FY 21 - 22, FY 22 - 23, FY 23 - 24 | W55: Francis Calderon, Fabiana Justiniano, Zihan Zhang, Ziyi Lin, Ismatu Barry, Gabriela Pena, Karla Arriola, Johalyn Perez, Matthew Vargas, Heiscelys Campusano, Rowena Otero, Shanick De Leon, Anais Martinez, Israel Martinez, Kimberly Paulino, Alejandra Minan Rodriguez, Mayra Poma and Erick Cuzco Cualchi | X55: FlushingIHS, ICHSBronx, WheelsNYC, IHSUnionSquare | AB55: =IFERROR(__xludf.DUMMYFUNCTION("IF( ISNUMBER(MATCH( C55, IMPORTRANGE(""https://docs.google.com/spreadsheets/d/1yTh1ELC33JHYOeEdgIiEclxPRyh0zOKtlawDltfUay8"",""'Champions'!A:A""), 0 )), ""Outreach Conducted"", """")"),"")
A56: Brandy | B56: Fonkam | C56: =CONCATENATE(A56," ",B56) -> Brandy Fonkam | D56: 16092546126 | E56: brandyfonkam@gmail.com | F56: Active CPC | G56: 553 | H56: {=IFERROR(INDEX('Hub CPC 226'!A:A, MATCH(C56, 'Hub CPC 226'!B:B, 0)), "")} -> 58 | I56: {=IFERROR(INDEX('Hub Users 226'!A:A, MATCH(C56, 'Hub Users 226'!B:B, 0)), "")} -> 78 | J56: Education | K56: 2/8/24 WW emailed for IR3 9/8/23 completed training with SB 8/17/23 Brandy signed up for training on 9/8/23 SB 8/15/23 Brand emailed saying that she had to stop Championing due to personal reasons but is ready to start again, SB replied and asked if training dates worked 1/9/23 CT sent follow up text 1/5/23 CT sent checking text 12/14/22 CT sent follow up text 12/12/22 CT sent follow up on reference email 9/26/22 SB emailed for training and wheel availability 12/22/21 SB sent IR2 FY21-22 schedule list for matching 11/20/21 congrats and training info email sent 11/19/21 Passed screening SB Lena Dandy referral | L56: 44519.434 | Q56: 61 South Central Avenue | R56: Sicklerville | S56: Sicklerville | T56: NJ | U56: Sunlightcare | V56: FY 23 - 24, FY 21 - 22 | W56: Alejandra Minan Rodriguez, Katherine (Katy) Flores, Fatou Diedhiou and Karidjatou Kone | X56: IHSUnionSquare, ELLIS | AB56: =IFERROR(__xludf.DUMMYFUNCTION("IF( ISNUMBER(MATCH( C56, IMPORTRANGE(""https://docs.google.com/spreadsheets/d/1yTh1ELC33JHYOeEdgIiEclxPRyh0zOKtlawDltfUay8"",""'Champions'!A:A""), 0 )), ""Outreach Conducted"", """")"),"")
A57: Brenda | B57: Morales | C57: =CONCATENATE(A57," ",B57) -> Brenda Morales | D57: 4052686784 | E57: brenda.morales@okstate.edu | F57: Active CPC | G57: 644 | H57: {=IFERROR(INDEX('Hub CPC 226'!A:A, MATCH(C57, 'Hub CPC 226'!B:B, 0)), "")} | I57: {=IFERROR(INDEX('Hub Users 226'!A:A, MATCH(C57, 'Hub Users 226'!B:B, 0)), "")} -> 79 | J57: STEM (Science, Technology, Engineering, Math) | K57: Pathways Days Speaker | L57: 44678.574 | AB57: =IFERROR(__xludf.DUMMYFUNCTION("IF( ISNUMBER(MATCH( C57, IMPORTRANGE(""https://docs.google.com/spreadsheets/d/1yTh1ELC33JHYOeEdgIiEclxPRyh0zOKtlawDltfUay8"",""'Champions'!A:A""), 0 )), ""Outreach Conducted"", """")"),"")
A58: Bryan | B58: Roberts | C58: =CONCATENATE(A58," ",B58) -> Bryan Roberts | D58: 19177505342 | E58: bryan.roberts14@gmail.com | F58: Active CPC | G58: 443 | H58: {=IFERROR(INDEX('Hub CPC 226'!A:A, MATCH(C58, 'Hub CPC 226'!B:B, 0)), "")} -> 60 | I58: {=IFERROR(INDEX('Hub Users 226'!A:A, MATCH(C58, 'Hub Users 226'!B:B, 0)), "")} -> 80 | J58: Health Sciences/Medicine | K58: 4/4/22 Not available for IR3. Going back to school. CT &amp; PQ 12/22/21 SB sent IR2 FY21-22 schedule list for matching JPS called and left a message on 5/25/21 to check Bryan's status as a Champion Bryan attended a training webinar on 3/28/21 with JPS but has not submitted his onboarding materials as of 3/29/21 Bryan was scheduled to attend a training webinar on 3/8/21 but did not show up. Sent follow up email on 3/10/21 to determine status moving forward. Bryan replied saying that the potential match dates do not work for him on 2/10/21 - JPS responded by asking for more specifics about his availability. JPS emailed on 2/10/21 to see if Bryan could be a champion for the IR2 20-21 session &#43; schedule a training JPS emailed on 2/10/2021 to ask Bryan to sign up for a training Bryan was screened on 2/9/2021 by Purvi Shah JPS emailed on 2/7/2021 to schedule a Screening Call | L58: 44232.597 | M58: 7 | N58: 25 | O58: 57 | P58: 35 | Q58: 202 Washington Ave, Brooklyn, NY 11205 | R58: Brooklyn | S58: Brooklyn | T58: NY | U58: New York Life Insurance Company | V58: FY 21 - 22 | W58: Rony Velasco, Carlos Hernandez, Cheikh Ka and Zakaria Billa | X58: FlushingIHS, ICHSBronx | AB58: =IFERROR(__xludf.DUMMYFUNCTION("IF( ISNUMBER(MATCH( C58, IMPORTRANGE(""https://docs.google.com/spreadsheets/d/1yTh1ELC33JHYOeEdgIiEclxPRyh0zOKtlawDltfUay8"",""'Champions'!A:A""), 0 )), ""Outreach Conducted"", """")"),"")
A59: Rex | B59: Xiong | C59: =CONCATENATE(A59," ",B59) -> Rex Xiong | D59: 14253015566 | E59: bychance@gmail.com | F59: Active CPC | G59: 514 | H59: {=IFERROR(INDEX('Hub CPC 226'!A:A, MATCH(C59, 'Hub CPC 226'!B:B, 0)), "")} -> 61 | I59: {=IFERROR(INDEX('Hub Users 226'!A:A, MATCH(C59, 'Hub Users 226'!B:B, 0)), "")} -> 81 | J59: Education | K59: 1/3/23 CT called &amp; sent text for IR2 12/27/22 CT sent follow up text for IR2 12/22/22 CT sent text for IR2 12/19/22 CT followed up for IR2 12/8/22 CT asked about IR2 availability asking for wheels schedule 12/28/21 SB sent IR2 FY21-22 schedule list for matching 10/28/21 SB training completed 10/28/21 Hetal conducted Rex's second screening call and he passed; ready to match with Flushing IHS for IR1 FY21-22 10/21/21 second screening call scheduled with Hetal for 10/28/21 10/20/21 screening call completed marked yellow SB SB sent screening scheduling email on 10/18/21 | L59: 44484.16 | Q59: 8008 NE 153RD PL | R59: Seattle, WA | S59: Seattle | T59: WA | U59: Airbnb | V59: FY 21 - 22 | W59: Kaite Cai and Luofeng Lin | X59: FlushingIHS | AB59: =IFERROR(__xludf.DUMMYFUNCTION("IF( ISNUMBER(MATCH( C59, IMPORTRANGE(""https://docs.google.com/spreadsheets/d/1yTh1ELC33JHYOeEdgIiEclxPRyh0zOKtlawDltfUay8"",""'Champions'!A:A""), 0 )), ""Outreach Conducted"", """")"),"")
A60: Cara | B60: Every | C60: =CONCATENATE(A60," ",B60) -> Cara Every | D60: 15166587211 | E60: cara.every@fmr.com | F60: Active CPC | G60: 721 | H60: {=IFERROR(INDEX('Hub CPC 226'!A:A, MATCH(C60, 'Hub CPC 226'!B:B, 0)), "")} -> 62 | I60: {=IFERROR(INDEX('Hub Users 226'!A:A, MATCH(C60, 'Hub Users 226'!B:B, 0)), "")} -> 82 | J60: Health Sciences/Medicine | K60: 5.10.24 - AT emailed re social media content 1/9/24 WW emailed for IR2-Ellis; she is available: only time conflict on Feb 13th 11/16/23 Cara OOO until 11/20, to follow up about EY then. SB 11/14/23 SB sent email to follow up about EY 11/9/23 SB emailed about EY sessions with Afrida 11/3/23 SB emailed about Sponsor Sessions Not available to do Seminars (see screening notes) 6/9/23 passed training with SB - most likely not available for IRS but yes for IR1 5/30/23 SB sent text to follow up for training - signed up for training on 6/9/23 5/25/23 SB sent follow up for training 5/23/23 SB sent congrats email 5/19/23 passed screening with SB, sending training email 5/15/23 SB called, left VM and sent text - Cara called back and scheduled screening call for 5/19/23 5/10/23 SB sent text for screening 4/25/23 SB sent follow up for screening 4/10/23 SB sent screening email | L60: 45026.565 | M60: 1 | N60: 2 | O60: 8 | Q60: 23 West Court, Smithtown NY 11787 | R60: NYC | S60: Smithtown | T60: NY | U60: Fidelity Investments | AB60: =IFERROR(__xludf.DUMMYFUNCTION("IF( ISNUMBER(MATCH( C60, IMPORTRANGE(""https://docs.google.com/spreadsheets/d/1yTh1ELC33JHYOeEdgIiEclxPRyh0zOKtlawDltfUay8"",""'Champions'!A:A""), 0 )), ""Outreach Conducted"", """")"),"")
A61: Carla | B61: Pierini Borenstein | C61: =CONCATENATE(A61," ",B61) -> Carla Pierini Borenstein | D61: +12408886973 | E61: CarlaPL28@gmail.com | F61: Discontinued | G61: 436 | H61: {=IFERROR(INDEX('Hub CPC 226'!A:A, MATCH(C61, 'Hub CPC 226'!B:B, 0)), "")} -> 63 | I61: {=IFERROR(INDEX('Hub Users 226'!A:A, MATCH(C61, 'Hub Users 226'!B:B, 0)), "")} -> 83 | K61: 9/22/23 Marking as discontinued, unsure why she was not marked before - SB 11/28/22 unsubscribed from newsletter SB Not available for IR1 and doesn't want to continue as a Champion. CT 8/10/22 9/22/21 Carla is still interest but most likely will not be available until end of 2022 (check in for round one of 2022)SB 8/11/21 voicemail/follow up email (champion replied with &#34;I am not participating in SpeakHire at this time. There is no need to contact my references&#34;) , email 8/3/21 HH Carla attended a CPC Training Webinar with JPS on 2/20/21 at 11 am est Carla wants to begin in Round 2 (IR 2020-2021) that begins in April, 2021 Carla was screened on 1/28/2021 at 8:15 am est by JPS JPS emailed on 1/26/2021 to schedule a screening call | L61: 44222.376 | M61: 12 | N61: 28 | O61: 75 | P61: 3 | Q61: 151 W 21st Street, Apt 7E, NY, NY 10011 | R61: New York, NY | S61: New York | T61: NY | U61: Cyrus R. Vance Center for International Justice | AB61: =IFERROR(__xludf.DUMMYFUNCTION("IF( ISNUMBER(MATCH( C61, IMPORTRANGE(""https://docs.google.com/spreadsheets/d/1yTh1ELC33JHYOeEdgIiEclxPRyh0zOKtlawDltfUay8"",""'Champions'!A:A""), 0 )), ""Outreach Conducted"", """")"),"")
A62: Carly | B62: Elaine Grunwald | C62: =CONCATENATE(A62," ",B62) -> Carly Elaine Grunwald | D62: 916-690-2848 | E62: carlyelaine@gmail.com | F62: Inactive CPC | G62: 117 | H62: {=IFERROR(INDEX('Hub CPC 226'!A:A, MATCH(C62, 'Hub CPC 226'!B:B, 0)), "")} -> 64 | I62: {=IFERROR(INDEX('Hub Users 226'!A:A, MATCH(C62, 'Hub Users 226'!B:B, 0)), "")} -> 84 | K62: 9/15/22 Stepping out of workforce for a while to spend more time with her family and won't be available for a while. CT Said no by email to champions to FY21-22 IR3 but said still interested. Back from maternity leave FY22-23 IR1 and check back then (HJ March, 21, 22) 12/30/21 SB sent IR2 FY21-22 schedule list for matching &#34;At this time I think I should withdraw from the program. Work and life are just a bit too busy right now for me to dedicate the appropriate time&#34; SB 8/19/21 Carly needs before 8 am PST for internship session times unsubscribed from the SPEAK newsletter on December 2, 2020 | L62: 43500.627 | Q62: 365 Hemlock Ave Unit C Carlsbad CA 92008 | R62: Carlsbad, CA | S62: Carlsbad | T62: CA | U62: Zoom Video Communications | V62: FY 19 - 20 | W62: Destiny Perry and Cilicia Cummings | X62: Academy of Medical Technology | AB62: =IFERROR(__xludf.DUMMYFUNCTION("IF( ISNUMBER(MATCH( C62, IMPORTRANGE(""https://docs.google.com/spreadsheets/d/1yTh1ELC33JHYOeEdgIiEclxPRyh0zOKtlawDltfUay8"",""'Champions'!A:A""), 0 )), ""Outreach Conducted"", """")"),"")
A63: Carmelo | B63: DeLeon | C63: =CONCATENATE(A63," ",B63) -> Carmelo DeLeon | D63: 13473765144 | E63: carmelo.DeLeon2021@gmail.com | F63: Active CPC | G63: 628 | H63: {=IFERROR(INDEX('Hub CPC 226'!A:A, MATCH(C63, 'Hub CPC 226'!B:B, 0)), "")} -> 65 | I63: {=IFERROR(INDEX('Hub Users 226'!A:A, MATCH(C63, 'Hub Users 226'!B:B, 0)), "")} -> 85 | J63: Rescue and Care | K63: 2/13/24 SB emailed for IR3 1/16/24 emailed SB not available - asked about IR3 1/11/24 SB called - Carmelo said he is looking at schedule and will let us know as soon as he can 1/10/24 SB sent text for IR2 1/9/24 SB emailed for IR2 Crotona 9/25/23 WW texted for IR1 and he is not available 9/21/23 WW emailed for IR1 5/4/23 SB texted for GCHS seminar 5/3/23 SB emailed for seminar 11/22/22 SB asked for Wheels. Carmelo said he would check his schedule and asked for info about Interns. SB sent email with info - Carmelo confirmed group SB reached out via email on 7/5 and was not available IRS. BWM sent text on 8/4. BMW responded on 8/5 and he said to reach out in Septemeber to ask because he will be starting school. Only had one round (FY21-22 IR3) with good interns. Open to working with any group 7/5/22 SB emailed Carmelo for match, work is busy in the summer - unavailable for IRS 6/22/22 SB emailed Carmelo for IRS match 4/21/22 Completed Orientation &amp; Onboarding Training. CT 3/14/22 Passed screening with SB - agreed to do Pathways Day as well. Sending training email with Seminar info 3/9/22 SB sent screening scheduling email | L63: 44627.562 | M63: 22 | N63: 50 | O63: 127 | Q63: 7157 Collamer Rd East Syracuse NY 13057 | R63: Syracuse, NY | S63: Syracuse | T63: NY | U63: National Grid | V63: Seminars 23, FY 21 - 22, FY 22 - 23 | W63: Fabian Kuclo, Rongze Yu, Matthew Vargas, Crisbelly Lopez, Leudis Rosario, Angel Tavarez and Michaell Morban | X63: GCHS, IHS Health, IHSUnionSquare, WheelsNYC | AB63: =IFERROR(__xludf.DUMMYFUNCTION("IF( ISNUMBER(MATCH( C63, IMPORTRANGE(""https://docs.google.com/spreadsheets/d/1yTh1ELC33JHYOeEdgIiEclxPRyh0zOKtlawDltfUay8"",""'Champions'!A:A""), 0 )), ""Outreach Conducted"", """")"),"")
A64: Carolina | B64: Chamorro | C64: =CONCATENATE(A64," ",B64) -> Carolina Chamorro | D64: 12152790643 (Whatsapp as well) | E64: carochamorro09@gmail.com | F64: Active CPC | G64: 437 | H64: {=IFERROR(INDEX('Hub CPC 226'!A:A, MATCH(C64, 'Hub CPC 226'!B:B, 0)), "")} -> 66 | I64: {=IFERROR(INDEX('Hub Users 226'!A:A, MATCH(C64, 'Hub Users 226'!B:B, 0)), "")} -> 86 | J64: STEM (Science, Technology, Engineering, Math) | K64: 3/8/24 WW emailed for IR3, called 3/15/24 1/11/23 SB sent email about IR2 Crotona 11/1/23 WW follow up for IR1, she is not available 10/31/23 SB sent text for IR1 10/30/23 SB emailed for IR1 4/8/22 Not available for Seminars until late summer/fall. CT Hetal confirmed with her 4/7/22 that she's busy with work and she said she'll reach back out when she's available -- try reaching out in July or October 2022 for further opportunities (4/8/22) 12/28/21 Carolina said she was not available for a Seminar or for IR2 SB 12/22/21 SB sent IR2 FY21-22 schedule list for matching Carolina attended a Champion Training Webinar on 2/20/21 with JPS at 11 am est Carolina was screened on 1/27/2020 at 8:15 am est by JPS JPS emailed on 1/26/2021 to schedule a screening call | L64: 44222.382 | M64: 10 | N64: 27 | O64: 66 | P64: 2 | Q64: 21 East 1st Street Apt 605 New York NY 10003 | R64: New York, NY | S64: New York | T64: NY | U64: Andara Global Services LLC | V64: FY 20 - 21, FY 21 - 22 | W64: Zabdy Orellana, Michael David Paredes, Jose Montalvan, Yemili Goodridge, Fernanda Marte Vasquez and Catalina Nunez De Caceres | X64: ICHSBronx, FlushingIHS, ClaremontIHS | AB64: =IFERROR(__xludf.DUMMYFUNCTION("IF( ISNUMBER(MATCH( C64, IMPORTRANGE(""https://docs.google.com/spreadsheets/d/1yTh1ELC33JHYOeEdgIiEclxPRyh0zOKtlawDltfUay8"",""'Champions'!A:A""), 0 )), ""Outreach Conducted"", """")"),"")
A65: Carolina | B65: Parra (D) | C65: =CONCATENATE(A65," ",B65) -> Carolina Parra (D) | D65: 19175147052 | E65: caroparra@gmail.com | F65: Duplicate Record | G65: 569 | H65: {=IFERROR(INDEX('Hub CPC 226'!A:A, MATCH(C65, 'Hub CPC 226'!B:B, 0)), "")} -> 67 | I65: {=IFERROR(INDEX('Hub Users 226'!A:A, MATCH(C65, 'Hub Users 226'!B:B, 0)), "")} -> 87 | K65: 1/7/22 passed training SB Carolina mentioned she has not been receiving invite emails so add her work email as well to communications ( parrashoots@gmail.com ) Carolina passed screening 12/15/21 SB, congrats email sent Sent Screening Scheduling Email 12/06/21 CT | L65: 44540.406 | M65: 13 | N65: 31 | O65: 71 | P65: 10 | Q65: 156-08 River Side Drive, Apt. 3G | R65: New York City | S65: New York | T65: NY | U65: I am a freelancer | AB65: =IFERROR(__xludf.DUMMYFUNCTION("IF( ISNUMBER(MATCH( C65, IMPORTRANGE(""https://docs.google.com/spreadsheets/d/1yTh1ELC33JHYOeEdgIiEclxPRyh0zOKtlawDltfUay8"",""'Champions'!A:A""), 0 )), ""Outreach Conducted"", """")"),"")
A66: Malene | B66: Ginete Carr | C66: =CONCATENATE(A66," ",B66) -> Malene Ginete Carr | D66: 571-565-9516 | E66: CarrMG@state.gov | F66: Active CPC | G66: 27 | H66: {=IFERROR(INDEX('Hub CPC 226'!A:A, MATCH(C66, 'Hub CPC 226'!B:B, 0)), "")} -> 68 | I66: {=IFERROR(INDEX('Hub Users 226'!A:A, MATCH(C66, 'Hub Users 226'!B:B, 0)), "")} -> 88 | K66: 7/17/23 - SB sent email for IRS, BC called &amp; left VM, SB sent follow up text 7/14/23 SB emailed for IRS 12/30/21 SB sent IR2 FY21-22 schedule list for matching Malene said on 2/17/21 that she will have to defer until next year (2021-22) JPS responded to previous email by asking when Malene would like to be considered again for a potential match (ex: Round Three?) JPS reached out to Malene on 2/9/2021 to check on status. Malene responded: &#34;Jennifer, thank you for your email. I wish you and the organization luck this year. I have been heavily involved in our internal mentoring program, so will have to pass this year. Kindly reach out for the next cycle.&#34; | L66: 43338.743 | Q66: 1415 N Taft St. Apt 780 | S66: Arlington | T66: VA | U66: US State Department | V66: FY 17 - 18 | W66: Jessica Castillo and Daniela Brito | X66: American History | AB66: =IFERROR(__xludf.DUMMYFUNCTION("IF( ISNUMBER(MATCH( C66, IMPORTRANGE(""https://docs.google.com/spreadsheets/d/1yTh1ELC33JHYOeEdgIiEclxPRyh0zOKtlawDltfUay8"",""'Champions'!A:A""), 0 )), ""Outreach Conducted"", """")"),"")
A67: Casey | B67: Burry | C67: =CONCATENATE(A67," ",B67) -> Casey Burry | D67: 646-346-3335 | E67: caseyburry@gmail.com | F67: Active CPC | G67: 129 | H67: {=IFERROR(INDEX('Hub CPC 226'!A:A, MATCH(C67, 'Hub CPC 226'!B:B, 0)), "")} -> 69 | I67: {=IFERROR(INDEX('Hub Users 226'!A:A, MATCH(C67, 'Hub Users 226'!B:B, 0)), "")} -> 89 | J67: Law | K67: 1/12/24 texted SB, &#34; I have school pickup on Mondays at 2:50. Can you please keep me in mind for the future? Mondays are usually great, but there was a change with my daughter's schedule and I can't do after 2:30.&#34; 1/11/23 SB called back - Casey asked for a email or text, which had already been sent, Casey said she would look it over and let us know 1/10/24 SB called - Casey answered and asked for a text or call tomorrow. SB sent text 1/9/24 SB sent email for IR2 Crotona 7/18/23 WW emailed for IRS, PC team followed up with text and call 3/16/23 SB send email for IR3 availability 12/27/22 CT not available for IR2 because of busy work in the spring. Reach out later next year. 12/08/22 CT asked about Wheels schedule for IR2 9/12/22 Not available for IR1 but might be for IR2 or IR3. Follow up with her in spring. CT 12/22/21 SB sent IR2 FY21-22 schedule list for matching | L67: 43510.053 | M67: 10 | N67: 26 | O67: 52 | P67: 33 | Q67: 333 Schermehorn St Brooklyn, NY | R67: New York | S67: Brooklyn | T67: NY | U67: Underline Projects | V67: FY 19 - 20, FY 20 - 21, FY 21 - 22 | W67: Chitra Srikishun, Chloe Navarro, Lenee Goggins, Arianna Francisco, Zakaria Billa, Claribelisa Gonzalez, Melany Ortiz, Xinyao Yang, Justin Martinez and Slinne Cruz | X67: Academy of Medical Technology, ICHSBronx, FlushingIHS, CrotonaIHS | AB67: =IFERROR(__xludf.DUMMYFUNCTION("IF( ISNUMBER(MATCH( C67, IMPORTRANGE(""https://docs.google.com/spreadsheets/d/1yTh1ELC33JHYOeEdgIiEclxPRyh0zOKtlawDltfUay8"",""'Champions'!A:A""), 0 )), ""Outreach Conducted"", """")"),"")
A68: Cathy Zubiate | B68: Whealon | C68: =CONCATENATE(A68," ",B68) -> Cathy Zubiate Whealon | D68: 3012190608 | E68: catherine.whealon@loreal.com | F68: Active CPC | G68: 332 | H68: {=IFERROR(INDEX('Hub CPC 226'!A:A, MATCH(C68, 'Hub CPC 226'!B:B, 0)), "")} -> 70 | I68: {=IFERROR(INDEX('Hub Users 226'!A:A, MATCH(C68, 'Hub Users 226'!B:B, 0)), "")} -> 90 | J68: Health Sciences/Medicine | K68: 3/8/24 WW emailed for IR3 10/30/23 WW left VM for IR2 and sponsor session 10/27/23 SB emailed about IR2 10/15/23 Cathy emailed and said she is too busy currently participate in IR1, but interested in rounds in 2024 10/23/23 SB called and left VM for IR1 10/19/23 SB sent Cathy text for IR1 10/18/23 SB emailed for IR1 2/28/23 CT sent follow up text to Cathy about Wheels group for IR2 2/24/23 SB emailed Cathy for mentoring month write up for magazine and for Vicki Teman replacement for IR2 Ellis group 10/21/22 Unavailable for IR1 SB 10/20/22 SB emailed Cathy for Wheels 10/5/22 SB emailed Cathy to let her know we are looking for IR1 and to see if she is able to do IR2 7/11/22 unavailable for IRS SB 7/5/22 SB emailed for IRS match - OOO office until 7/11, looking for replacement 12/22/21 SB sent IR2 FY21-22 schedule list for matching Cathy confirmed that she is available to mentor for the 2020-2021 mentoring rounds beginning in November Emailed references on 9/29/2020 Cathy was trained on 9/28/2020 at 7:30 pm EST with Jennifer Peterson-Sharma and Kiesha Charles. Cathy would like to start out with one mentee pair for her first mentoring round. Jennifer screened Cathy on 9/16/2020 at 5 pm EST. Jennifer Peterson-Sharma sent a follow-up email for the Mentor Screening Call on 9/9/2020. Emailed 8/27/2020 about setting up screening call | L68: 44025.583 | Q68: 3500 Singers Glen Dr Olney, MD 20832 | R68: Maryland | S68: Olney | T68: MD | U68: L'Oreal USA | V68: FY 20 - 21 | W68: Mairol Rivas, Estuardo Lopez, Mariama Diallo and Souleymane Bah | X68: CrotonaIHS, NYC Mission - Emma Lazarus | AB68: =IFERROR(__xludf.DUMMYFUNCTION("IF( ISNUMBER(MATCH( C68, IMPORTRANGE(""https://docs.google.com/spreadsheets/d/1yTh1ELC33JHYOeEdgIiEclxPRyh0zOKtlawDltfUay8"",""'Champions'!A:A""), 0 )), ""Outreach Conducted"", """")"),"")
A69: Connie | B69: Lewin | C69: =CONCATENATE(A69," ",B69) -> Connie Lewin | D69: 19544396702 | E69: cdlewin@gmail.com | F69: Active CPC | G69: 640 | H69: {=IFERROR(INDEX('Hub CPC 226'!A:A, MATCH(C69, 'Hub CPC 226'!B:B, 0)), "")} -> 71 | I69: {=IFERROR(INDEX('Hub Users 226'!A:A, MATCH(C69, 'Hub Users 226'!B:B, 0)), "")} -> 91 | J69: Armed Services/Law Enforcement | K69: 3/3/23 texted SB, &#34; I wish I could help but I'm not available at this time for the next few months. I'll consider signing up again the fall.&#34; 2/27/23 SB messaged to see if she could be a replacement CPC for IR2 5/16/22 CT Attended CPC Orientation &amp; Onboarding Training 5/5/22 Sent Congrats email CT 5/4/22 Passed Screening Call CT 4/25 SB sent screening email | L69: 44674.73 | T69: FL | U69: LISC | AB69: =IFERROR(__xludf.DUMMYFUNCTION("IF( ISNUMBER(MATCH( C69, IMPORTRANGE(""https://docs.google.com/spreadsheets/d/1yTh1ELC33JHYOeEdgIiEclxPRyh0zOKtlawDltfUay8"",""'Champions'!A:A""), 0 )), ""Outreach Conducted"", """")"),"") | AD69: Issue 10, Issue 11 | AE69: Issue 10,11 - 2/8/22 | AF69: Thank you for your support letter | AG69: Issue 10,11 - 50 + $50 summit ticket
A70: Carlos | B70: Guzman | C70: =CONCATENATE(A70," ",B70) -> Carlos Guzman | D70: (949)903-2058 | E70: cguzman@umassglobal.edu | F70: Inactive CPC | G70: 714 | H70: {=IFERROR(INDEX('Hub CPC 226'!A:A, MATCH(C70, 'Hub CPC 226'!B:B, 0)), "")} -> 72 | I70: {=IFERROR(INDEX('Hub Users 226'!A:A, MATCH(C70, 'Hub Users 226'!B:B, 0)), "")} -> 92 | J70: Business | K70: 4/19/23 emailed, &#34;I am saddened to inform you that recent events at my university have created a situation where I can no longer volunteer with Speakhire at this time. I have been tasked with additional committee responsibilities and duties which have placed a huge burden on my workload. As a result, I will not be able to put in the time to work with interns and provide consistency and quality. It is my hope that in the future I can resume voluntary work with Speakhire.&#34; SB 4/3/23 SB sent follow up about training 3/27/23 passed screening with SB and BC, sending training email 3/23/23 SB sent follow up screening email 3/17/23 SB sent screening email | L70: 45007.606 | Q70: 17 Drover Court Trabuco Canyon California 92679 | S70: Trabuco Canyon | T70: CA | U70: University of Massachusetts Global | AB70: =IFERROR(__xludf.DUMMYFUNCTION("IF( ISNUMBER(MATCH( C70, IMPORTRANGE(""https://docs.google.com/spreadsheets/d/1yTh1ELC33JHYOeEdgIiEclxPRyh0zOKtlawDltfUay8"",""'Champions'!A:A""), 0 )), ""Outreach Conducted"", """")"),"")
A71: Chaney | B71: Matos | C71: =CONCATENATE(A71," ",B71) -> Chaney Matos | D71: 6466287701 | E71: chaney.matos@gmail.com | F71: Inactive CPC | G71: 60 | H71: {=IFERROR(INDEX('Hub CPC 226'!A:A, MATCH(C71, 'Hub CPC 226'!B:B, 0)), "")} -> 73 | I71: {=IFERROR(INDEX('Hub Users 226'!A:A, MATCH(C71, 'Hub Users 226'!B:B, 0)), "")} -> 93 | J71: Health Sciences/Medicine | K71: 5/16/22 SB sent re-engagement email 12/22/21 SB sent IR2 FY21-22 schedule list for matching HJ called on 10/4/21 and left a vm saying we needed spanish and/or educators Chaney said that she was already screened by Scotney, but also said she is currently unavailable to be a Champion in February 2021. &#34;I'm unable to commit to Speakhire. I'm currently in grad school, working and doing remote learning with my two boys. If possible, I'd like to stay on your list for the future.&#34; Marking as inactive/green. On 2/4/21, Chaney responded to JPS's email by saying, &#34;At this time, I'm unable to commit to Speakhire. I'm currently in grad school, working and doing remote learning with my two boys. If possible, I'd like to stay on your list for the future.&#34; JPS Emailed on 2/3/2021 to schedule a Screening Call Dema Alhuraibi called on 10/6/20 and left a voice message. | L71: 43338.743 | M71: 15 | N71: 33 | O71: 80 | P71: 13 | Q71: 2166 Matthews Avenue#4F | S71: Bronx | T71: NY | U71: Research Foundation of CUNY at Lehman College | AB71: =IFERROR(__xludf.DUMMYFUNCTION("IF( ISNUMBER(MATCH( C71, IMPORTRANGE(""https://docs.google.com/spreadsheets/d/1yTh1ELC33JHYOeEdgIiEclxPRyh0zOKtlawDltfUay8"",""'Champions'!A:A""), 0 )), ""Outreach Conducted"", """")"),"")
A72: Lena | B72: Chang | C72: =CONCATENATE(A72," ",B72) -> Lena Chang | D72: 917-969-9696 | E72: changlena@aol.com | F72: Active CPC | G72: 724 | H72: {=IFERROR(INDEX('Hub CPC 226'!A:A, MATCH(C72, 'Hub CPC 226'!B:B, 0)), "")} -> 74 | I72: {=IFERROR(INDEX('Hub Users 226'!A:A, MATCH(C72, 'Hub Users 226'!B:B, 0)), "")} -> 94 | J72: Health Sciences/Medicine | K72: 05/10/24 - AT emailed regarding Mother's day social media content 1/18/24 not available for IR2 - &#34;Unfortunately, my availability is better in the evenings at this point. If anything changes, I will let you know.&#34; SB 1/9/24 SB sent follow up about IR2 12/29/23 SB emailed about IR2, sent Ellis schedule 7/17/23 - SB sent email for IRS, BC called &amp; left VM, SB sent follow up text 5/23/23 CT Completed CPC Orientation &amp; Onboarding Webinar 5/18/23 son graduated SB 5/8/23 SB sent follow up via text for training - scheduled training for 5/23/23 5/4/23 SB sent follow up email for training 5/1/23 passed screening with SB 4/27/23 Scheduled screening call with SB. Did not show, SB sent email and text to get her online. Still nothing. SB sent email to reschedule Instagram: LenaChang1 LinkedIn: Lena Chang Facebook: Lena Chang Twitter: @LenaChang8 TikTok: @lenachang8 | L72: 45041.974 | M72: 10 | N72: 27 | O72: 61 | P72: 1 | Q72: 200 Rector Place Apt 34N, New York 10280 | R72: New York | S72: New York | T72: NY | U72: CenterLight Healthcare System | AB72: =IFERROR(__xludf.DUMMYFUNCTION("IF( ISNUMBER(MATCH( C72, IMPORTRANGE(""https://docs.google.com/spreadsheets/d/1yTh1ELC33JHYOeEdgIiEclxPRyh0zOKtlawDltfUay8"",""'Champions'!A:A""), 0 )), ""Outreach Conducted"", """")"),"")
A73: Chante | B73: Adams | C73: =CONCATENATE(A73," ",B73) -> Chante Adams | D73: 17025314626 | E73: chante.adams@csaa.com | F73: Active CPC | G73: 558 | H73: {=IFERROR(INDEX('Hub CPC 226'!A:A, MATCH(C73, 'Hub CPC 226'!B:B, 0)), "")} -> 75 | I73: {=IFERROR(INDEX('Hub Users 226'!A:A, MATCH(C73, 'Hub Users 226'!B:B, 0)), "")} -> 95 | J73: Social Sciences/Psychology | K73: 7/17/23 - SB sent email for IRS, BC called &amp; left VM, SB sent follow up text 7/11/23 SB sent text for IRS 7/10/23 SB emailed for IRS 11/22/22 CT sent re-engagement email with training dates 4/5/22 Not available for IR3. CT 2/7/22 Passed screening SB 2/2/22 SB called and sent text 2/1/22 SB called and left VM 12/3/21 SB sent screening scheduling email | L73: 44530.747 | Q73: 10639 Forum Peak Lane Las Vegas, NV 89166 | R73: Las Vegas | S73: Las Vegas | T73: NV | U73: CSAA | V73: FY 21 - 22 | W73: Carolyn Guzman and Jose Salas | X73: ClaremontIHS | AB73: =IFERROR(__xludf.DUMMYFUNCTION("IF( ISNUMBER(MATCH( C73, IMPORTRANGE(""https://docs.google.com/spreadsheets/d/1yTh1ELC33JHYOeEdgIiEclxPRyh0zOKtlawDltfUay8"",""'Champions'!A:A""), 0 )), ""Outreach Conducted"", """")"),"")
A74: Joanne | B74: Hsu | C74: =CONCATENATE(A74," ",B74) -> Joanne Hsu | D74: 15189862883 | E74: chemang@gmail.com | F74: Active CPC | G74: 523 | H74: {=IFERROR(INDEX('Hub CPC 226'!A:A, MATCH(C74, 'Hub CPC 226'!B:B, 0)), "")} -> 76 | I74: {=IFERROR(INDEX('Hub Users 226'!A:A, MATCH(C74, 'Hub Users 226'!B:B, 0)), "")} -> 96 | J74: Social Sciences/Psychology | K74: Donated money to Interns for FY22-23 3/16/23 - For IR3 not available on April 20th (session 1) SB 3/6/23 SB emailed for IR3 availability (did not send About Interns yet) - agreed to time, sending about Interns - confirmed group 10/19/22 SB emailed for Wheels availability Completed onboarding and orientation webinar on 11/5/21 SB 10/27/21 SB sent congrats and training scheduling email 10/26/21 SB screening passed - Prefers to be matched with someone with a similar background. 10/25/21 SB sent screening scheduling email | L74: 44494.395 | Q74: 22 Belle Terre Road, West Orange NJ 07052 | R74: New York | S74: West Orange | T74: NJ | U74: Hunter College/PRIDE Research Consortium | V74: FY 21 - 22, FY 22 - 23 | W74: Yechi Ma, Ziyi Lin, Chuanxun Li, Rana Musleh, Stephanie Leonzo and Yoana Reyes | X74: FlushingIHS, WheelsNYC | AB74: =IFERROR(__xludf.DUMMYFUNCTION("IF( ISNUMBER(MATCH( C74, IMPORTRANGE(""https://docs.google.com/spreadsheets/d/1yTh1ELC33JHYOeEdgIiEclxPRyh0zOKtlawDltfUay8"",""'Champions'!A:A""), 0 )), ""Outreach Conducted"", """")"),"") | AD74: Issue 9, Issue 10, Issue 11 | AE74: Issue 9,10,11 - 2/8/22 | AF74: Thank you for your support letter
A75: Chetana | B75: Manjunath Kaushik | C75: =CONCATENATE(A75," ",B75) -> Chetana Manjunath Kaushik | D75: 14167320512 | E75: chetanamkaushik@gmail.com | F75: Active CPC | G75: 498 | H75: {=IFERROR(INDEX('Hub CPC 226'!A:A, MATCH(C75, 'Hub CPC 226'!B:B, 0)), "")} -> 77 | I75: {=IFERROR(INDEX('Hub Users 226'!A:A, MATCH(C75, 'Hub Users 226'!B:B, 0)), "")} -> 97 | J75: Social Sciences/Psychology | K75: 1/16/23 IR2 does not work. SB asked for IR3 - is interested in IR3 1/4/23 Chetana emailed back, Union Square schedule does not work -&gt;SB emailed back seeing if Ellis schedule does 12/29/23 SB emailed to see if available for IR2, sent Union Square schedule 9/20/23 emailed saying she is interested in mentoring soon, SB replied letting her know we'd follow up about IR1 when we have more info about schedules 11/22/22 Might be available for IR2, reach out to her later. CT 10/04/22 Not available for IR1 CT 3/21/22 Not available for IR3 CT Completed training on 9/25/21 SB Screening call passed passed on 9/14 SB Screening scheduling email sent 9/10/21 SB | L75: 44447.803 | Q75: 504-1580 Haro St, Vancouver, BC-V6G1G6 | R75: Vancouver, British Columbia | U75: Microchip Technology | V75: Seminars 22, FY 21 - 22 | W75: Alessandro Guzman, Dipson Khatri Chhetri, Magby Orellana and Adama Bah | X75: FlushingIHS, P2GBronx, IHS Health, ICHSBronx | AB75: =IFERROR(__xludf.DUMMYFUNCTION("IF( ISNUMBER(MATCH( C75, IMPORTRANGE(""https://docs.google.com/spreadsheets/d/1yTh1ELC33JHYOeEdgIiEclxPRyh0zOKtlawDltfUay8"",""'Champions'!A:A""), 0 )), ""Outreach Conducted"", """")"),"")
A76: Chetna | B76: Bail | C76: =CONCATENATE(A76," ",B76) -> Chetna Bail | D76: 4254453391 | E76: chetnab@gmail.com | F76: Active CPC | G76: 58 | H76: {=IFERROR(INDEX('Hub CPC 226'!A:A, MATCH(C76, 'Hub CPC 226'!B:B, 0)), "")} -> 78 | I76: {=IFERROR(INDEX('Hub Users 226'!A:A, MATCH(C76, 'Hub Users 226'!B:B, 0)), "")} -> 98 | K76: 7/18/23 WW emailed for IRS, PC team followed up with text and call 2/28/23 CT left voicemail &amp; sent text about taking Wheels group IR2 2/27/23 CT sent email asking if Chetna can take over group of Wheels Interns for IR2 for CPC who had to drop out. 1/27/23 CT left voicemail &amp; sent text for IR2 1/25/23 CT asked for IR2 wheels schedule 3/21/22 Not available for IR3 CT 12/30/21 SB sent IR2 FY21-22 schedule list for matching JPS emailed on 2/10/21 to see if Chetna could accommodate a Claremont match for IR2 20-21. Only available after 12:30pmEST | L76: 43338.743 | Q76: 3411 Plateau Dr | S76: Belmont | T76: CA | U76: DropBox | V76: FY 21 - 22 | W76: Jaritza Ortega and Christopher Mendoza | X76: FlushingIHS | AB76: =IFERROR(__xludf.DUMMYFUNCTION("IF( ISNUMBER(MATCH( C76, IMPORTRANGE(""https://docs.google.com/spreadsheets/d/1yTh1ELC33JHYOeEdgIiEclxPRyh0zOKtlawDltfUay8"",""'Champions'!A:A""), 0 )), ""Outreach Conducted"", """")"),"")
A77: Chiemela | B77: Okwandu | C77: =CONCATENATE(A77," ",B77) -> Chiemela Okwandu | D77: 19095681293 | E77: chiemelao@gmail.com | F77: Active CPC | G77: 457 | H77: {=IFERROR(INDEX('Hub CPC 226'!A:A, MATCH(C77, 'Hub CPC 226'!B:B, 0)), "")} -> 79 | I77: {=IFERROR(INDEX('Hub Users 226'!A:A, MATCH(C77, 'Hub Users 226'!B:B, 0)), "")} -> 99 | J77: Entertainment/Lifestyle | K77: 1/10/24 SB emailed for IR2 Union Square 4/25/23 SB emailed Chiemela for IR3 12/12/22 CT Chiemela confirmed availability for Wheels IR2 12/9/22 Chiemela responded saying she can confirm her availability next week. SB responded to her email 12/08/22 CT asked about Wheels schedule for IR2 12/22/21 SB sent IR2 FY21-22 schedule list for matching Chiemela attended a training webinar on 3/22/21 with JPS Screened on 3/5/21 by SU JPS sent screening call email on 2/26/21 | L77: 44253.012 | Q77: 1028 Park Spring Lane, Diamond bar, CA, 91765 | R77: Diamond Bar | S77: Diamond Bar | T77: CA | U77: Troutman Pepper | V77: Seminars 22, Seminars 21, FY 22 - 23, FY 21 - 22, FY 20 - 21 | W77: Wilenie De Jesus Lancer, Wilson Infante, Yisneiri Rojas, Jhoana Guevara, Alison Vargas, Raya Tovmasyan, Genesis Moreno, Amelia Rodriguez, Johana Gonzalez, Rocio Hernandez, Yaire Moore, Catalina Nunez De Caceres, Masooma Chaudhry and Luis Parra Pestana | X77: IHSUnionSquare, ClaremontIHS, HSEI, WheelsNYC, IHS Lafayette, IHS Health, FlushingIHS | AB77: =IFERROR(__xludf.DUMMYFUNCTION("IF( ISNUMBER(MATCH( C77, IMPORTRANGE(""https://docs.google.com/spreadsheets/d/1yTh1ELC33JHYOeEdgIiEclxPRyh0zOKtlawDltfUay8"",""'Champions'!A:A""), 0 )), ""Outreach Conducted"", """")"),"")
A78: Christa | B78: Neu | C78: =CONCATENATE(A78," ",B78) -> Christa Neu | D78: 14849517637 | E78: chn211@lehigh.edu | F78: Active CPC | G78: 621 | H78: {=IFERROR(INDEX('Hub CPC 226'!A:A, MATCH(C78, 'Hub CPC 226'!B:B, 0)), "")} -> 80 | I78: {=IFERROR(INDEX('Hub Users 226'!A:A, MATCH(C78, 'Hub Users 226'!B:B, 0)), "")} -> 100 | J78: Law | K78: Ig @cneu Twitter @neuey Fb: probably christa neu 10/26/23 WW emailed for Champion-led Info Session; 10/27/23 Christa replied &#34;I'm not able to take this on right now with work and other commitments&#34;; WW followed up 10/30/23 2/1/23 CT confirmed Wheels for IR2 2/1/23 CT asked for IR2 Wheels schedule 1/6/23 SB emailed for IR2 Mondays - confirmed schedule Unavailable for IR1 - interested in IR2. 10/19/22 SB 10/13/22 SB emailed for wheels match Last communciation for IR3 in April CT - BMW sent a text on 8/4. She is available for Wednesdays. Needs a strong group. Very positive and understanding. 4/4/22 Not available for IR3. Reach out in fall for next round. CT 2/11/22 Completed Orientation and Onboarding Training SB Passed screening with Hetal on Feb 3rd, 2022 | L78: 44596.717 | Q78: 316 Race St | R78: north eastern Pennsylvania | S78: Catasauqua | T78: PA | U78: Lehigh University | V78: FY 21 - 22, FY 22 - 23 | W78: Xilena Toris, Nixon Vergara, Steisy Rodriguez, Hayes Mendez, Robert Morillo, Jayson Munoz, Brandon Nunez and Yannelle Kunakey | X78: IHS Health, WheelsNYC | AB78: =IFERROR(__xludf.DUMMYFUNCTION("IF( ISNUMBER(MATCH( C78, IMPORTRANGE(""https://docs.google.com/spreadsheets/d/1yTh1ELC33JHYOeEdgIiEclxPRyh0zOKtlawDltfUay8"",""'Champions'!A:A""), 0 )), ""Outreach Conducted"", """")"),"")
A79: Jennifer | B79: Chowdhury | C79: =CONCATENATE(A79," ",B79) -> Jennifer Chowdhury | D79: 6464797979 | E79: chowdhuryj315@gmail.com | F79: Inactive CPC | G79: 22 | H79: {=IFERROR(INDEX('Hub CPC 226'!A:A, MATCH(C79, 'Hub CPC 226'!B:B, 0)), "")} -> 81 | I79: {=IFERROR(INDEX('Hub Users 226'!A:A, MATCH(C79, 'Hub Users 226'!B:B, 0)), "")} -> 101 | K79: 8/8/23 AT sent re-engagement email. Jennifer is delivering her baby soon and would love to get involved in the future. I've emailed to se if she is available for the November 2023 round, if not when to check in with her again. 8/8 - Jennifer will not be available to Champion until 2024; please contact her again then - marking inactive for now 5/22/22 SB sent re-engagement email Double checked on 1/26 KW not always responsive | L79: 43338.743 | M79: 10 | N79: 26 | O79: 52 | P79: 33 | Q79: 421 Degraw street | S79: Brooklyn | T79: NY | U79: World Food Programme | V79: FY 17 - 18 | W79: Ayoko Kessouagni | AB79: =IFERROR(__xludf.DUMMYFUNCTION("IF( ISNUMBER(MATCH( C79, IMPORTRANGE(""https://docs.google.com/spreadsheets/d/1yTh1ELC33JHYOeEdgIiEclxPRyh0zOKtlawDltfUay8"",""'Champions'!A:A""), 0 )), ""Outreach Conducted"", """")"),"")
A80: Christian | B80: Espinoza | C80: =CONCATENATE(A80," ",B80) -> Christian Espinoza | D80: +19493079469 | E80: christian.espinoza@matthews.com | F80: Discontinued | G80: 488 | H80: {=IFERROR(INDEX('Hub CPC 226'!A:A, MATCH(C80, 'Hub CPC 226'!B:B, 0)), "")} -> 82 | I80: {=IFERROR(INDEX('Hub Users 226'!A:A, MATCH(C80, 'Hub Users 226'!B:B, 0)), "")} -> 102 | K80: 3/8/24 WW emailed for IR3 - he asked to be removed from our emailing list - WW asked if he's interested in other initiatives like seminars or don't want to proceed as a Champion; he said &#34; unscribe me&#34; again, also for ccc emails, so WW mark him as discontinue 3/11/24 1/3/23 CT called &amp; sent text for IR2 12/27/22 CT follow up text for IR2 12/22/22 CT sent text for IR2 12/19/22 CT followed up for IR2 12/14/22 CT followed up for IR2 12/08/22 CT asked about Wheels schedule for IR2 12/22/21 SB sent IR2 FY21-22 schedule list for matching Completed Onboarding and Training on 8/14/21 SB Training scheduled for 8/14/21 on 8/4/21 SB Training scheduling email sent 8/4/21 SB Screening call done on 7/29/21 SB | L80: 44399.487 | Q80: 3200 Park Center Dr. Suite #520, Costa Mesa, CA | R80: Costa Mesa | S80: Costa Mesa | T80: CA | U80: Matthews Real Estate Investment Services | V80: FY 21 - 22 | W80: Bryan Montesdeoca Montesdeoca and Walter Ramos | X80: FlushingIHS | AB80: =IFERROR(__xludf.DUMMYFUNCTION("IF( ISNUMBER(MATCH( C80, IMPORTRANGE(""https://docs.google.com/spreadsheets/d/1yTh1ELC33JHYOeEdgIiEclxPRyh0zOKtlawDltfUay8"",""'Champions'!A:A""), 0 )), ""Outreach Conducted"", """")"),"")
A81: Christina | B81: Kiffney | C81: =CONCATENATE(A81," ",B81) -> Christina Kiffney | D81: +17205418119 | E81: christina@christinakiffney.com | F81: Discontinued | G81: 679 | H81: {=IFERROR(INDEX('Hub CPC 226'!A:A, MATCH(C81, 'Hub CPC 226'!B:B, 0)), "")} -> 83 | I81: {=IFERROR(INDEX('Hub Users 226'!A:A, MATCH(C81, 'Hub Users 226'!B:B, 0)), "")} -> 103 | K81: 1/6/23 CT Started Screening Call but 5 minutes in Christina said she really doesn't have time because of her personal and professional life and she's sorry but she has to end this meeting and can't be a CPC. Scheduled screening for 1/5/23 SB 12/5/22 SB messaged for screening 11/30/22 SB followed up about screening 11/18/22 SB followed up for screening 11/15/22 SB sent screening email | L81: 44879.706 | Q81: 270 31st St | R81: Boulder, CO | S81: Boulder | U81: Christina Kiffney Photography, Inc. | AB81: =IFERROR(__xludf.DUMMYFUNCTION("IF( ISNUMBER(MATCH( C81, IMPORTRANGE(""https://docs.google.com/spreadsheets/d/1yTh1ELC33JHYOeEdgIiEclxPRyh0zOKtlawDltfUay8"",""'Champions'!A:A""), 0 )), ""Outreach Conducted"", """")"),"")
A82: CHRISTINA | B82: BROOMES | C82: =CONCATENATE(A82," ",B82) -> CHRISTINA BROOMES | D82: 16507595799 | E82: christina_broomes@yahoo.com | F82: Active CPC | G82: 516 | H82: {=IFERROR(INDEX('Hub CPC 226'!A:A, MATCH(C82, 'Hub CPC 226'!B:B, 0)), "")} -> 84 | I82: {=IFERROR(INDEX('Hub Users 226'!A:A, MATCH(C82, 'Hub Users 226'!B:B, 0)), "")} -> 104 | J82: Armed Services/Law Enforcement | K82: 1/18/24 SB emailed for Black History Month 11/17/23 recently lost job - learned from LinkedIn post SB 2/28/23 Christina confirmed group for IR3 SB 2/27/23 SB emailed Christina to see if she still might be available for the group for IR3 2/1/23 CT Christina is swamped with work this round &amp; not available anymore. Wants to meet with group of 4 Wheels Interns (Ashley Diaz, Raquel Guerrero, Daylan Peralta, Alexa Barrueco) for IR3. 1/27/23 CT left voicemail &amp; sent text for IR2 1/25/23 CT asked for IR2 with wheels schedule Hetal reached out to Christina Broomes by text to confirm Queens Prep for FY 21-22 IR1 -- she confirmed quickly by text (11/1/21) Screening note: prefers interns who have African heritage or background and STEM interest 10/28/21 SB - Screening and training passed Screening scheduling email sent 10/20/21 SB | L82: 44487.775 | Q82: 39 ASPEN AVE | R82: Grafton Massachusettes | S82: South Grafton | T82: MA | U82: Ultragenyx Pharmaceutical | V82: FY 21 - 22, FY 22 - 23 | W82: Bradley Edwards, Devin Rhodie, Naveer Ramsarran, Blair Vales, Alexa Barrueco, Raquel Guerrero, Daylan Peralta, Ashley Diaz, Scarlett Cotto, Justin Pinero, Jaliyha Eberhart, Aaliyah Dennis and Aliyah Maliq | X82: QueensPrepAcad, WheelsNYC, NYC Mission - Bronx Community and Washington Irving YABC | AB82: =IFERROR(__xludf.DUMMYFUNCTION("IF( ISNUMBER(MATCH( C82, IMPORTRANGE(""https://docs.google.com/spreadsheets/d/1yTh1ELC33JHYOeEdgIiEclxPRyh0zOKtlawDltfUay8"",""'Champions'!A:A""), 0 )), ""Outreach Conducted"", """")"),"")
A83: Christine | B83: Elizabeth Katt | C83: =CONCATENATE(A83," ",B83) -> Christine Elizabeth Katt | D83: 914-447-3136 | E83: christine.katt@gmail.com | F83: Inactive CPC | G83: 140 | H83: {=IFERROR(INDEX('Hub CPC 226'!A:A, MATCH(C83, 'Hub CPC 226'!B:B, 0)), "")} -> 85 | I83: {=IFERROR(INDEX('Hub Users 226'!A:A, MATCH(C83, 'Hub Users 226'!B:B, 0)), "")} -> 105 | K83: 5/18/22 SB sent re-engagement email 01/05/22 CT sent follow up email for matching 12/30/21 SB sent IR2 FY21-22 schedule list for matching JPS sent an email via Champions@speakhire.org to schedule a training webinar on 7/21/21. Looks like they may have had a screening call with Jenny Hoefler in Feb 2019 Hetal called on 3/26/20 and left a voice message to see if available during COVID-19. No response. | L83: 43590.634 | Q83: 1012 S. 12th St Apt 2 | R83: Philadelphia, PA | S83: Philadelphia | T83: PA | U83: Alex's Lemonade Stand Foundation | AB83: =IFERROR(__xludf.DUMMYFUNCTION("IF( ISNUMBER(MATCH( C83, IMPORTRANGE(""https://docs.google.com/spreadsheets/d/1yTh1ELC33JHYOeEdgIiEclxPRyh0zOKtlawDltfUay8"",""'Champions'!A:A""), 0 )), ""Outreach Conducted"", """")"),"")
A84: Claudia | B84: Mendez | C84: =CONCATENATE(A84," ",B84) -> Claudia Mendez | D84: 310-500-7107 | E84: cmendez771@gmail.com | F84: Active CPC | G84: 93 | H84: {=IFERROR(INDEX('Hub CPC 226'!A:A, MATCH(C84, 'Hub CPC 226'!B:B, 0)), "")} -> 86 | I84: {=IFERROR(INDEX('Hub Users 226'!A:A, MATCH(C84, 'Hub Users 226'!B:B, 0)), "")} -> 106 | K84: 4/3/23 CT sent follow up email with CPC training dates 2/22/23 CT sent follow up email to re-engage 2/9/23 CT sent re-engagement email 5/16/22 SB emailed for re-engagement 12/22/21 SB sent IR2 FY21-22 schedule list for matching Claudia had been matched and agreed but then because of a divorce and other physical issues as a result, opted out after being matched -- see if she's emotionally available by IR2 (Hetal 11/5/2021) Hetal conducted screening call 11/1/21 - passed, green. Hetal called her on 10/31/21 and she said she was going through a divorce so having difficulty keeping up with things but she wants to and needs to do this to focus on something -- really wants to help Spanish speaking students; will also share with her organization ChangeMakers Collective who are Latinas looking for change (paralegals, lawyers, social workers) Hetal shared the text to share with her by text and confirmed a screening call with Hetal by phone -- she can join the November 5th training (10/31/21) HH email 8/5/21, HH email 7/28/21, HH text 7/20/21 (why not a voicemail? JPS phone disconnected HH) | L84: 43393.576 | Q84: 7003 4th av LA CA 90043 | R84: Los Angeles | S84: Los Angeles | T84: CA | U84: Self employed | AB84: =IFERROR(__xludf.DUMMYFUNCTION("IF( ISNUMBER(MATCH( C84, IMPORTRANGE(""https://docs.google.com/spreadsheets/d/1yTh1ELC33JHYOeEdgIiEclxPRyh0zOKtlawDltfUay8"",""'Champions'!A:A""), 0 )), ""Outreach Conducted"", """")"),"")
A85: Christopher | B85: Pasi | C85: =CONCATENATE(A85," ",B85) -> Christopher Pasi | D85: 19087208444 | E85: cpasi55@gmail.com | F85: Active CPC | G85: 619 | H85: {=IFERROR(INDEX('Hub CPC 226'!A:A, MATCH(C85, 'Hub CPC 226'!B:B, 0)), "")} -> 88 | I85: {=IFERROR(INDEX('Hub Users 226'!A:A, MATCH(C85, 'Hub Users 226'!B:B, 0)), "")} -> 108 | J85: Arts/Creative | K85: 2/13/24 SB emailed for IR3 10/17/23 Christopher email SB saying he is booked with projects but would love to participate in spring of 2024 10/16/23 SB emailed for IR1 12/9/22 emailed &#34; I would like to be considered for the 2024 semesters because I have too much work going on in my life right now to make time for the internship.&#34; SB responded. marking inactive 12/08/22 CT asked about Wheels schedule for IR2 02/03/22 Completed CPC Orientation &amp; Onboarding Training CT 02/01/22 Sent Screening email &amp; CPC Training email with Handbook and Instructional Guide CT | L85: 44593.74 | M85: 13 | N85: 30 | O85: 70 | P85: 9 | Q85: 356 West 118th Street, Apt. 2, New York, NY, 10026 | R85: New York City, Harlem & Brooklyn | S85: New York | T85: NY | U85: Pivot Productions | V85: Seminars 22, FY 21 - 22 | W85: Kaitlynn Coppin, Crisffer Urena, Alisha Ramos and Heather Nieves | X85: IHSUnionSquare, NYC Mission - Bronx Community and Washington Irving YABC | AB85: =IFERROR(__xludf.DUMMYFUNCTION("IF( ISNUMBER(MATCH( C85, IMPORTRANGE(""https://docs.google.com/spreadsheets/d/1yTh1ELC33JHYOeEdgIiEclxPRyh0zOKtlawDltfUay8"",""'Champions'!A:A""), 0 )), ""Outreach Conducted"", """")"),"")
A86: Colleen | B86: Rebecca Osborne | C86: =CONCATENATE(A86," ",B86) -> Colleen Rebecca Osborne | D86: 1-818-618-6532 | E86: crosborne9@gmail.com | F86: Inactive CPC | G86: 109 | H86: {=IFERROR(INDEX('Hub CPC 226'!A:A, MATCH(C86, 'Hub CPC 226'!B:B, 0)), "")} -> 89 | I86: {=IFERROR(INDEX('Hub Users 226'!A:A, MATCH(C86, 'Hub Users 226'!B:B, 0)), "")} -> 109 | K86: 01/05/22 CT sent follow up email for matching 12/30/21 SB sent IR2 FY21-22 schedule list for matching 12/21/21 SB sent Collenn a text about match for IR1 FY21-22 Jenny completed Colleen's reference calls in Nov 2018 | L86: 43484.715 | M86: 10 | N86: 20 | O86: 44 | P86: 35 | Q86: 326 St Johns Pl, Apt 6D, Brooklyn NY 11238 | R86: NYC | S86: Brooklyn | T86: NY | U86: TED Talks | AB86: =IFERROR(__xludf.DUMMYFUNCTION("IF( ISNUMBER(MATCH( C86, IMPORTRANGE(""https://docs.google.com/spreadsheets/d/1yTh1ELC33JHYOeEdgIiEclxPRyh0zOKtlawDltfUay8"",""'Champions'!A:A""), 0 )), ""Outreach Conducted"", """")"),"")
A87: Carmen | B87: Maldonado-Bowling | C87: =CONCATENATE(A87," ",B87) -> Carmen Maldonado-Bowling | D87: 19379749913 | E87: czbowling@gmail.com | F87: Active CPC | G87: 670 | H87: {=IFERROR(INDEX('Hub CPC 226'!A:A, MATCH(C87, 'Hub CPC 226'!B:B, 0)), "")} -> 90 | I87: {=IFERROR(INDEX('Hub Users 226'!A:A, MATCH(C87, 'Hub Users 226'!B:B, 0)), "")} -> 110 | J87: Business | K87: 1/8/24 SB called and left VM for IR2 availability 1/5/24 SB sent text about IR2 1/3/24 SB sent follow up email for IR2 12/12/23 SB emailed for IR2 10/18/23 SB called and left vm about IR1 10/16/23 SB sent follow up text about IR1 10/13/23 SB sent text to follow up about IR1 availability - Carmen asked for the weekend to think about it 10/5/23 SB emailed for IR1 availability 8/18/23 SB Updated location from Louisville, Ky to Dallas, Texas. And update job info from Nurse Consultant/Interim Nurse Leader at Healthlinx to current info. SB also updated bio to reflect this change 7/17/23 Carmen got a new position at work. SB asked for updated info 7/17/23 - SB sent email for IRS, BC called &amp; left VM, SB sent follow up text - Not available for IRS, asked for IR1 12/14/22 Carmen agreed to Ellis match 12/13/22 SB sent follow up email for IR2 matching 12/8/22 SB emailed for Ellis match 10/27/22 Completed Orientation &amp; Onboarding Training CT Scheduled training for 10/27/22 SB 10/19/22 SB followed up to schedule screening 10/12/22 passed screening with SB 10/11/22 SB sent screening email | L87: 44844.723 | Q87: 2411 Brownsboro Road, Unit 105 | R87: Dallas, Texas | S87: Dallas | T87: TX | U87: Women & Infants Specialty Health Division (WISH) at Parkland Health | V87: FY 22 - 23, Seminars 23 | W87: Yumeiry Mauricio, Wladimir Veloz Balbuena, Sabrina Galay, Alexa Velasquez and Maradiatou Kassim | X87: ELLIS, GCHS | AB87: =IFERROR(__xludf.DUMMYFUNCTION("IF( ISNUMBER(MATCH( C87, IMPORTRANGE(""https://docs.google.com/spreadsheets/d/1yTh1ELC33JHYOeEdgIiEclxPRyh0zOKtlawDltfUay8"",""'Champions'!A:A""), 0 )), ""Outreach Conducted"", """")"),"")
A88: Daniela | B88: Alarcon | C88: =CONCATENATE(A88," ",B88) -> Daniela Alarcon | D88: +19152028899 | E88: daalarcon24@gmail.com | F88: Discontinued | G88: 594 | H88: {=IFERROR(INDEX('Hub CPC 226'!A:A, MATCH(C88, 'Hub CPC 226'!B:B, 0)), "")} -> 91 | I88: {=IFERROR(INDEX('Hub Users 226'!A:A, MATCH(C88, 'Hub Users 226'!B:B, 0)), "")} -> 111 | K88: 2/14 ended match after 3rd session, few empathy to Interns &amp; their background; 2/16 had a meeting with Hetal &amp; WW, insisted quitting while being told Interns are abandoned 12/5/23 SB updated Whatsapp number to &#43;19152028899 from &#43;34667551542 11/27/23 confirmed group for IR2 SB 11/13/23 emailed saying available for IR1 - SB replied letting her know we found someone but asking for IR2 10/30/23 SB emailed for IR1 1/9/23 PT sent message on whatsapp for SB about IR2 match 1/4/23 SB followed up for IR2 match 12/15/22 SB emailed for Union square match Not available for IR1. CT 8/22/22 3/11/22 passed training SB 2/2/22 passed screening SB No show to 1/31/22 screening, SB emailed- Husband covid positive, rescheduled 1/17/22 SB sent screening scheduling email | L88: 44574.676 | Q88: Calle de la Madera 29, Piso 1 Derecha Interior Madrid Spain 28004 | R88: Madrid, Spain | U88: Student | V88: FY 21 - 22 | W88: Diego Rojas, Justin Martinez, Slinne Cruz and Yomar Matias | X88: CrotonaIHS | AB88: =IFERROR(__xludf.DUMMYFUNCTION("IF( ISNUMBER(MATCH( C88, IMPORTRANGE(""https://docs.google.com/spreadsheets/d/1yTh1ELC33JHYOeEdgIiEclxPRyh0zOKtlawDltfUay8"",""'Champions'!A:A""), 0 )), ""Outreach Conducted"", """")"),"")
A89: Dominique | B89: Kagele | C89: =CONCATENATE(A89," ",B89) -> Dominique Kagele | D89: 775-287-9482 | E89: dakagele@gmail.com | F89: Active CPC | G89: 108 | H89: {=IFERROR(INDEX('Hub CPC 226'!A:A, MATCH(C89, 'Hub CPC 226'!B:B, 0)), "")} -> 92 | I89: {=IFERROR(INDEX('Hub Users 226'!A:A, MATCH(C89, 'Hub Users 226'!B:B, 0)), "")} -> 112 | K89: 3/1/24 WW emailed for IR3 1/9/24 SB called, left VM, sent text 1/8/24 SB emailed for IR2 Crotona schedule 10/30/23 WW left VM and text for IR1; WW sent follow-up email and LinkedIn message 11/1/23 10/26/23 SB called for IR1 and left VM 10/25/23 SB sent text for IR1 10/23/23 SB emailed for IR1 7/15/23 SB emailed for IRS 3/22/23 SB sent text about IR3 availability 2/27/23 CT left voicemail &amp; sent text regarding new job position 2/7/23 CT sent follow up email regarding new position 2/6/23 CT not available for IR2 because of new job position. 2/2/23 CT left voicemail &amp; sent text asking for IR2 with Wheels schedule 1/17/23 CT sent congrats on new position &amp; asked for updated description for job duties 1/4/23 SB followed up for IR2 via email 12/15/22 SB emailed for Union Square match 10/4/22 SB messaged Dominique for ICHS Bronx match 9/30/22 emailed asking for availability for ellis match 8/12/22 Interested in IR1 SB 7/5/22 LG left voicemail and sent text for IRS - Dominique unavailable for match 6/28/22 LG sent email for IRS availability 12/28/21 SB sent IR2 FY21-22 schedule list for matching Dominique attended a training on 3/8/21 with JPS Hetal checked off that she had been screened -- by Scotney Young in 2019; she was interested just not matched with a clear understanding of the timeline to match so struggled to make things work when we reached out in 2019. JPS sent re-engagement email on 2/22/21 to see if Dominique is interested in moving forward &amp; attending a training webinar | L89: 43484.711 | Q89: 9805 Nestling Circle Elk Grove CA | R89: San Francisco, CA | S89: San Francisco | T89: CA | U89: Genentech | V89: Seminars 22, Seminars 21, FY 20 - 21, FY 21 - 22 | W89: D'Marjia Rankine, Ben Junior Polynice, Ariah Martin, Jhennel Bailey, Zihan Zhang and JiaJing Li | X89: CypressHills, HSEI, QueensPrepAcad | AB89: =IFERROR(__xludf.DUMMYFUNCTION("IF( ISNUMBER(MATCH( C89, IMPORTRANGE(""https://docs.google.com/spreadsheets/d/1yTh1ELC33JHYOeEdgIiEclxPRyh0zOKtlawDltfUay8"",""'Champions'!A:A""), 0 )), ""Outreach Conducted"", """")"),"")
A90: Dalida | B90: Jaafar | C90: =CONCATENATE(A90," ",B90) -> Dalida Jaafar | D90: 9515667361 | E90: dalidajaafar@gmail.com | F90: Inactive CPC | G90: 407 | H90: {=IFERROR(INDEX('Hub CPC 226'!A:A, MATCH(C90, 'Hub CPC 226'!B:B, 0)), "")} -> 93 | I90: {=IFERROR(INDEX('Hub Users 226'!A:A, MATCH(C90, 'Hub Users 226'!B:B, 0)), "")} -> 113 | J90: Business | K90: 5/18/22 SB sent re-engagement email JPS sent an email via Champions@speakhire.org to schedule a training webinar on 7/21/21. JPS tried to call on 6/2/21 but Dalida's mailbox was full, so JPS followed up with a text message Dalida has not been responsive to any outreach emails to attend a training since passing her screening call. JPS followed up again on 2/17/21 to schedule Dalida for a training JPS followed up on 2/9/21 to schedule Dalida for training JPS emailed congratulations email on 2/7/21 &#43; tried to schedule Dalida for a training Dalida was screened by JPS at 1 pm est on 2/5/2021 JPS emailed on 2/3/2021 to schedule a Screening Call KW double checked on 1/19 | L90: 44200.78 | Q90: 3800 W Devonshire Ave Apt 50, Hemet | R90: Hemet CA | S90: Hemet | T90: CA | U90: self employed | AB90: =IFERROR(__xludf.DUMMYFUNCTION("IF( ISNUMBER(MATCH( C90, IMPORTRANGE(""https://docs.google.com/spreadsheets/d/1yTh1ELC33JHYOeEdgIiEclxPRyh0zOKtlawDltfUay8"",""'Champions'!A:A""), 0 )), ""Outreach Conducted"", """")"),"")
A91: Lena K | B91: Dandy | C91: =CONCATENATE(A91," ",B91) -> Lena K Dandy | D91: 856-900-2505 | E91: dandylena97@gmail.com | F91: Active CPC | G91: 162 | H91: {=IFERROR(INDEX('Hub CPC 226'!A:A, MATCH(C91, 'Hub CPC 226'!B:B, 0)), "")} -> 94 | I91: {=IFERROR(INDEX('Hub Users 226'!A:A, MATCH(C91, 'Hub Users 226'!B:B, 0)), "")} -> 114 | K91: Hero Quotes: &#34;love this initiative. SPEAKHIRE is personal for me and I love what it stands for.&#34; / &#34; Love everything about the experience&#34; 7/31/23 - 100 hours of service (5 IR*18 hours) &#43; (2 Seminars * 4 hours) - Bronze award received on August 16th, 2023 4/17/23 CT sent email asking to be in-person Speaker for BCHS 3/22/23 SB sent text for IR3 2/9/23 CT sent text for IR2 2/8/23 CT sent follow up for IR2 2/6/23 CT sent email asking for IR2 with Wheels schedule 10/28/22 SB emailed for wheels 10/20/22 SB emailed for wheels availability 8/12/22 Interested in IR1 SB 12/28/21 SB sent IR2 FY21-22 schedule list for matching Lena is available for round one (11/2020) and is matched Lena was trained on 9/28/2020 at 7:30 pm EST by Jennifer Peterson-Sharma and Kiesha Charles. Hetal called on March 19, 2020. She's happy to help and share. Marked as Active. | L91: 43590.64 | Q91: 5101 Royal Crescent Court Mt. Royal, NJ 08061 | R91: NY | S91: Mt Royal | T91: NJ | U91: FMC | V91: FY 20 - 21, FY 21 - 22 | W91: Mariama Diallo, Abdurakhim Yunusov, Arwa Alhaj, Noashin Sarker, Maria Polanco, Rassiel Munoz Gomez, Mahmoud Ahmed, Nayeli Cruz, Oceanne Compaore, Djaka Kante, Fatoumata Diallo, Wendy Ouedraogo, Aicha Doukoure and Safiatou Jalloh | X91: NYC Mission - Emma Lazarus, ELLIS, IHS Health, CrotonaIHS | AB91: =IFERROR(__xludf.DUMMYFUNCTION("IF( ISNUMBER(MATCH( C91, IMPORTRANGE(""https://docs.google.com/spreadsheets/d/1yTh1ELC33JHYOeEdgIiEclxPRyh0zOKtlawDltfUay8"",""'Champions'!A:A""), 0 )), ""Outreach Conducted"", """")"),"")
A92: Daniela | B92: Russo | C92: =CONCATENATE(A92," ",B92) -> Daniela Russo | D92: 917-858-2071 | E92: danielarusso06@gmail.com | F92: Active CPC | G92: 216 | H92: {=IFERROR(INDEX('Hub CPC 226'!A:A, MATCH(C92, 'Hub CPC 226'!B:B, 0)), "")} -> 95 | I92: {=IFERROR(INDEX('Hub Users 226'!A:A, MATCH(C92, 'Hub Users 226'!B:B, 0)), "")} -> 115 | J92: Health Sciences/Medicine | K92: 7/18/23 WW emailed for IRS, PC team followed up with text and call 3/28/23 SB sent text about Ir3 10/13/22 Not available for IR1. CT 12/22/21 SB sent IR2 FY21-22 schedule list for matching JPS followed up on 2/25/21 JPS emailed on 2/22/21 to request Instructional Guide | L92: 43739.447 | M92: 6 | N92: 12 | O92: 37 | P92: 26 | Q92: 50-05 43rd Avenue | R92: New York | S92: Woodside | T92: NY | U92: Stella McCartney | V92: FY 19 - 20 | W92: Afrida Ahmed and Mahfuja Khatun | X92: ELLIS | AB92: =IFERROR(__xludf.DUMMYFUNCTION("IF( ISNUMBER(MATCH( C92, IMPORTRANGE(""https://docs.google.com/spreadsheets/d/1yTh1ELC33JHYOeEdgIiEclxPRyh0zOKtlawDltfUay8"",""'Champions'!A:A""), 0 )), ""Outreach Conducted"", """")"),"")
A93: Danielle | B93: Lian Farage | C93: =CONCATENATE(A93," ",B93) -> Danielle Lian Farage | D93: 9178428767 | E93: danielle.farage@gmail.com | F93: Active CPC | G93: 369 | H93: {=IFERROR(INDEX('Hub CPC 226'!A:A, MATCH(C93, 'Hub CPC 226'!B:B, 0)), "")} -> 96 | I93: {=IFERROR(INDEX('Hub Users 226'!A:A, MATCH(C93, 'Hub Users 226'!B:B, 0)), "")} -> 116 | J93: Health Sciences/Medicine | K93: 3/13/24 WW emailed for IR3 9/18/23 WW emailed for IR1 4/25/23 SB messaged for IR3 4/22/23 SB emailed for IR3 12/14 SB left Danielle a Voice mail 12/13/21 Hetal called Danielle about possible FY21-22 IR1 match and left VM, SB sent text, CT sent email Danielle attended a training with JPS on 5/8/21 but she has not submitted an onboarding form as of 5/10/21 JPS reached out to Danielle on 2/4/2021 to see if she would like to attend a training. JPS reached out to three times (12/29/2020, 1/2/2021, 1/4/2021) to scheduler her for a training but she never responded. Danielle was screened on 12/4/2020 at 12 pm EST by Jennifer Peterson-Sharma. Danielle is scheduled for a screening call on 12/4/2020 Jennifer followed up on 12/1/2020 to schedule a Screening Call. No reply as of 12/1/2020. Jennifer Peterson-Sharma emailed on 11/27/2020 to schedule a Screening Call. | L93: 44160.648 | M93: 12 | N93: 47 | O93: 67 | P93: 3 | Q93: 250 West 90th St, New York | R93: New York | S93: New York | T93: NY | U93: Wade & Wendy | AB93: =IFERROR(__xludf.DUMMYFUNCTION("IF( ISNUMBER(MATCH( C93, IMPORTRANGE(""https://docs.google.com/spreadsheets/d/1yTh1ELC33JHYOeEdgIiEclxPRyh0zOKtlawDltfUay8"",""'Champions'!A:A""), 0 )), ""Outreach Conducted"", """")"),"")
A94: Daniela | B94: Fernandez Espinosa | C94: =CONCATENATE(A94," ",B94) -> Daniela Fernandez Espinosa | D94: 15102069806 | E94: danyfdz.92@gmail.com | F94: Active CPC | G94: 626 | H94: {=IFERROR(INDEX('Hub CPC 226'!A:A, MATCH(C94, 'Hub CPC 226'!B:B, 0)), "")} -> 97 | I94: {=IFERROR(INDEX('Hub Users 226'!A:A, MATCH(C94, 'Hub Users 226'!B:B, 0)), "")} -> 117 | K94: 10/26/23 WW emailed for Champion-led Info Session 5/19/23 &#34;She is usually absent with no prior communication. If she joins, she needs to get reminders but still joins late and keep Sessions short. Maybe better for Seminars.&#34; -Note from PC team SB 4/18/23 SB emailed for IR3 1/5/23 confirmed Union Square schedule for IR2 SB 1/4/23 SB follow up email for IR2 12/15/22 SB emailed for IR2 Union Square 7/5/22 SB emailed for IRS match - 7/6, Daniela confirmed availability completed training with SB on 4/8/22 3/3/22 Passed screening and was sent training email. SB 3/2/22 SB sent screening scheduling email | L94: 44621.734 | Q94: 1389 Jefferson st A310 | R94: Oakland, California | S94: Oakland | T94: CA | U94: Ask Media Group | V94: FY 21 - 22, FY 22 - 23, FY 23 - 24 | W94: Navier Rojas, Luis Chimbo, Josimar Lucero, Gabriel Morris, Jatziry Guity, Anny Garcia, Doussouba Diakite, Hendry Bello, Aristid Reynoso, Adalbelys Polanco, Jeter Perez, Allison Perez, Marthiel Cruz and Jazir Cabrera | X94: ICHSBronx, IHSUnionSquare, WheelsNYC, CrotonaIHS | AB94: =IFERROR(__xludf.DUMMYFUNCTION("IF( ISNUMBER(MATCH( C94, IMPORTRANGE(""https://docs.google.com/spreadsheets/d/1yTh1ELC33JHYOeEdgIiEclxPRyh0zOKtlawDltfUay8"",""'Champions'!A:A""), 0 )), ""Outreach Conducted"", """")"),"")
A95: Dave | B95: Landa | C95: =CONCATENATE(A95," ",B95) -> Dave Landa | D95: 415-850-8614 | E95: dave.landa@lava.ai | F95: Active CPC | G95: 471 | H95: {=IFERROR(INDEX('Hub CPC 226'!A:A, MATCH(C95, 'Hub CPC 226'!B:B, 0)), "")} -> 98 | I95: {=IFERROR(INDEX('Hub Users 226'!A:A, MATCH(C95, 'Hub Users 226'!B:B, 0)), "")} -> 118 | J95: Business | K95: 4/3/23 CT sent follow up email with CPC training dates 2/22/23 CT sent follow up checking in email 2/9/23 CT sent check in email 10/12/22 CT added new phone number to profile 10/11/22 CT took out phone number because it belongs to a different person now. Sent Dave an email asking for new phone number. Speak Mandarin which we are in need of. Try to follow up again and reengage. 7/11 LG called - phone number has been disconnected; email for updated number and soiree invite 7/5/22 LG updated email address and workplace from dave@kintone.com to LAVA AI 5/18/22 SB sent re-engagement email 12/28/21 SB sent IR2 FY21-22 schedule list for matching Dave was screened on 4/30/21 | L95: 44314.381 | Q95: 31 Catskill Ct, San Anselmo, CA 94960 | R95: San Francisco, CA | S95: San Francisco | T95: CA | U95: LAVA AI | V95: FY 21 - 22 | W95: Yuzhi Fang, Long Xiong Long, Bohan Yang, Luofeng Lin, Kaite Cai and Yeling Lin | AB95: =IFERROR(__xludf.DUMMYFUNCTION("IF( ISNUMBER(MATCH( C95, IMPORTRANGE(""https://docs.google.com/spreadsheets/d/1yTh1ELC33JHYOeEdgIiEclxPRyh0zOKtlawDltfUay8"",""'Champions'!A:A""), 0 )), ""Outreach Conducted"", """")"),"")
A96: David | B96: Temple | C96: =CONCATENATE(A96," ",B96) -> David Temple | D96: 19788848156 | E96: david.temple@foxroach.com | F96: Active CPC | G96: 485 | H96: {=IFERROR(INDEX('Hub CPC 226'!A:A, MATCH(C96, 'Hub CPC 226'!B:B, 0)), "")} -> 99 | I96: {=IFERROR(INDEX('Hub Users 226'!A:A, MATCH(C96, 'Hub Users 226'!B:B, 0)), "")} -> 119 | J96: Health Sciences/Medicine | K96: 10/5/22 SB emailed for Wheels match, David agreed to schedule 12/17 SB sent text for IR1 match Completed Onboarding and Training 8/14/21 SB - had some trouble with zoom but figured it out Screened by SB on 7/12/21. Sent email to schedule training on 7/13/21 SB Sent follow up email on 7/15/21 SB Scheduled training for 8/12/21 SB | L96: 44384.377 | Q96: 526 Pacific Ave, 1204, Atlantic City, NJ 08401 | R96: 526 Pacific Ave, Apt. 1204, Atlantic City, NJ 08401 | S96: Atlantic City | T96: NJ | U96: BHHS Fox Roach Realtors | V96: FY 22 - 23, FY 21 - 22 | W96: Gary Hernandez, Ansel Castro, Aristid Reynoso, Diogo Perez, Anjalie Ramkissoon, Rowena Otero, Angelina Gil, Jennyfer Montilla, Amir Saunders, Sabina Musayeva and jefferson colon | X96: WheelsNYC, GWHS | AB96: =IFERROR(__xludf.DUMMYFUNCTION("IF( ISNUMBER(MATCH( C96, IMPORTRANGE(""https://docs.google.com/spreadsheets/d/1yTh1ELC33JHYOeEdgIiEclxPRyh0zOKtlawDltfUay8"",""'Champions'!A:A""), 0 )), ""Outreach Conducted"", """")"),"")
A97: Lee | B97: Davis | C97: =CONCATENATE(A97," ",B97) -> Lee Davis | D97: 19014962323 | E97: davisl13@mail.wlu.edu | F97: Active CPC | G97: 639 | H97: {=IFERROR(INDEX('Hub CPC 226'!A:A, MATCH(C97, 'Hub CPC 226'!B:B, 0)), "")} -> 100 | I97: {=IFERROR(INDEX('Hub Users 226'!A:A, MATCH(C97, 'Hub Users 226'!B:B, 0)), "")} -> 120 | J97: Business | K97: Other email: davisl13@alumni.wlu.edu 2/1/24 SB sent initial outreach for sponsor session -&gt; follow up 2/7 -&gt; tried other email 2/8 11/27/23 not able to be a STAR training speaker - &#34; I communicated awhile back I won't be able to continue with Speakhire for the following year and so won't be able to attend the training&#34; 3/30/23 SB sent texted about IR3 3/1/23 SB sent follow up email 2/24/23 SB emailed Wheels availability request and about Interns 1/12/23 emailed SB, &#34; I don't think I'll be able to serve this semester.&#34; - SB responded asking about IR3 1/10/23 SB emailed to follow up for IR2 1/6/23 SB emailed for IR2 match - crotona 8/15/22 Not available for IR1 SB Needs a strong group 4/29/22 passed training SB 4/18/22 passed screening call - SB 4/14/22 SB sent screening email and times for possible matches | L97: 44664.813 | M97: 10 | N97: 27 | O97: 61 | P97: 1 | Q97: 120 Greenwich St Apt 7J | R97: New York City | S97: New York | T97: NY | U97: Bank of America | V97: FY 21 - 22 | W97: Israel Martinez, Samuel Rodriguez and Joshua Jimenez | X97: WheelsNYC | AB97: =IFERROR(__xludf.DUMMYFUNCTION("IF( ISNUMBER(MATCH( C97, IMPORTRANGE(""https://docs.google.com/spreadsheets/d/1yTh1ELC33JHYOeEdgIiEclxPRyh0zOKtlawDltfUay8"",""'Champions'!A:A""), 0 )), ""Outreach Conducted"", """")"),"")
A98: Debaleena | B98: Majumdar | C98: =CONCATENATE(A98," ",B98) -> Debaleena Majumdar | D98: 17653378330 | E98: debaleena.majumdar@asu.edu | F98: Active CPC | G98: 596 | H98: {=IFERROR(INDEX('Hub CPC 226'!A:A, MATCH(C98, 'Hub CPC 226'!B:B, 0)), "")} -> 101 | I98: {=IFERROR(INDEX('Hub Users 226'!A:A, MATCH(C98, 'Hub Users 226'!B:B, 0)), "")} -> 121 | J98: Business | K98: 11/20/23 SB updated email from debaleena.majumdar@umassglobal.edu to debaleena.majumdar@asu.edu . Debaleena still looking for job and will reach out when things settle down 11/14/23 SB tried to connect on linkedin and sent message to try to get updated contact info 8/10/23 SB emailed for soiree and email bounced back with, &#34; Thank you for your email. The person you are attempting to reach is no longer with the University, this mailbox may no longer be monitored. If you are a current student, or need help with university degree programs, please call 800.746.0082.&#34; SB to text about getting an updated email 4/17/23 CT Debaleena was laid off due to budget cuts and has to focus on finding a new job. Not available for Seminars in May anymore. Reach out again in July. 3/2/23 CT asked to be Seminar Speaker for Crotona IHS 3/2/23 CT not available from April on because of busy schedule. Asked to reach out in spring 2024 3/1/23 CT asked about IR3 availability with Crotona schedule 2/28/23 CT sent email asking to take over Wheels group for IR2 Needs a strong group 1/12/23 SB emailed to thank for reference for Leigh Ann and ask for IR2 - not available on Tuesdays and asked for Wednesdays schedule - SB sent dates and she confirmed availability 7/8/22 Debaleena emailed to let us know that she is moving to a new school at her university and will be too busy with program development for being a Champion in the fall. She said she should be available in spring 2023. Hetal responded to ask if her email will change. 6/15/22 FY 21-22 IR3 she had low engagement from Interns and felt discouraged. Resulting in her feeling that re-scheduling sessions was not worth it. Give her a break for IRS and give her stronger students next round. 3/8/22 Sent email for IR3 availability CT 02/03/22 Completed CPC Orientation &amp; Onboarding Training CT 01/28/22 Sent congrats email with CPC training SB 1/17/22 SB sent screening scheduling email | L98: 44577.86 | Q98: 7440 Dwell Well Way Apt 2302, Winter Park, FL 32792 | R98: Winter Park, FL | S98: Winter Park | T98: FL | U98: School of Business and Professional Studies at University of Massachusetts Global | V98: FY 21 - 22, FY 22 - 23 | W98: Siyan Wu, Yafei Huang, Sijia Su, Siyu Liu, Wanting Huang, Phue Naing, Romina Sulaimonova, Mariama Toure, Yannick Diaby and El Hadji Ndong | X98: FlushingIHS, NYC Mission - Emma Lazarus, IHSUnionSquare | AB98: =IFERROR(__xludf.DUMMYFUNCTION("IF( ISNUMBER(MATCH( C98, IMPORTRANGE(""https://docs.google.com/spreadsheets/d/1yTh1ELC33JHYOeEdgIiEclxPRyh0zOKtlawDltfUay8"",""'Champions'!A:A""), 0 )), ""Outreach Conducted"", """")"),"")
A99: Diana | B99: Elejalde | C99: =CONCATENATE(A99," ",B99) -> Diana Elejalde | D99: 9176791832 | E99: delejalde@bseglobal.net | F99: Discontinued | G99: 210 | H99: {=IFERROR(INDEX('Hub CPC 226'!A:A, MATCH(C99, 'Hub CPC 226'!B:B, 0)), "")} -> 102 | I99: {=IFERROR(INDEX('Hub Users 226'!A:A, MATCH(C99, 'Hub Users 226'!B:B, 0)), "")} -> 122 | K99: 12/13/22 CT left voicemail &amp; sent text to re-engage 10/18/22 CT left voicemail &amp; sent text regarding new email address &amp; re-engagement. 09/15/22 CT sent email regarding references but bounced back. 5/24/22 SB sent re-engagement email 11/15/21 SB sent engagement text 10/8/21 SB sent email about screening call, email bounced back. Trying phone JPS sent email on 7/20/21 to check on Diana's status. Sent scheduling a screening email 3/2/21. SU. Hetal sent a screening email 03/04/21. Soneya send a follow up - screening email 3/9/21. Diana scheduled a screening call 3/16/2021.SU. Sent a revise email to schedule a screening call 3/19/2021. SU. Diana pick up she said she will set up a screening call within this week. 3/22/2021. SU. Diana pick up and stated she will liket to come back for the next session in Fall. SU. 4/6/2021. Diana did not show up to her screening call on 3/30/21. dianamelej@gmail.com (personal email) JPS emailed on 2/7/2021 to re-engage and schedule a Screening Call Jennifer Peterson-Sharma called and left vm on 10/6/2020 to check in on Diana's availability for the 2020-2021 mentoring rounds. | L99: 43738.836 | M99: 10 | N99: 25 | O99: 44 | P99: 35 | Q99: 295 Flatbush Ave | R99: Brooklyn | S99: Brooklyn | T99: NY | U99: Jax Media | AB99: =IFERROR(__xludf.DUMMYFUNCTION("IF( ISNUMBER(MATCH( C99, IMPORTRANGE(""https://docs.google.com/spreadsheets/d/1yTh1ELC33JHYOeEdgIiEclxPRyh0zOKtlawDltfUay8"",""'Champions'!A:A""), 0 )), ""Outreach Conducted"", """")"),"")
A100: Demi | B100: Ajayi | C100: =CONCATENATE(A100," ",B100) -> Demi Ajayi | D100: 857-928-3835 | E100: demi.ajayi@gmail.com | F100: Inactive CPC | G100: 90 | H100: {=IFERROR(INDEX('Hub CPC 226'!A:A, MATCH(C100, 'Hub CPC 226'!B:B, 0)), "")} -> 103 | I100: {=IFERROR(INDEX('Hub Users 226'!A:A, MATCH(C100, 'Hub Users 226'!B:B, 0)), "")} -> 123 | K100: Unsubscribed from Newsletter, not responsive KW 6/10/25 Recently had a Child, making as inactive. Try for FY 22-23? SB 2/28/22 Demi appears to respond better with texts instead of emails. Demi had a refresher training with Jennifer Peterson-Sharma on 11/30/2020 at 4 pm EST. She is mentoring for Round One 2020 (filling in last minute). Have not heard back from Demi and Jennifer Peterson-Sharma followed up again on 10/6/2020. Emailed on 9/28/2020 to ask if she speaks French for a potential mentee match. | L100: 43393.574 | M100: 10 | N100: 20 | O100: 44 | P100: 35 | Q100: 203 Underhill Avenue #1F Brooklyn NY 11238 | R100: New York, NY | S100: Brooklyn | T100: NY | U100: IBM | V100: FY 20 - 21 | W100: Alpha Sylla and Abrahan Castro | X100: ELLIS | AB100: =IFERROR(__xludf.DUMMYFUNCTION("IF( ISNUMBER(MATCH( C100, IMPORTRANGE(""https://docs.google.com/spreadsheets/d/1yTh1ELC33JHYOeEdgIiEclxPRyh0zOKtlawDltfUay8"",""'Champions'!A:A""), 0 )), ""Outreach Conducted"", """")"),"")
...

Sheet Interns
A1: Contact Status | B1: Duplicate Record | C1: Full Name | D1: First Name | E1: Last Name | F1: Hub Intern ID | G1: Hub User ID | H1: Kintone Record Number | I1: Main Career Field | J1: Country of Origin | K1: Continent of Origin | L1: Gender | M1: Email Address | N1: Date Applied | O1: Birthdate | P1: Current Age | Q1: Notes | R1: Address | S1: NY Congressional Districts | T1: NY Senate District | U1: NY Assembly District | V1: NYC City Council District (Personal Address) | W1: City | X1: State | Y1: Phone Number | Z1: Associated Partner Organization | AA1: Associated Partner Organization | AB1: NYC City Council District (School) | AC1: Programs Participated In | AD1: Ambassador | AE1: Year | AF1: Connected Champions | AG1: Other Activities Participated in | AH1: Hub Active | AI1: Sessions Attended vs not attended | AJ1: Quotes/Testimonials Internship Session Feedback Canva Posts | AK1: Alumni Outreach Status | AL1: Events Invited To | AM1: Notes | AN1: Awards | AO1: Parent/Guardian Name | AP1: Guardian Relationship to Intern | AQ1: Guardian Email | AR1: Guardian Phone Number | AS1: College Attended Alumni Outreach | AT1: Outreach Notes
A2: Alum | B2: Unique | C2: =CONCATENATE(D2," ",E2) -> Ngawang Tashi | D2: Ngawang | E2: Tashi | F2: {=IFERROR( INDEX('Hub Interns 226'!A:A, MATCH(C2, 'Hub Interns 226'!B:B, 0)),"")} -> 935 | G2: {=IFERROR( INDEX('Hub Users 226'!A:A, MATCH(C2, 'Hub Users 226'!B:B, 0)),"")} -> 1368 | H2: 1574 | I2: Health Sciences/Medicine | L2: Male-identifying | M2: ngawangt14@nycstudents.net | N2: 45016.363 | O2: 40430 | P2: =DATEDIF(O2, TODAY(), "Y") -> 15 | Q2: He emailed us in 6/26 giving his address. After that Ops. has been emailing to get him sharing more info (bank account #, etc.) We tried through his school too but, no response until now. 8/23- PQ | R2: Is5 | W2: Queens | X2: NY | Y2: +17182056788 | Z2: NYC IS 5 NY | AA2: WCSL5 | AB2: 30 | AC2: DL | AD2: Yes | AE2: 22 - 23 | AH2: =IFERROR(__xludf.DUMMYFUNCTION("IF( ISNUMBER(MATCH( C2, IMPORTRANGE(""https://docs.google.com/spreadsheets/d/1yTh1ELC33JHYOeEdgIiEclxPRyh0zOKtlawDltfUay8"",""'Interns'!A:A""), 0 )), ""Outreach Conducted"", """")"),"") | AK2: =IFERROR(__xludf.DUMMYFUNCTION("XLOOKUP(C2, IMPORTRANGE(""1RdEdgHYrZ33LJ7RUHj_h-qkAFL92bcVjtIdVa-UlsCw"", ""Interns!D:D""), IMPORTRANGE(""1RdEdgHYrZ33LJ7RUHj_h-qkAFL92bcVjtIdVa-UlsCw"", ""Interns!M:M""), ""Not Found"")"),"Contacted") -> Contacted | AL2: =IFERROR(__xludf.DUMMYFUNCTION("XLOOKUP(C2, IMPORTRANGE(""1RdEdgHYrZ33LJ7RUHj_h-qkAFL92bcVjtIdVa-UlsCw"", ""Interns!D:D""), IMPORTRANGE(""1RdEdgHYrZ33LJ7RUHj_h-qkAFL92bcVjtIdVa-UlsCw"", ""Interns!N:N""), ""Not Found"")"),"#Cheers4Careers") -> #Cheers4Careers | AM2: =IFERROR(__xludf.DUMMYFUNCTION("XLOOKUP(C2, IMPORTRANGE(""1RdEdgHYrZ33LJ7RUHj_h-qkAFL92bcVjtIdVa-UlsCw"", ""Interns!D:D""), IMPORTRANGE(""1RdEdgHYrZ33LJ7RUHj_h-qkAFL92bcVjtIdVa-UlsCw"", ""Interns!O:O""), ""Not Found"")"),"Hetal reached out March 27 for March #Cheers4 Careers ") -> Hetal reached out March 27 for March #Cheers4 Careers | AO2: Osisiske | AP2: Uncle/Aunt/Guardian
A3: Alum | B3: Unique | C3: =CONCATENATE(D3," ",E3) -> Verni Perez | D3: Verni | E3: Perez | F3: {=IFERROR( INDEX('Hub Interns 226'!A:A, MATCH(C3, 'Hub Interns 226'!B:B, 0)),"")} -> 1173 | G3: {=IFERROR( INDEX('Hub Users 226'!A:A, MATCH(C3, 'Hub Users 226'!B:B, 0)),"")} -> 1606 | H3: 1571 | J3: Honduras | K3: North America | L3: Male-identifying | M3: vernip@nycstudents.net | N3: 45015.542 | O3: 44959 | P3: =DATEDIF(O3, TODAY(), "Y") -> 3 | R3: No. | Y3: +19293965438 | Z3: NYC IS 5 NY | AA3: WCSL5 | AB3: 30 | AC3: DL | AE3: 22 - 23 | AH3: =IFERROR(__xludf.DUMMYFUNCTION("IF( ISNUMBER(MATCH( C3, IMPORTRANGE(""https://docs.google.com/spreadsheets/d/1yTh1ELC33JHYOeEdgIiEclxPRyh0zOKtlawDltfUay8"",""'Interns'!A:A""), 0 )), ""Outreach Conducted"", """")"),"") | AK3: =IFERROR(__xludf.DUMMYFUNCTION("XLOOKUP(C3, IMPORTRANGE(""1RdEdgHYrZ33LJ7RUHj_h-qkAFL92bcVjtIdVa-UlsCw"", ""Interns!D:D""), IMPORTRANGE(""1RdEdgHYrZ33LJ7RUHj_h-qkAFL92bcVjtIdVa-UlsCw"", ""Interns!M:M""), ""Not Found"")"),"Contacted") -> Contacted | AL3: =IFERROR(__xludf.DUMMYFUNCTION("XLOOKUP(C3, IMPORTRANGE(""1RdEdgHYrZ33LJ7RUHj_h-qkAFL92bcVjtIdVa-UlsCw"", ""Interns!D:D""), IMPORTRANGE(""1RdEdgHYrZ33LJ7RUHj_h-qkAFL92bcVjtIdVa-UlsCw"", ""Interns!N:N""), ""Not Found"")"),"#Cheers4Careers") -> #Cheers4Careers | AM3: =IFERROR(__xludf.DUMMYFUNCTION("XLOOKUP(C3, IMPORTRANGE(""1RdEdgHYrZ33LJ7RUHj_h-qkAFL92bcVjtIdVa-UlsCw"", ""Interns!D:D""), IMPORTRANGE(""1RdEdgHYrZ33LJ7RUHj_h-qkAFL92bcVjtIdVa-UlsCw"", ""Interns!O:O""), ""Not Found"")"),"Hetal reached out March 27 for March #Cheers4 Careers ") -> Hetal reached out March 27 for March #Cheers4 Careers | AO3: Iris Vega | AP3: Mother
A4: Alum | B4: Unique | C4: =CONCATENATE(D4," ",E4) -> Munir ahmad Bakhtyar | D4: Munir ahmad | E4: Bakhtyar | F4: {=IFERROR( INDEX('Hub Interns 226'!A:A, MATCH(C4, 'Hub Interns 226'!B:B, 0)),"")} -> 866 | G4: {=IFERROR( INDEX('Hub Users 226'!A:A, MATCH(C4, 'Hub Users 226'!B:B, 0)),"")} -> 1299 | H4: 375 | I4: Armed Services/Law Enforcement | J4: Afghanistan | K4: Asia | L4: Male-identifying | M4: mbakhtyar@flushinginternational.org | N4: 44252.822 | O4: 37925 | P4: =DATEDIF(O4, TODAY(), "Y") -> 22 | R4: 11355 | W4: Queens | X4: NY | Y4: +16466595476 | Z4: Flushing International High School NY | AA4: FlushingIHS | AB4: 20 | AC4: FY | AE4: 20 - 21 | AF4: =IFERROR(__xludf.DUMMYFUNCTION("TEXTJOIN("", "", TRUE, FILTER(Champions!C:C, ISNUMBER(SEARCH(C4, Champions!W:W)) ) )"),"Joseph Temowo, Sana Ahmad") -> Joseph Temowo, Sana Ahmad | AH4: =IFERROR(__xludf.DUMMYFUNCTION("IF( ISNUMBER(MATCH( C4, IMPORTRANGE(""https://docs.google.com/spreadsheets/d/1yTh1ELC33JHYOeEdgIiEclxPRyh0zOKtlawDltfUay8"",""'Interns'!A:A""), 0 )), ""Outreach Conducted"", """")"),"") | AK4: =IFERROR(__xludf.DUMMYFUNCTION("XLOOKUP(C4, IMPORTRANGE(""1RdEdgHYrZ33LJ7RUHj_h-qkAFL92bcVjtIdVa-UlsCw"", ""Interns!D:D""), IMPORTRANGE(""1RdEdgHYrZ33LJ7RUHj_h-qkAFL92bcVjtIdVa-UlsCw"", ""Interns!M:M""), ""Not Found"")"),"Contacted") -> Contacted | AL4: =IFERROR(__xludf.DUMMYFUNCTION("XLOOKUP(C4, IMPORTRANGE(""1RdEdgHYrZ33LJ7RUHj_h-qkAFL92bcVjtIdVa-UlsCw"", ""Interns!D:D""), IMPORTRANGE(""1RdEdgHYrZ33LJ7RUHj_h-qkAFL92bcVjtIdVa-UlsCw"", ""Interns!N:N""), ""Not Found"")"),"#Cheers4Careers") -> #Cheers4Careers | AM4: =IFERROR(__xludf.DUMMYFUNCTION("XLOOKUP(C4, IMPORTRANGE(""1RdEdgHYrZ33LJ7RUHj_h-qkAFL92bcVjtIdVa-UlsCw"", ""Interns!D:D""), IMPORTRANGE(""1RdEdgHYrZ33LJ7RUHj_h-qkAFL92bcVjtIdVa-UlsCw"", ""Interns!O:O""), ""Not Found"")"),"Hetal reached out by email 3/27 followed by text") -> Hetal reached out by email 3/27 followed by text | AO4: BASHIR Ahmad | AP4: Father | AQ4: bashirahmadbakhtyar786@gmail.com | AR4: +19143127820
A5: Alum | B5: Unique | C5: =CONCATENATE(D5," ",E5) -> Baseria Atta | D5: Baseria | E5: Atta | F5: {=IFERROR( INDEX('Hub Interns 226'!A:A, MATCH(C5, 'Hub Interns 226'!B:B, 0)),"")} | G5: {=IFERROR( INDEX('Hub Users 226'!A:A, MATCH(C5, 'Hub Users 226'!B:B, 0)),"")} -> 730 | H5: 571 | I5: Business | J5: Afghanistan | K5: Asia | L5: Female-identifying | M5: bibibaseria2019@flushinginternational.org | N5: 44480.53 | O5: 38059 | P5: =DATEDIF(O5, TODAY(), "Y") -> 22 | Q5: HJ Changed language from not comfortable to very comfortable based on short answers | R5: 147-10-41 Ave apt 5p flusing NY 11355 | S5: 6 | T5: 16 | U5: 40 | V5: 20 | W5: Queens | X5: NY | Y5: +13478811966 | Z5: Flushing International High School NY | AA5: FlushingIHS | AB5: 20 | AC5: FY | AE5: 21 - 22 | AF5: =IFERROR(__xludf.DUMMYFUNCTION("TEXTJOIN("", "", TRUE, FILTER(Champions!C:C, ISNUMBER(SEARCH(C5, Champions!W:W)) ) )"),"Madhumitha Sowndararajan, Vatsala Sarathy") -> Madhumitha Sowndararajan, Vatsala Sarathy | AH5: =IFERROR(__xludf.DUMMYFUNCTION("IF( ISNUMBER(MATCH( C5, IMPORTRANGE(""https://docs.google.com/spreadsheets/d/1yTh1ELC33JHYOeEdgIiEclxPRyh0zOKtlawDltfUay8"",""'Interns'!A:A""), 0 )), ""Outreach Conducted"", """")"),"") | AK5: =IFERROR(__xludf.DUMMYFUNCTION("XLOOKUP(C5, IMPORTRANGE(""1RdEdgHYrZ33LJ7RUHj_h-qkAFL92bcVjtIdVa-UlsCw"", ""Interns!D:D""), IMPORTRANGE(""1RdEdgHYrZ33LJ7RUHj_h-qkAFL92bcVjtIdVa-UlsCw"", ""Interns!M:M""), ""Not Found"")"),"Contacted") -> Contacted | AL5: =IFERROR(__xludf.DUMMYFUNCTION("XLOOKUP(C5, IMPORTRANGE(""1RdEdgHYrZ33LJ7RUHj_h-qkAFL92bcVjtIdVa-UlsCw"", ""Interns!D:D""), IMPORTRANGE(""1RdEdgHYrZ33LJ7RUHj_h-qkAFL92bcVjtIdVa-UlsCw"", ""Interns!N:N""), ""Not Found"")"),"#Cheers4Careers") -> #Cheers4Careers | AM5: =IFERROR(__xludf.DUMMYFUNCTION("XLOOKUP(C5, IMPORTRANGE(""1RdEdgHYrZ33LJ7RUHj_h-qkAFL92bcVjtIdVa-UlsCw"", ""Interns!D:D""), IMPORTRANGE(""1RdEdgHYrZ33LJ7RUHj_h-qkAFL92bcVjtIdVa-UlsCw"", ""Interns!O:O""), ""Not Found"")"),"Hetal reached out by email 3/27 followed by text") -> Hetal reached out by email 3/27 followed by text | AO5: Atta Mohammad | AP5: Father | AQ5: bibibaseria2019@flushinginternational.org | AR5: +13478811966
A6: Inactive | B6: Unique | C6: =CONCATENATE(D6," ",E6) -> cristofe hernandez | D6: cristofe | E6: hernandez | F6: {=IFERROR( INDEX('Hub Interns 226'!A:A, MATCH(C6, 'Hub Interns 226'!B:B, 0)),"")} -> 393 | G6: {=IFERROR( INDEX('Hub Users 226'!A:A, MATCH(C6, 'Hub Users 226'!B:B, 0)),"")} -> 826 | H6: 933 | I6: Social Sciences/Psychology | L6: Male-identifying | M6: cristofe.hernandez@ichsbronx.org | N6: 44603.483 | O6: 38659 | P6: =DATEDIF(O6, TODAY(), "Y") -> 20 | R6: 2600 creston av | S6: 13 | T6: 33 | U6: 78 | V6: 14 | W6: Bronx | X6: NY | Y6: +19292458574 | Z6: ICHS-Bronx NY | AA6: ICHSBronx | AB6: 8 | AC6: EL | AE6: 21 - 22 | AH6: =IFERROR(__xludf.DUMMYFUNCTION("IF( ISNUMBER(MATCH( C6, IMPORTRANGE(""https://docs.google.com/spreadsheets/d/1yTh1ELC33JHYOeEdgIiEclxPRyh0zOKtlawDltfUay8"",""'Interns'!A:A""), 0 )), ""Outreach Conducted"", """")"),"") | AK6: =IFERROR(__xludf.DUMMYFUNCTION("XLOOKUP(C6, IMPORTRANGE(""1RdEdgHYrZ33LJ7RUHj_h-qkAFL92bcVjtIdVa-UlsCw"", ""Interns!D:D""), IMPORTRANGE(""1RdEdgHYrZ33LJ7RUHj_h-qkAFL92bcVjtIdVa-UlsCw"", ""Interns!M:M""), ""Not Found"")"),"") | AL6: =IFERROR(__xludf.DUMMYFUNCTION("XLOOKUP(C6, IMPORTRANGE(""1RdEdgHYrZ33LJ7RUHj_h-qkAFL92bcVjtIdVa-UlsCw"", ""Interns!D:D""), IMPORTRANGE(""1RdEdgHYrZ33LJ7RUHj_h-qkAFL92bcVjtIdVa-UlsCw"", ""Interns!N:N""), ""Not Found"")"),"") | AM6: =IFERROR(__xludf.DUMMYFUNCTION("XLOOKUP(C6, IMPORTRANGE(""1RdEdgHYrZ33LJ7RUHj_h-qkAFL92bcVjtIdVa-UlsCw"", ""Interns!D:D""), IMPORTRANGE(""1RdEdgHYrZ33LJ7RUHj_h-qkAFL92bcVjtIdVa-UlsCw"", ""Interns!O:O""), ""Not Found"")"),"") | AO6: Ross hernandez | AP6: Mother
A7: Alum | B7: Unique | C7: =CONCATENATE(D7," ",E7) -> Asia Atta | D7: Asia | E7: Atta | F7: {=IFERROR( INDEX('Hub Interns 226'!A:A, MATCH(C7, 'Hub Interns 226'!B:B, 0)),"")} -> 296 | G7: {=IFERROR( INDEX('Hub Users 226'!A:A, MATCH(C7, 'Hub Users 226'!B:B, 0)),"")} -> 729 | H7: 592 | I7: Business | J7: Afghanistan | K7: Asia | L7: Female-identifying | M7: bibiasia2019@flushinginternational.org | N7: 44486.542 | O7: 38505 | P7: =DATEDIF(O7, TODAY(), "Y") -> 20 | R7: 147-10-41Ave flushing NY 11355 | S7: 6 | T7: 16 | U7: 40 | V7: 20 | W7: Queens | X7: NY | Z7: Flushing International High School NY | AA7: FlushingIHS | AB7: 20 | AC7: FY | AE7: 21 - 22 | AF7: =IFERROR(__xludf.DUMMYFUNCTION("TEXTJOIN("", "", TRUE, FILTER(Champions!C:C, ISNUMBER(SEARCH(C7, Champions!W:W)) ) )"),"Neha Ganjoo, Madhumitha Sowndararajan") -> Neha Ganjoo, Madhumitha Sowndararajan | AH7: =IFERROR(__xludf.DUMMYFUNCTION("IF( ISNUMBER(MATCH( C7, IMPORTRANGE(""https://docs.google.com/spreadsheets/d/1yTh1ELC33JHYOeEdgIiEclxPRyh0zOKtlawDltfUay8"",""'Interns'!A:A""), 0 )), ""Outreach Conducted"", """")"),"") | AK7: =IFERROR(__xludf.DUMMYFUNCTION("XLOOKUP(C7, IMPORTRANGE(""1RdEdgHYrZ33LJ7RUHj_h-qkAFL92bcVjtIdVa-UlsCw"", ""Interns!D:D""), IMPORTRANGE(""1RdEdgHYrZ33LJ7RUHj_h-qkAFL92bcVjtIdVa-UlsCw"", ""Interns!M:M""), ""Not Found"")"),"Contacted") -> Contacted | AL7: =IFERROR(__xludf.DUMMYFUNCTION("XLOOKUP(C7, IMPORTRANGE(""1RdEdgHYrZ33LJ7RUHj_h-qkAFL92bcVjtIdVa-UlsCw"", ""Interns!D:D""), IMPORTRANGE(""1RdEdgHYrZ33LJ7RUHj_h-qkAFL92bcVjtIdVa-UlsCw"", ""Interns!N:N""), ""Not Found"")"),"#Cheers4Careers") -> #Cheers4Careers | AM7: =IFERROR(__xludf.DUMMYFUNCTION("XLOOKUP(C7, IMPORTRANGE(""1RdEdgHYrZ33LJ7RUHj_h-qkAFL92bcVjtIdVa-UlsCw"", ""Interns!D:D""), IMPORTRANGE(""1RdEdgHYrZ33LJ7RUHj_h-qkAFL92bcVjtIdVa-UlsCw"", ""Interns!O:O""), ""Not Found"")"),"Hetal reached out by email 3/27") -> Hetal reached out by email 3/27 | AO7: Atta Mohammed | AP7: Father | AQ7: matta2073@gmail.com | AR7: +13478811966
A8: Alum | B8: Unique | C8: =CONCATENATE(D8," ",E8) -> Ehsanullah Sulimanzoy | D8: Ehsanullah | E8: Sulimanzoy | F8: {=IFERROR( INDEX('Hub Interns 226'!A:A, MATCH(C8, 'Hub Interns 226'!B:B, 0)),"")} -> 500 | G8: {=IFERROR( INDEX('Hub Users 226'!A:A, MATCH(C8, 'Hub Users 226'!B:B, 0)),"")} -> 933 | H8: 248 | I8: STEM (Science, Technology, Engineering, Math) | J8: Afghanistan | K8: Asia | L8: Male-identifying | M8: esulimanzoy2020@gmail.com | N8: 44140.521 | O8: 37665 | P8: =DATEDIF(O8, TODAY(), "Y") -> 23 | Q8: school email: 10085622@philasd.org | R8: 6063 ROOSEVELT BLVD #220, PHILADELPHIA, PA 19149-3340 | W8: Philadelphia | X8: PA | Y8: 267-991-4981 | Z8: Frankford HS Philadelphia | AA8: Frankford | AB8: Philadelphia City Council District 10 | AC8: FY | AE8: 20 - 21 | AF8: =IFERROR(__xludf.DUMMYFUNCTION("TEXTJOIN("", "", TRUE, FILTER(Champions!C:C, ISNUMBER(SEARCH(C8, Champions!W:W)) ) )"),"Ian Paratore, Naqeebullah Jalalzay, Nilesh Murthy") -> Ian Paratore, Naqeebullah Jalalzay, Nilesh Murthy | AH8: =IFERROR(__xludf.DUMMYFUNCTION("IF( ISNUMBER(MATCH( C8, IMPORTRANGE(""https://docs.google.com/spreadsheets/d/1yTh1ELC33JHYOeEdgIiEclxPRyh0zOKtlawDltfUay8"",""'Interns'!A:A""), 0 )), ""Outreach Conducted"", """")"),"") | AK8: =IFERROR(__xludf.DUMMYFUNCTION("XLOOKUP(C8, IMPORTRANGE(""1RdEdgHYrZ33LJ7RUHj_h-qkAFL92bcVjtIdVa-UlsCw"", ""Interns!D:D""), IMPORTRANGE(""1RdEdgHYrZ33LJ7RUHj_h-qkAFL92bcVjtIdVa-UlsCw"", ""Interns!M:M""), ""Not Found"")"),"") | AL8: =IFERROR(__xludf.DUMMYFUNCTION("XLOOKUP(C8, IMPORTRANGE(""1RdEdgHYrZ33LJ7RUHj_h-qkAFL92bcVjtIdVa-UlsCw"", ""Interns!D:D""), IMPORTRANGE(""1RdEdgHYrZ33LJ7RUHj_h-qkAFL92bcVjtIdVa-UlsCw"", ""Interns!N:N""), ""Not Found"")"),"") | AM8: =IFERROR(__xludf.DUMMYFUNCTION("XLOOKUP(C8, IMPORTRANGE(""1RdEdgHYrZ33LJ7RUHj_h-qkAFL92bcVjtIdVa-UlsCw"", ""Interns!D:D""), IMPORTRANGE(""1RdEdgHYrZ33LJ7RUHj_h-qkAFL92bcVjtIdVa-UlsCw"", ""Interns!O:O""), ""Not Found"")"),"") | AO8: Suliman | AP8: Father | AQ8: sahmadzay2010@gmail.com | AR8: 2679914980
A9: Alum | B9: Unique | C9: =CONCATENATE(D9," ",E9) -> Matiullah Sulimanzoy | D9: Matiullah | E9: Sulimanzoy | F9: {=IFERROR( INDEX('Hub Interns 226'!A:A, MATCH(C9, 'Hub Interns 226'!B:B, 0)),"")} | G9: {=IFERROR( INDEX('Hub Users 226'!A:A, MATCH(C9, 'Hub Users 226'!B:B, 0)),"")} -> 1337 | H9: 238 | I9: Health Sciences/Medicine | J9: Afghanistan | K9: Asia | L9: Male-identifying | M9: msulimanzoy2020@gmail.com | N9: 44131.513 | O9: 37033 | P9: =DATEDIF(O9, TODAY(), "Y") -> 24 | Q9: Mother's cell phone 2679914981 I came from Afghanistan in the spring of 2020 and went directly into remote learning because of COVID. Although remote learning was difficult, SPEAKHIRE and my Foundational Year Champions saw through my English learning and now I can speak better English to ensure my college success next year. I am hardworking, attentive, and competitive so I want to excel in my English studies and stand out amongst the competitors in my future film career. Even as an immigrant English learner from Afghanistan, I know I will make it big with the help of Career Pathways Champions. | R9: 6063 ROOSEVELT BLVD #220, PHILADELPHIA, PA 19149-3340 | W9: Philadelphia | X9: PA | Y9: 267-991-4981 | Z9: Frankford HS Philadelphia | AA9: Frankford | AB9: Philadelphia City Council District 10 | AC9: FY | AE9: 20 - 21 | AF9: =IFERROR(__xludf.DUMMYFUNCTION("TEXTJOIN("", "", TRUE, FILTER(Champions!C:C, ISNUMBER(SEARCH(C9, Champions!W:W)) ) )"),"Ian Paratore, Naqeebullah Jalalzay, Nilesh Murthy") -> Ian Paratore, Naqeebullah Jalalzay, Nilesh Murthy | AH9: =IFERROR(__xludf.DUMMYFUNCTION("IF( ISNUMBER(MATCH( C9, IMPORTRANGE(""https://docs.google.com/spreadsheets/d/1yTh1ELC33JHYOeEdgIiEclxPRyh0zOKtlawDltfUay8"",""'Interns'!A:A""), 0 )), ""Outreach Conducted"", """")"),"") | AK9: =IFERROR(__xludf.DUMMYFUNCTION("XLOOKUP(C9, IMPORTRANGE(""1RdEdgHYrZ33LJ7RUHj_h-qkAFL92bcVjtIdVa-UlsCw"", ""Interns!D:D""), IMPORTRANGE(""1RdEdgHYrZ33LJ7RUHj_h-qkAFL92bcVjtIdVa-UlsCw"", ""Interns!M:M""), ""Not Found"")"),"") | AL9: =IFERROR(__xludf.DUMMYFUNCTION("XLOOKUP(C9, IMPORTRANGE(""1RdEdgHYrZ33LJ7RUHj_h-qkAFL92bcVjtIdVa-UlsCw"", ""Interns!D:D""), IMPORTRANGE(""1RdEdgHYrZ33LJ7RUHj_h-qkAFL92bcVjtIdVa-UlsCw"", ""Interns!N:N""), ""Not Found"")"),"") | AM9: =IFERROR(__xludf.DUMMYFUNCTION("XLOOKUP(C9, IMPORTRANGE(""1RdEdgHYrZ33LJ7RUHj_h-qkAFL92bcVjtIdVa-UlsCw"", ""Interns!D:D""), IMPORTRANGE(""1RdEdgHYrZ33LJ7RUHj_h-qkAFL92bcVjtIdVa-UlsCw"", ""Interns!O:O""), ""Not Found"")"),"") | AO9: Suliman | AP9: Father | AQ9: sahmadzay2010@gmail.com | AR9: 2679914980
A10: Alum | B10: Unique | C10: =CONCATENATE(D10," ",E10) -> Rasoul Sher Ahmad | D10: Rasoul Sher | E10: Ahmad | F10: {=IFERROR( INDEX('Hub Interns 226'!A:A, MATCH(C10, 'Hub Interns 226'!B:B, 0)),"")} | G10: {=IFERROR( INDEX('Hub Users 226'!A:A, MATCH(C10, 'Hub Users 226'!B:B, 0)),"")} -> 1529 | H10: 635 | I10: Business | J10: Afghanistan | K10: Asia | L10: Male-identifying | M10: sher2019@flushinginternational.org | N10: 44498.492 | O10: 38497 | P10: =DATEDIF(O10, TODAY(), "Y") -> 20 | Q10: Hetal changed from 'Very comfortable' to 'somewhat comfortable' from short responses (10.31.21) | R10: rent house the adrees is flushing main st zip 11355 | W10: Queens | X10: NY | Z10: Flushing International High School NY | AA10: FlushingIHS | AB10: 20 | AC10: FY | AE10: 21 - 22 | AF10: =IFERROR(__xludf.DUMMYFUNCTION("TEXTJOIN("", "", TRUE, FILTER(Champions!C:C, ISNUMBER(SEARCH(C10, Champions!W:W)) ) )"),"Madhumitha Sowndararajan, Vatsala Sarathy") -> Madhumitha Sowndararajan, Vatsala Sarathy | AH10: =IFERROR(__xludf.DUMMYFUNCTION("IF( ISNUMBER(MATCH( C10, IMPORTRANGE(""https://docs.google.com/spreadsheets/d/1yTh1ELC33JHYOeEdgIiEclxPRyh0zOKtlawDltfUay8"",""'Interns'!A:A""), 0 )), ""Outreach Conducted"", """")"),"") | AK10: =IFERROR(__xludf.DUMMYFUNCTION("XLOOKUP(C10, IMPORTRANGE(""1RdEdgHYrZ33LJ7RUHj_h-qkAFL92bcVjtIdVa-UlsCw"", ""Interns!D:D""), IMPORTRANGE(""1RdEdgHYrZ33LJ7RUHj_h-qkAFL92bcVjtIdVa-UlsCw"", ""Interns!M:M""), ""Not Found"")"),"Contacted") -> Contacted | AL10: =IFERROR(__xludf.DUMMYFUNCTION("XLOOKUP(C10, IMPORTRANGE(""1RdEdgHYrZ33LJ7RUHj_h-qkAFL92bcVjtIdVa-UlsCw"", ""Interns!D:D""), IMPORTRANGE(""1RdEdgHYrZ33LJ7RUHj_h-qkAFL92bcVjtIdVa-UlsCw"", ""Interns!N:N""), ""Not Found"")"),"#Cheers4Careers") -> #Cheers4Careers | AM10: =IFERROR(__xludf.DUMMYFUNCTION("XLOOKUP(C10, IMPORTRANGE(""1RdEdgHYrZ33LJ7RUHj_h-qkAFL92bcVjtIdVa-UlsCw"", ""Interns!D:D""), IMPORTRANGE(""1RdEdgHYrZ33LJ7RUHj_h-qkAFL92bcVjtIdVa-UlsCw"", ""Interns!O:O""), ""Not Found"")"),"Hetal reached out by email 3/27 followed by text") -> Hetal reached out by email 3/27 followed by text | AO10: Rasoul ghulam | AP10: Father | AQ10: sher2019@flushinginternational.org | AR10: +19177045190
A11: Alum | B11: Unique | C11: =CONCATENATE(D11," ",E11) -> Madina Raufi | D11: Madina | E11: Raufi | F11: {=IFERROR( INDEX('Hub Interns 226'!A:A, MATCH(C11, 'Hub Interns 226'!B:B, 0)),"")} -> 817 | G11: {=IFERROR( INDEX('Hub Users 226'!A:A, MATCH(C11, 'Hub Users 226'!B:B, 0)),"")} -> 1250 | H11: 358 | I11: STEM (Science, Technology, Engineering, Math) | J11: Afghanistan | K11: Asia | L11: Female-identifying | M11: madina.rawofi@gmail.com | N11: 44248.896 | O11: 37695 | P11: =DATEDIF(O11, TODAY(), "Y") -> 23 | R11: 71-71 Parsons Blvd Fresh Meadows, NY 11365 United States | S11: 6 | T11: 16 | U11: 27 | V11: 24 | W11: Queens | X11: NY | Y11: +17187993207 | Z11: Flushing International High School NY | AA11: FlushingIHS | AB11: 20 | AC11: FY | AE11: 20 - 21 | AF11: =IFERROR(__xludf.DUMMYFUNCTION("TEXTJOIN("", "", TRUE, FILTER(Champions!C:C, ISNUMBER(SEARCH(C11, Champions!W:W)) ) )"),"Swathi Koundinya, Danielle Flood") -> Swathi Koundinya, Danielle Flood | AH11: =IFERROR(__xludf.DUMMYFUNCTION("IF( ISNUMBER(MATCH( C11, IMPORTRANGE(""https://docs.google.com/spreadsheets/d/1yTh1ELC33JHYOeEdgIiEclxPRyh0zOKtlawDltfUay8"",""'Interns'!A:A""), 0 )), ""Outreach Conducted"", """")"),"") | AJ11: I just love having this internship and meeting new people! Thank you so much. I would like to take this SPEAKHIRE internship next year. Thank you for giving us an amazing internship program! | AK11: =IFERROR(__xludf.DUMMYFUNCTION("XLOOKUP(C11, IMPORTRANGE(""1RdEdgHYrZ33LJ7RUHj_h-qkAFL92bcVjtIdVa-UlsCw"", ""Interns!D:D""), IMPORTRANGE(""1RdEdgHYrZ33LJ7RUHj_h-qkAFL92bcVjtIdVa-UlsCw"", ""Interns!M:M""), ""Not Found"")"),"Contacted") -> Contacted | AL11: =IFERROR(__xludf.DUMMYFUNCTION("XLOOKUP(C11, IMPORTRANGE(""1RdEdgHYrZ33LJ7RUHj_h-qkAFL92bcVjtIdVa-UlsCw"", ""Interns!D:D""), IMPORTRANGE(""1RdEdgHYrZ33LJ7RUHj_h-qkAFL92bcVjtIdVa-UlsCw"", ""Interns!N:N""), ""Not Found"")"),"#Cheers4Careers") -> #Cheers4Careers | AM11: =IFERROR(__xludf.DUMMYFUNCTION("XLOOKUP(C11, IMPORTRANGE(""1RdEdgHYrZ33LJ7RUHj_h-qkAFL92bcVjtIdVa-UlsCw"", ""Interns!D:D""), IMPORTRANGE(""1RdEdgHYrZ33LJ7RUHj_h-qkAFL92bcVjtIdVa-UlsCw"", ""Interns!O:O""), ""Not Found"")"),"Hetal reached out by email 3/27 followed by text") -> Hetal reached out by email 3/27 followed by text | AO11: Lema Raufi | AP11: Sister | AQ11: Lema.raufi12@gmail.com | AR11: +17187992619
A12: Alum | B12: Unique | C12: =CONCATENATE(D12," ",E12) -> Mouhamed Samb | D12: Mouhamed | E12: Samb | F12: {=IFERROR( INDEX('Hub Interns 226'!A:A, MATCH(C12, 'Hub Interns 226'!B:B, 0)),"")} -> 899 | G12: {=IFERROR( INDEX('Hub Users 226'!A:A, MATCH(C12, 'Hub Users 226'!B:B, 0)),"")} -> 1332 | H12: 474 | I12: Health Sciences/Medicine | K12: Africa | L12: Male-identifying | M12: mouhamed.samb@ichsbronx.org | N12: 44362.576 | O12: 38101 | P12: =DATEDIF(O12, TODAY(), "Y") -> 22 | Q12: Updated date/time for AY 21-22 for Monday 3pm - PQ 9/27/21 | R12: W 181st Grand Ave | W12: Bronx | X12: NY | Y12: 9293321893 | Z12: ICHS-Bronx NY | AA12: ICHSBronx | AB12: 8 | AC12: FY | AE12: 21 - 22 | AF12: =IFERROR(__xludf.DUMMYFUNCTION("TEXTJOIN("", "", TRUE, FILTER(Champions!C:C, ISNUMBER(SEARCH(C12, Champions!W:W)) ) )"),"Dragana Glumac, Jannet Figueroa Gallardo, Sunkyung Park") -> Dragana Glumac, Jannet Figueroa Gallardo, Sunkyung Park | AH12: =IFERROR(__xludf.DUMMYFUNCTION("IF( ISNUMBER(MATCH( C12, IMPORTRANGE(""https://docs.google.com/spreadsheets/d/1yTh1ELC33JHYOeEdgIiEclxPRyh0zOKtlawDltfUay8"",""'Interns'!A:A""), 0 )), ""Outreach Conducted"", """")"),"") | AK12: =IFERROR(__xludf.DUMMYFUNCTION("XLOOKUP(C12, IMPORTRANGE(""1RdEdgHYrZ33LJ7RUHj_h-qkAFL92bcVjtIdVa-UlsCw"", ""Interns!D:D""), IMPORTRANGE(""1RdEdgHYrZ33LJ7RUHj_h-qkAFL92bcVjtIdVa-UlsCw"", ""Interns!M:M""), ""Not Found"")"),"Contacted") -> Contacted | AL12: =IFERROR(__xludf.DUMMYFUNCTION("XLOOKUP(C12, IMPORTRANGE(""1RdEdgHYrZ33LJ7RUHj_h-qkAFL92bcVjtIdVa-UlsCw"", ""Interns!D:D""), IMPORTRANGE(""1RdEdgHYrZ33LJ7RUHj_h-qkAFL92bcVjtIdVa-UlsCw"", ""Interns!N:N""), ""Not Found"")"),"#Cheers4Careers") -> #Cheers4Careers | AM12: =IFERROR(__xludf.DUMMYFUNCTION("XLOOKUP(C12, IMPORTRANGE(""1RdEdgHYrZ33LJ7RUHj_h-qkAFL92bcVjtIdVa-UlsCw"", ""Interns!D:D""), IMPORTRANGE(""1RdEdgHYrZ33LJ7RUHj_h-qkAFL92bcVjtIdVa-UlsCw"", ""Interns!O:O""), ""Not Found"")"),"Hetal reached out by email 3/27") -> Hetal reached out by email 3/27 | AO12: Ngouille Cisse | AP12: Mother | AQ12: cisse55443@hotmail.com | AR12: +19178701932
A13: Alum | B13: Unique | C13: =CONCATENATE(D13," ",E13) -> Ina Hoxhaj | D13: Ina | E13: Hoxhaj | F13: {=IFERROR( INDEX('Hub Interns 226'!A:A, MATCH(C13, 'Hub Interns 226'!B:B, 0)),"")} -> 1376 | G13: {=IFERROR( INDEX('Hub Users 226'!A:A, MATCH(C13, 'Hub Users 226'!B:B, 0)),"")} -> 1905 | H13: 1774 | I13: Architecture | J13: Albania | K13: Europe | L13: Female-identifying | M13: 2025_inahoxhaj@ihs-us.org | N13: 45312.759 | O13: 39323 | P13: =DATEDIF(O13, TODAY(), "Y") -> 18 | Q13: Ina Hoxhaj: &#34;I can to the United States from Albania when I was 15 years old. I am interested in architecture. I describe myself as creative, thoughtful, patient.&#34; She is also interested in business and is still exploring her options for colleges. Ina , we matched you based on your interest in business. Additional Email - hoxhajina29@gmail.com | R13: 235 E 84th St apt 33 New York, New York 10028 United States | S13: 12 | T13: 28 | U13: 76 | V13: 5 | W13: New York | X13: NY | Z13: IHS - Union Square NY | AA13: IHSUnionSquare | AB13: 2 | AC13: FY | AE13: 23 - 24 | AF13: =IFERROR(__xludf.DUMMYFUNCTION("TEXTJOIN("", "", TRUE, FILTER(Champions!C:C, ISNUMBER(SEARCH(C13, Champions!W:W)) ) )"),"Frances Tseng, Saima Malik, Saima Malik (D)") -> Frances Tseng, Saima Malik, Saima Malik (D) | AH13: =IFERROR(__xludf.DUMMYFUNCTION("IF( ISNUMBER(MATCH( C13, IMPORTRANGE(""https://docs.google.com/spreadsheets/d/1yTh1ELC33JHYOeEdgIiEclxPRyh0zOKtlawDltfUay8"",""'Interns'!A:A""), 0 )), ""Outreach Conducted"", """")"),"") | AJ13: “SPEAKHIRE’s Foundation Year Program was the best fit for me since I researched much about it, and everyone who commented said how much this internship helped them choose the best career fit—just as it did for me. My Champion was very nice, understandable, and made us very comfortable during the sessions. I learned much about her career that would help me everywhere I go. I had two careers in mind, and the champion that SPEAKHIRE chose for me gave useful advice for both. I enjoyed every session; it was a great opportunity for anyone who is unsure about their future. Everything was clear, enjoyable, and I’m totally glad and grateful for this experience.” | AK13: =IFERROR(__xludf.DUMMYFUNCTION("XLOOKUP(C13, IMPORTRANGE(""1RdEdgHYrZ33LJ7RUHj_h-qkAFL92bcVjtIdVa-UlsCw"", ""Interns!D:D""), IMPORTRANGE(""1RdEdgHYrZ33LJ7RUHj_h-qkAFL92bcVjtIdVa-UlsCw"", ""Interns!M:M""), ""Not Found"")"),"Contacted") -> Contacted | AL13: =IFERROR(__xludf.DUMMYFUNCTION("XLOOKUP(C13, IMPORTRANGE(""1RdEdgHYrZ33LJ7RUHj_h-qkAFL92bcVjtIdVa-UlsCw"", ""Interns!D:D""), IMPORTRANGE(""1RdEdgHYrZ33LJ7RUHj_h-qkAFL92bcVjtIdVa-UlsCw"", ""Interns!N:N""), ""Not Found"")"),"#Cheers4Careers") -> #Cheers4Careers | AM13: =IFERROR(__xludf.DUMMYFUNCTION("XLOOKUP(C13, IMPORTRANGE(""1RdEdgHYrZ33LJ7RUHj_h-qkAFL92bcVjtIdVa-UlsCw"", ""Interns!D:D""), IMPORTRANGE(""1RdEdgHYrZ33LJ7RUHj_h-qkAFL92bcVjtIdVa-UlsCw"", ""Interns!O:O""), ""Not Found"")"),"Ousmane reached out by email 3/26 and reach out by text 3/28") -> Ousmane reached out by email 3/26 and reach out by text 3/28 | AO13: Sebastjan Tinaj | AP13: Brother in law | AQ13: sebastjantinaj93@gmail.com | AR13: +1(845)287-3868
A14: Alum | B14: Unique | C14: =CONCATENATE(D14," ",E14) -> Lylia Belbegra | D14: Lylia | E14: Belbegra | F14: {=IFERROR( INDEX('Hub Interns 226'!A:A, MATCH(C14, 'Hub Interns 226'!B:B, 0)),"")} -> 809 | G14: {=IFERROR( INDEX('Hub Users 226'!A:A, MATCH(C14, 'Hub Users 226'!B:B, 0)),"")} -> 1242 | H14: 62 | I14: Entertainment/Lifestyle | J14: Algeria | K14: Africa | L14: Female-identifying | M14: lylia.belbegra@gmail.com | N14: 43741.631 | O14: 37257 | P14: =DATEDIF(O14, TODAY(), "Y") -> 24 | Q14: Bio as of 4/24/2020: Hi, I'm Lylia , a senior at George Washington High School. I am interested in being a dermatologist and beauty entrepreneur. I choose to do both because I always wanted to be a doctor but I also love makeup so I decided to combine both. I want to create my own skincare line and organic makeup that can be customized for different skin types and when being a dermatologist people with skin problems will come I will present them my skincare line and I will be able to customize them the perfect remedy for acne scars or something else | R14: 2435 Tremont Street Apt. B, Philadelphia, PA | W14: Philadelphia | X14: PA | Y14: 215-251-4142 | Z14: George Washington High School Philadelphia | AA14: GWHS | AB14: Philadelphia City Council District 10 | AC14: FY, EY | AD14: Yes | AE14: 17-18, 19 - 20 | AF14: =IFERROR(__xludf.DUMMYFUNCTION("TEXTJOIN("", "", TRUE, FILTER(Champions!C:C, ISNUMBER(SEARCH(C14, Champions!W:W)) ) )"),"Roopa Kohli") -> Roopa Kohli | AG14: Summit/Soiree 2023, ICAN | AH14: =IFERROR(__xludf.DUMMYFUNCTION("IF( ISNUMBER(MATCH( C14, IMPORTRANGE(""https://docs.google.com/spreadsheets/d/1yTh1ELC33JHYOeEdgIiEclxPRyh0zOKtlawDltfUay8"",""'Interns'!A:A""), 0 )), ""Outreach Conducted"", """")"),"Outreach Conducted") -> Outreach Conducted | AK14: =IFERROR(__xludf.DUMMYFUNCTION("XLOOKUP(C14, IMPORTRANGE(""1RdEdgHYrZ33LJ7RUHj_h-qkAFL92bcVjtIdVa-UlsCw"", ""Interns!D:D""), IMPORTRANGE(""1RdEdgHYrZ33LJ7RUHj_h-qkAFL92bcVjtIdVa-UlsCw"", ""Interns!M:M""), ""Not Found"")"),"") | AL14: =IFERROR(__xludf.DUMMYFUNCTION("XLOOKUP(C14, IMPORTRANGE(""1RdEdgHYrZ33LJ7RUHj_h-qkAFL92bcVjtIdVa-UlsCw"", ""Interns!D:D""), IMPORTRANGE(""1RdEdgHYrZ33LJ7RUHj_h-qkAFL92bcVjtIdVa-UlsCw"", ""Interns!N:N""), ""Not Found"")"),"") | AM14: =IFERROR(__xludf.DUMMYFUNCTION("XLOOKUP(C14, IMPORTRANGE(""1RdEdgHYrZ33LJ7RUHj_h-qkAFL92bcVjtIdVa-UlsCw"", ""Interns!D:D""), IMPORTRANGE(""1RdEdgHYrZ33LJ7RUHj_h-qkAFL92bcVjtIdVa-UlsCw"", ""Interns!O:O""), ""Not Found"")"),"") | AO14: belyaci@hotmail.com | AP14: Mother | AQ14: belyaci@hotmail.com | AR14: 215-834-1269
A15: Inactive | B15: Unique | C15: =CONCATENATE(D15," ",E15) -> Yasir Sharifi | D15: Yasir | E15: Sharifi | F15: {=IFERROR( INDEX('Hub Interns 226'!A:A, MATCH(C15, 'Hub Interns 226'!B:B, 0)),"")} -> 1221 | G15: {=IFERROR( INDEX('Hub Users 226'!A:A, MATCH(C15, 'Hub Users 226'!B:B, 0)),"")} -> 1654 | H15: 893 | J15: Afghanistan | K15: Asia | L15: Male-identifying | M15: yasirsharifi05@gmail.com | N15: 44601.533 | O15: 38712 | P15: =DATEDIF(O15, TODAY(), "Y") -> 20 | Q15: He is on task all the time like her sister. | R15: 154-12 71st Ave Apt 86A | S15: 6 | T15: 16 | U15: 27 | V15: 24 | W15: Queens | X15: NY | Y15: +13473700295 | Z15: Flushing International High School NY | AA15: FlushingIHS | AB15: 20 | AC15: EL | AE15: 21 - 22 | AH15: =IFERROR(__xludf.DUMMYFUNCTION("IF( ISNUMBER(MATCH( C15, IMPORTRANGE(""https://docs.google.com/spreadsheets/d/1yTh1ELC33JHYOeEdgIiEclxPRyh0zOKtlawDltfUay8"",""'Interns'!A:A""), 0 )), ""Outreach Conducted"", """")"),"") | AK15: =IFERROR(__xludf.DUMMYFUNCTION("XLOOKUP(C15, IMPORTRANGE(""1RdEdgHYrZ33LJ7RUHj_h-qkAFL92bcVjtIdVa-UlsCw"", ""Interns!D:D""), IMPORTRANGE(""1RdEdgHYrZ33LJ7RUHj_h-qkAFL92bcVjtIdVa-UlsCw"", ""Interns!M:M""), ""Not Found"")"),"") | AL15: =IFERROR(__xludf.DUMMYFUNCTION("XLOOKUP(C15, IMPORTRANGE(""1RdEdgHYrZ33LJ7RUHj_h-qkAFL92bcVjtIdVa-UlsCw"", ""Interns!D:D""), IMPORTRANGE(""1RdEdgHYrZ33LJ7RUHj_h-qkAFL92bcVjtIdVa-UlsCw"", ""Interns!N:N""), ""Not Found"")"),"") | AM15: =IFERROR(__xludf.DUMMYFUNCTION("XLOOKUP(C15, IMPORTRANGE(""1RdEdgHYrZ33LJ7RUHj_h-qkAFL92bcVjtIdVa-UlsCw"", ""Interns!D:D""), IMPORTRANGE(""1RdEdgHYrZ33LJ7RUHj_h-qkAFL92bcVjtIdVa-UlsCw"", ""Interns!O:O""), ""Not Found"")"),"") | AO15: Sharifi | AP15: Father
